Workbook

Sheet Version-Level Changes
B2: v4: Yellow tabs represent changes listed below while the light orange tabs mean that changes may come or TBD
B3: - In the "INT Web" tab, maintaining the 2025-26 Start of Season pricing with the following exceptions:
C4: => Due to FX devaluation from inflation risk across many seasons, changing NBA.com currency for Argentina to USD from ARS - pricing now matches 2025-26 in-app and CED pricing (reported in USD)
C5: => To maximize revenue, increasing only League Pass Premium pricing (Monthly and SL / Annual) in Australia
C6: => Due to FX devaluation from inflation risk, increasing pricing for all packages in Nigeria by ~4% YoY
C7: => Due to FX devaluation from inflation risk, increasing pricing for all packages in Romania by ~13% YoY
C8: => Due to FX devaluation from inflation risk, increasing pricing for all packages in Turkey by ~45% YoY
B9: - In the "Student Plan Web" tab, added India pricing as it's being sold in a new market for Student Plans in the 2026-27 season
B10: - In the "Apple" tab, increasing prices across subscription and/or transactional packages to match the changes seen in the "INT Web" tab for Australia, Nigeria, Romania, and Turkey
C11: => Note: Price increases for existing in-app subscribers will occur around November. Thus, only new paying sign-ups will purchase at the higher prices.
B12: - In the "Google" tab, increased prices across subscription and/or transactional packages to match the changes seen in the "INT Web" tab for Australia, Cameroon, Cote D'Ivoire, Nigeria, Romania, Senegal, and Turkey
C13: => Note: Price increases for existing in-app subscribers will occur around November. Thus, only new paying sign-ups will purchase at the higher prices.
B14: - In the "AMZN Fire TV" tab, increasing only League Pass Premium pricing (Monthly and Annual) in Australia
C15: => Note: Price increases for existing in-app subscribers will occur around November. Thus, only new paying sign-ups will purchase at the higher prices.
B16: - In the "Samsung" tab, increasing prices across Australia (LPP Only), Nigeria, and Turkey
C17: => Note: Price increases for existing in-app subscribers will occur around November. Thus, only new paying sign-ups will purchase at the higher prices.
B18: - In the "Country-Level Tactics" tab, added country-level tactics across pricing, offers, and BFCM for the Monetization team's reference
B19: - In the "Addt'l Payment Methods" tab, Kenny made the following updates ahead of the 2026-27 season: Added Klarna Pay Now in Finland and United Kingdom; Venmo in the U.S.
B20: - In the "Intro Offer Details" tab, updated introductory pricing to 30% off (from 35% off) for Annual (Pay Up Front) subscriptions across both the Apple and Google platforms
B21: - In the "Post-AR Web Cancel Deflection" tab, (i) identified the global SL save offer turn off date as 8/27/26, and (ii), in select markets only, adjusted monthly save offers from pause to 100% off next month
B22: - In the "Cancel Deflection - Apple" tab, updated certain markets (e.g., United States) to remove save offers (feasibility of doing this by market is an open question with Chelsea and Apple)
B23: - In the "Winback - Apple" tab, turned back on offers from 10.01 to 10.15; offers are 15% off all SKUs for select markets only (will remain off in others)
B24: - In the "Winback - Google" tab, turned back on offers from 10.01 to 10.15; offers are 15% off all SKUs for select markets only (will remain off in others)
B26: v5: Yellow tabs represent changes listed below while the light orange tabs mean that changes may come or TBD
B27: v6 will include the TBU changes that are highlighted in light orange above
B28: - In all Apple-related tabs, added the three-digit country code
B30: v6
B31: - In all tabs that showcase country x region mapping, updated French Guiana, Guadeloupe, Martinique, Mayotte, and Reunion to Africa (from what originally was LatAm or Africa)
... B41: '- Accurately depicted Bulgaria's currency from USD to EUR - no changes to pricing in absolute terms, just the currency change

Sheet SKU & Platform Availability ->

Sheet DOM
B2: Country | C2: Region | D2: BLPEUS | E2: BLPEUSMONTHLY | F2: BLPPUS | G2: BLPPUSMONTHLY | H2: BTCUS | I2: BTCUSMONTHLY | J2: BLPTV | K2: BLPTVMONTHLY | L2: GSINGLEGAMEUS | M2: GSINGLEGAMEUSA | N2: GSINGLEGAMEUSB | O2: GSINGLEGAMEUSC | P2: BLPAUDIO
B3: United States | C3: Domestic | D3: Web & IAP | E3: Web & IAP | F3: Web & IAP | G3: Web & IAP | H3: Web | I3: Web | J3: Web | K3: Web | L3: IAP | M3: IAP | N3: IAP | O3: IAP | P3: Web
B4: Guam | C4: Domestic | D4: =+D3 -> Web & IAP | E4: =+E3 -> Web & IAP | F4: =+F3 -> Web & IAP | G4: =+G3 -> Web & IAP | H4: =+H3 -> Web | I4: =+I3 -> Web | J4: =+J3 -> Web | K4: =+K3 -> Web | ... P4: =+P3 -> Web
B5: Puerto Rico | C5: Domestic | D5: =+D4 -> Web & IAP | E5: =+E4 -> Web & IAP | F5: =+F4 -> Web & IAP | G5: =+G4 -> Web & IAP | H5: =+H4 -> Web | I5: =+I4 -> Web | J5: =+J4 -> Web | K5: =+K4 -> Web | ... P5: =+P4 -> Web
B6: US Virgin Islands | C6: Domestic | D6: =+D5 -> Web & IAP | E6: =+E5 -> Web & IAP | F6: =+F5 -> Web & IAP | G6: =+G5 -> Web & IAP | H6: =+H5 -> Web | I6: =+I5 -> Web | J6: =+J5 -> Web | K6: =+K5 -> Web | ... P6: =+P5 -> Web
B7: US Minor Outlying Islands | C7: Domestic | D7: =+D6 -> Web & IAP | E7: =+E6 -> Web & IAP | F7: =+F6 -> Web & IAP | G7: =+G6 -> Web & IAP | H7: =+H6 -> Web | I7: =+I6 -> Web | J7: =+J6 -> Web | K7: =+K6 -> Web | ... P7: =+P6 -> Web

Sheet INT
B2: Country | C2: Region | D2: BLPE | E2: BLPEMONTHLY | F2: BLPP | G2: BLPPMONTHLY | H2: BTC | I2: BTCMONTHLY | J2: GSINGLEGAME | K2: GSINGLEGAMEA | L2: GSINGLEGAMEB | M2: GSINGLEGAMEC | N2: BLPE1C | O2: BLPE2C | P2: BLPE3C | Q2: Apple | R2: Google
B3: Afghanistan | C3: =+VLOOKUP($B3,'[2]Pricing Scenario - Maintain'!$B$4:$AM$238,2,FALSE) -> Asia | D3: Web & IAP | E3: Web & IAP | F3: Web & IAP | G3: Web & IAP | H3: Web | I3: Web | J3: IAP | K3: IAP | L3: IAP | M3: IAP | N3: Web | O3: Web | P3: Web | Q3: =+IFERROR(VLOOKUP(B3,[2]Apple!$B$3:$C$173,2,FALSE),"") -> AF | R3: =+IFERROR(VLOOKUP(B3,[2]Google!$B$3:$C$99,2,FALSE),"")
B4: Aland Islands | C4: =+VLOOKUP($B4,'[2]Pricing Scenario - Maintain'!$B$4:$AM$238,2,FALSE) -> Europe | D4: Web / IAP | E4: Web / IAP | F4: Web / IAP | G4: Web / IAP | H4: Web | I4: Web | J4: IAP | K4: IAP | L4: IAP | M4: IAP | N4: Web | O4: Web | P4: Web | Q4: =+IFERROR(VLOOKUP(B4,[2]Apple!$B$3:$C$173,2,FALSE),"") | R4: =+IFERROR(VLOOKUP(B4,[2]Google!$B$3:$C$99,2,FALSE),"")
B5: Albania | C5: =+VLOOKUP($B5,'[2]Pricing Scenario - Maintain'!$B$4:$AM$238,2,FALSE) -> Europe | D5: Web & IAP | E5: Web & IAP | F5: Web & IAP | G5: Web & IAP | H5: Web | I5: Web | J5: IAP | K5: IAP | L5: IAP | M5: IAP | N5: Web | O5: Web | P5: Web | Q5: =+IFERROR(VLOOKUP(B5,[2]Apple!$B$3:$C$173,2,FALSE),"") -> AL | R5: =+IFERROR(VLOOKUP(B5,[2]Google!$B$3:$C$99,2,FALSE),"") -> AL
B6: Algeria | C6: =+VLOOKUP($B6,'[2]Pricing Scenario - Maintain'!$B$4:$AM$238,2,FALSE) -> Africa | D6: Web & IAP | E6: Web & IAP | F6: Web & IAP | G6: Web & IAP | H6: Web | I6: Web | J6: IAP | K6: IAP | L6: IAP | M6: IAP | N6: Web | O6: Web | P6: Web | Q6: =+IFERROR(VLOOKUP(B6,[2]Apple!$B$3:$C$173,2,FALSE),"") -> DZ | R6: =+IFERROR(VLOOKUP(B6,[2]Google!$B$3:$C$99,2,FALSE),"") -> DZ
B7: American Samoa | C7: =+VLOOKUP($B7,'[2]Pricing Scenario - Maintain'!$B$4:$AM$238,2,FALSE) -> Asia | D7: Web / IAP | E7: Web / IAP | F7: Web / IAP | G7: Web / IAP | H7: Web | I7: Web | J7: IAP | K7: IAP | L7: IAP | M7: IAP | N7: Web | O7: Web | P7: Web | Q7: =+IFERROR(VLOOKUP(B7,[2]Apple!$B$3:$C$173,2,FALSE),"") | R7: =+IFERROR(VLOOKUP(B7,[2]Google!$B$3:$C$99,2,FALSE),"")
B8: Andorra | C8: =+VLOOKUP($B8,'[2]Pricing Scenario - Maintain'!$B$4:$AM$238,2,FALSE) -> Europe | D8: Web / IAP | E8: Web / IAP | F8: Web / IAP | G8: Web / IAP | H8: Web | I8: Web | J8: IAP | K8: IAP | L8: IAP | M8: IAP | N8: Web | O8: Web | P8: Web | Q8: =+IFERROR(VLOOKUP(B8,[2]Apple!$B$3:$C$173,2,FALSE),"") | R8: =+IFERROR(VLOOKUP(B8,[2]Google!$B$3:$C$99,2,FALSE),"")
B9: Angola | C9: =+VLOOKUP($B9,'[2]Pricing Scenario - Maintain'!$B$4:$AM$238,2,FALSE) -> Africa | D9: Web & IAP | E9: Web & IAP | F9: Web & IAP | G9: Web & IAP | H9: Web | I9: Web | J9: IAP | K9: IAP | L9: IAP | M9: IAP | N9: Web | O9: Web | P9: Web | Q9: =+IFERROR(VLOOKUP(B9,[2]Apple!$B$3:$C$173,2,FALSE),"") -> AO | R9: =+IFERROR(VLOOKUP(B9,[2]Google!$B$3:$C$99,2,FALSE),"") -> AO
B10: Anguilla | C10: =+VLOOKUP($B10,'[2]Pricing Scenario - Maintain'!$B$4:$AM$238,2,FALSE) -> Latin America | D10: Web & IAP | E10: Web & IAP | F10: Web & IAP | G10: Web & IAP | H10: Web | I10: Web | J10: IAP | K10: IAP | L10: IAP | M10: IAP | N10: Web | O10: Web | P10: Web | Q10: =+IFERROR(VLOOKUP(B10,[2]Apple!$B$3:$C$173,2,FALSE),"") -> AI | R10: =+IFERROR(VLOOKUP(B10,[2]Google!$B$3:$C$99,2,FALSE),"")
B11: Antarctica | C11: =+VLOOKUP($B11,'[2]Pricing Scenario - Maintain'!$B$4:$AM$238,2,FALSE) -> Europe | D11: Web / IAP | E11: Web / IAP | F11: Web / IAP | G11: Web / IAP | H11: Web | I11: Web | J11: IAP | K11: IAP | L11: IAP | M11: IAP | N11: Web | O11: Web | P11: Web | Q11: =+IFERROR(VLOOKUP(B11,[2]Apple!$B$3:$C$173,2,FALSE),"") | R11: =+IFERROR(VLOOKUP(B11,[2]Google!$B$3:$C$99,2,FALSE),"")
B12: Antigua And Barbuda | C12: =+VLOOKUP($B12,'[2]Pricing Scenario - Maintain'!$B$4:$AM$238,2,FALSE) -> Latin America | D12: Web & IAP | E12: Web & IAP | F12: Web & IAP | G12: Web & IAP | H12: Web | I12: Web | J12: IAP | K12: IAP | L12: IAP | M12: IAP | N12: Web | O12: Web | P12: Web | Q12: =+IFERROR(VLOOKUP(B12,[2]Apple!$B$3:$C$173,2,FALSE),"") -> AG | R12: =+IFERROR(VLOOKUP(B12,[2]Google!$B$3:$C$99,2,FALSE),"") -> AG
B13: Argentina | C13: =+VLOOKUP($B13,'[2]Pricing Scenario - Maintain'!$B$4:$AM$238,2,FALSE) -> Latin America | D13: Web & IAP | E13: Web & IAP | F13: Web & IAP | G13: Web & IAP | H13: Web | I13: Web | J13: IAP | K13: IAP | L13: IAP | M13: IAP | N13: Web | O13: Web | P13: Web | Q13: =+IFERROR(VLOOKUP(B13,[2]Apple!$B$3:$C$173,2,FALSE),"") -> AR | R13: =+IFERROR(VLOOKUP(B13,[2]Google!$B$3:$C$99,2,FALSE),"") -> AR
B14: Armenia | C14: =+VLOOKUP($B14,'[2]Pricing Scenario - Maintain'!$B$4:$AM$238,2,FALSE) -> Middle East | D14: Web & IAP | E14: Web & IAP | F14: Web & IAP | G14: Web & IAP | H14: Web | I14: Web | J14: IAP | K14: IAP | L14: IAP | M14: IAP | N14: Web | O14: Web | P14: Web | Q14: =+IFERROR(VLOOKUP(B14,[2]Apple!$B$3:$C$173,2,FALSE),"") -> AM | R14: =+IFERROR(VLOOKUP(B14,[2]Google!$B$3:$C$99,2,FALSE),"") -> AM
... B22: Barbados | C22: =+VLOOKUP($B22,'[2]Pricing Scenario - Maintain'!$B$4:$AM$238,2,FALSE) -> Latin America | D22: Web & IAP | E22: Web & IAP | F22: Web & IAP | G22: Web & IAP | H22: Web | I22: Web | J22: IAP | K22: IAP | L22: IAP | M22: IAP | N22: Web | O22: Web | P22: Web | Q22: =+IFERROR(VLOOKUP(B22,[2]Apple!$B$3:$C$173,2,FALSE),"") -> BB | R22: =+IFERROR(VLOOKUP(B22,[2]Google!$B$3:$C$99,2,FALSE),"")
B23: Belarus | C23: =+VLOOKUP($B23,'[2]Pricing Scenario - Maintain'!$B$4:$AM$238,2,FALSE) -> Europe | Q23: =+IFERROR(VLOOKUP(B23,[2]Apple!$B$3:$C$173,2,FALSE),"") -> BY | R23: =+IFERROR(VLOOKUP(B23,[2]Google!$B$3:$C$99,2,FALSE),"") -> BY
B24: Belgium | C24: =+VLOOKUP($B24,'[2]Pricing Scenario - Maintain'!$B$4:$AM$238,2,FALSE) -> Europe | D24: Web & IAP | E24: Web & IAP | F24: Web & IAP | G24: Web & IAP | H24: Web | I24: Web | J24: IAP | K24: IAP | L24: IAP | M24: IAP | N24: Web | O24: Web | P24: Web | Q24: =+IFERROR(VLOOKUP(B24,[2]Apple!$B$3:$C$173,2,FALSE),"") -> BE | R24: =+IFERROR(VLOOKUP(B24,[2]Google!$B$3:$C$99,2,FALSE),"") -> BE
B25: Belize | C25: =+VLOOKUP($B25,'[2]Pricing Scenario - Maintain'!$B$4:$AM$238,2,FALSE) -> Latin America | D25: Web & IAP | E25: Web & IAP | F25: Web & IAP | G25: Web & IAP | H25: Web | I25: Web | J25: IAP | K25: IAP | L25: IAP | M25: IAP | N25: Web | O25: Web | P25: Web | Q25: =+IFERROR(VLOOKUP(B25,[2]Apple!$B$3:$C$173,2,FALSE),"") -> BZ | R25: =+IFERROR(VLOOKUP(B25,[2]Google!$B$3:$C$99,2,FALSE),"") -> BZ
B26: Benin | C26: =+VLOOKUP($B26,'[2]Pricing Scenario - Maintain'!$B$4:$AM$238,2,FALSE) -> Africa | D26: Web & IAP | E26: Web & IAP | F26: Web & IAP | G26: Web & IAP | H26: Web | I26: Web | J26: IAP | K26: IAP | L26: IAP | M26: IAP | N26: Web | O26: Web | P26: Web | Q26: =+IFERROR(VLOOKUP(B26,[2]Apple!$B$3:$C$173,2,FALSE),"") -> BJ | R26: =+IFERROR(VLOOKUP(B26,[2]Google!$B$3:$C$99,2,FALSE),"") -> BJ
B27: Bermuda | C27: Latin America | D27: Web & IAP | E27: Web & IAP | F27: Web & IAP | G27: Web & IAP | H27: Web | I27: Web | J27: IAP | K27: IAP | L27: IAP | M27: IAP | N27: Web | O27: Web | P27: Web | Q27: =+IFERROR(VLOOKUP(B27,[2]Apple!$B$3:$C$173,2,FALSE),"") -> BM | R27: =+IFERROR(VLOOKUP(B27,[2]Google!$B$3:$C$99,2,FALSE),"") -> BM
B28: Bhutan | C28: =+VLOOKUP($B28,'[2]Pricing Scenario - Maintain'!$B$4:$AM$238,2,FALSE) -> Asia | D28: Web & IAP | E28: Web & IAP | F28: Web & IAP | G28: Web & IAP | H28: Web | I28: Web | J28: IAP | K28: IAP | L28: IAP | M28: IAP | N28: Web | O28: Web | P28: Web | Q28: =+IFERROR(VLOOKUP(B28,[2]Apple!$B$3:$C$173,2,FALSE),"") -> BT | R28: =+IFERROR(VLOOKUP(B28,[2]Google!$B$3:$C$99,2,FALSE),"")
B29: Bolivia | C29: Latin America | D29: Web & IAP | E29: Web & IAP | F29: Web & IAP | G29: Web & IAP | H29: Web | I29: Web | J29: IAP | K29: IAP | L29: IAP | M29: IAP | N29: Web | O29: Web | P29: Web | Q29: =+IFERROR(VLOOKUP(B29,[2]Apple!$B$3:$C$173,2,FALSE),"") -> BO | R29: =+IFERROR(VLOOKUP(B29,[2]Google!$B$3:$C$99,2,FALSE),"") -> BO
B30: Bonaire, St. Eustatius, & Saba | C30: Europe | D30: Web / IAP | E30: Web / IAP | F30: Web / IAP | G30: Web / IAP | H30: Web | I30: Web | J30: IAP | K30: IAP | L30: IAP | M30: IAP | N30: Web | O30: Web | P30: Web | Q30: =+IFERROR(VLOOKUP(B30,[2]Apple!$B$3:$C$173,2,FALSE),"") | R30: =+IFERROR(VLOOKUP(B30,[2]Google!$B$3:$C$99,2,FALSE),"")
B31: Bosnia And Herzegovina | C31: =+VLOOKUP($B31,'[2]Pricing Scenario - Maintain'!$B$4:$AM$238,2,FALSE) -> Europe | D31: Web & IAP | E31: Web & IAP | F31: Web & IAP | G31: Web & IAP | H31: Web | I31: Web | J31: IAP | K31: IAP | L31: IAP | M31: IAP | N31: Web | O31: Web | P31: Web | Q31: =+IFERROR(VLOOKUP(B31,[2]Apple!$B$3:$C$173,2,FALSE),"") -> BA | R31: =+IFERROR(VLOOKUP(B31,[2]Google!$B$3:$C$99,2,FALSE),"") -> BA
B32: Botswana | C32: =+VLOOKUP($B32,'[2]Pricing Scenario - Maintain'!$B$4:$AM$238,2,FALSE) -> Africa | D32: Web & IAP | E32: Web & IAP | F32: Web & IAP | G32: Web & IAP | H32: Web | I32: Web | J32: IAP | K32: IAP | L32: IAP | M32: IAP | N32: Web | O32: Web | P32: Web | Q32: =+IFERROR(VLOOKUP(B32,[2]Apple!$B$3:$C$173,2,FALSE),"") -> BW | R32: =+IFERROR(VLOOKUP(B32,[2]Google!$B$3:$C$99,2,FALSE),"") -> BW
B33: Bouvet Island | C33: =+VLOOKUP($B33,'[2]Pricing Scenario - Maintain'!$B$4:$AM$238,2,FALSE) -> Europe | D33: Web / IAP | E33: Web / IAP | F33: Web / IAP | G33: Web / IAP | H33: Web | I33: Web | J33: IAP | K33: IAP | L33: IAP | M33: IAP | N33: Web | O33: Web | P33: Web | Q33: =+IFERROR(VLOOKUP(B33,[2]Apple!$B$3:$C$173,2,FALSE),"") | R33: =+IFERROR(VLOOKUP(B33,[2]Google!$B$3:$C$99,2,FALSE),"")
B34: Brazil | C34: =+VLOOKUP($B34,'[2]Pricing Scenario - Maintain'!$B$4:$AM$238,2,FALSE) -> Latin America | D34: Web & IAP | E34: Web & IAP | F34: Web & IAP | G34: Web & IAP | H34: Web | I34: Web | J34: IAP | K34: IAP | L34: IAP | M34: IAP | N34: Web | O34: Web | P34: Web | Q34: =+IFERROR(VLOOKUP(B34,[2]Apple!$B$3:$C$173,2,FALSE),"") -> BR | R34: =+IFERROR(VLOOKUP(B34,[2]Google!$B$3:$C$99,2,FALSE),"") -> BR
B35: British Indian Ocean Territory | C35: =+VLOOKUP($B35,'[2]Pricing Scenario - Maintain'!$B$4:$AM$238,2,FALSE) -> Asia | D35: Web / IAP | E35: Web / IAP | F35: Web / IAP | G35: Web / IAP | H35: Web | I35: Web | J35: IAP | K35: IAP | L35: IAP | M35: IAP | N35: Web | O35: Web | P35: Web | Q35: =+IFERROR(VLOOKUP(B35,[2]Apple!$B$3:$C$173,2,FALSE),"") | R35: =+IFERROR(VLOOKUP(B35,[2]Google!$B$3:$C$99,2,FALSE),"")
B36: British Virgin Islands | C36: =+VLOOKUP($B36,'[2]Pricing Scenario - Maintain'!$B$4:$AM$238,2,FALSE) -> Latin America | D36: Web & IAP | E36: Web & IAP | F36: Web & IAP | G36: Web & IAP | H36: Web | I36: Web | J36: IAP | K36: IAP | L36: IAP | M36: IAP | N36: Web | O36: Web | P36: Web | Q36: =+IFERROR(VLOOKUP(B36,[2]Apple!$B$3:$C$173,2,FALSE),"") -> VG | R36: =+IFERROR(VLOOKUP(B36,[2]Google!$B$3:$C$99,2,FALSE),"") -> VG
B37: Brunei | C37: =+VLOOKUP($B37,'[2]Pricing Scenario - Maintain'!$B$4:$AM$238,2,FALSE) -> Asia | D37: Web & IAP | E37: Web & IAP | F37: Web & IAP | G37: Web & IAP | H37: Web | I37: Web | J37: IAP | K37: IAP | L37: IAP | M37: IAP | N37: Web | O37: Web | P37: Web | Q37: =+IFERROR(VLOOKUP(B37,[2]Apple!$B$3:$C$173,2,FALSE),"") -> BN | R37: =+IFERROR(VLOOKUP(B37,[2]Google!$B$3:$C$99,2,FALSE),"")
B38: Bulgaria | C38: =+VLOOKUP($B38,'[2]Pricing Scenario - Maintain'!$B$4:$AM$238,2,FALSE) -> Europe | D38: Web & IAP | E38: Web & IAP | F38: Web & IAP | G38: Web & IAP | H38: Web | I38: Web | J38: IAP | K38: IAP | L38: IAP | M38: IAP | N38: Web | O38: Web | P38: Web | Q38: =+IFERROR(VLOOKUP(B38,[2]Apple!$B$3:$C$173,2,FALSE),"") -> BG | R38: =+IFERROR(VLOOKUP(B38,[2]Google!$B$3:$C$99,2,FALSE),"") -> BG
B39: Burkina Faso | C39: =+VLOOKUP($B39,'[2]Pricing Scenario - Maintain'!$B$4:$AM$238,2,FALSE) -> Africa | D39: Web & IAP | E39: Web & IAP | F39: Web & IAP | G39: Web & IAP | H39: Web | I39: Web | J39: IAP | K39: IAP | L39: IAP | M39: IAP | N39: Web | O39: Web | P39: Web | Q39: =+IFERROR(VLOOKUP(B39,[2]Apple!$B$3:$C$173,2,FALSE),"") -> BF | R39: =+IFERROR(VLOOKUP(B39,[2]Google!$B$3:$C$99,2,FALSE),"") -> BF
B40: Burundi | C40: =+VLOOKUP($B40,'[2]Pricing Scenario - Maintain'!$B$4:$AM$238,2,FALSE) -> Africa | D40: Web / IAP | E40: Web / IAP | F40: Web / IAP | G40: Web / IAP | H40: Web | I40: Web | J40: IAP | K40: IAP | L40: IAP | M40: IAP | N40: Web | O40: Web | P40: Web | Q40: =+IFERROR(VLOOKUP(B40,[2]Apple!$B$3:$C$173,2,FALSE),"") | R40: =+IFERROR(VLOOKUP(B40,[2]Google!$B$3:$C$99,2,FALSE),"")
B41: Cambodia | C41: =+VLOOKUP($B41,'[2]Pricing Scenario - Maintain'!$B$4:$AM$238,2,FALSE) -> Asia | D41: Web & IAP | E41: Web & IAP | F41: Web & IAP | G41: Web & IAP | H41: Web | I41: Web | J41: IAP | K41: IAP | L41: IAP | M41: IAP | N41: Web | O41: Web | P41: Web | Q41: =+IFERROR(VLOOKUP(B41,[2]Apple!$B$3:$C$173,2,FALSE),"") -> KH | R41: =+IFERROR(VLOOKUP(B41,[2]Google!$B$3:$C$99,2,FALSE),"") -> KH
B42: Cameroon | C42: =+VLOOKUP($B42,'[2]Pricing Scenario - Maintain'!$B$4:$AM$238,2,FALSE) -> Africa | D42: Web & IAP | E42: Web & IAP | F42: Web & IAP | G42: Web & IAP | H42: Web | I42: Web | J42: IAP | K42: IAP | L42: IAP | M42: IAP | N42: Web | O42: Web | P42: Web | Q42: =+IFERROR(VLOOKUP(B42,[2]Apple!$B$3:$C$173,2,FALSE),"") -> CM | R42: =+IFERROR(VLOOKUP(B42,[2]Google!$B$3:$C$99,2,FALSE),"") -> CM
... B78: France | C78: =+VLOOKUP($B78,'[2]Pricing Scenario - Maintain'!$B$4:$AM$238,2,FALSE) -> Europe | D78: Web & IAP | E78: Web & IAP | F78: Web & IAP | G78: Web & IAP | H78: Web | I78: Web | J78: IAP | K78: IAP | L78: IAP | M78: IAP | N78: Web | O78: Web | P78: Web | Q78: =+IFERROR(VLOOKUP(B78,[2]Apple!$B$3:$C$173,2,FALSE),"") -> FR | R78: =+IFERROR(VLOOKUP(B78,[2]Google!$B$3:$C$99,2,FALSE),"") -> FR
B79: French Guiana | C79: Europe | D79: Web / IAP | E79: Web / IAP | F79: Web / IAP | G79: Web / IAP | H79: Web | I79: Web | J79: IAP | K79: IAP | L79: IAP | M79: IAP | N79: Web | O79: Web | P79: Web | Q79: =+IFERROR(VLOOKUP(B79,[2]Apple!$B$3:$C$173,2,FALSE),"") | R79: =+IFERROR(VLOOKUP(B79,[2]Google!$B$3:$C$99,2,FALSE),"")
B80: French Polynesia | C80: =+VLOOKUP($B80,'[2]Pricing Scenario - Maintain'!$B$4:$AM$238,2,FALSE) -> Asia | D80: Web / IAP | E80: Web / IAP | F80: Web / IAP | G80: Web / IAP | H80: Web | I80: Web | J80: IAP | K80: IAP | L80: IAP | M80: IAP | N80: Web | O80: Web | P80: Web | Q80: =+IFERROR(VLOOKUP(B80,[2]Apple!$B$3:$C$173,2,FALSE),"") | R80: =+IFERROR(VLOOKUP(B80,[2]Google!$B$3:$C$99,2,FALSE),"")
B81: French Southern Territories | C81: =+VLOOKUP($B81,'[2]Pricing Scenario - Maintain'!$B$4:$AM$238,2,FALSE) -> Europe | D81: Web / IAP | E81: Web / IAP | F81: Web / IAP | G81: Web / IAP | H81: Web | I81: Web | J81: IAP | K81: IAP | L81: IAP | M81: IAP | N81: Web | O81: Web | P81: Web | Q81: =+IFERROR(VLOOKUP(B81,[2]Apple!$B$3:$C$173,2,FALSE),"") | R81: =+IFERROR(VLOOKUP(B81,[2]Google!$B$3:$C$99,2,FALSE),"")
B82: Gabon | C82: =+VLOOKUP($B82,'[2]Pricing Scenario - Maintain'!$B$4:$AM$238,2,FALSE) -> Africa | D82: Web & IAP | E82: Web & IAP | F82: Web & IAP | G82: Web & IAP | H82: Web | I82: Web | J82: IAP | K82: IAP | L82: IAP | M82: IAP | N82: Web | O82: Web | P82: Web | Q82: =+IFERROR(VLOOKUP(B82,[2]Apple!$B$3:$C$173,2,FALSE),"") -> GA | R82: =+IFERROR(VLOOKUP(B82,[2]Google!$B$3:$C$99,2,FALSE),"") -> GA
B83: Gambia | C83: =+VLOOKUP($B83,'[2]Pricing Scenario - Maintain'!$B$4:$AM$238,2,FALSE) -> Africa | D83: Web & IAP | E83: Web & IAP | F83: Web & IAP | G83: Web & IAP | H83: Web | I83: Web | J83: IAP | K83: IAP | L83: IAP | M83: IAP | N83: Web | O83: Web | P83: Web | Q83: =+IFERROR(VLOOKUP(B83,[2]Apple!$B$3:$C$173,2,FALSE),"") -> GM | R83: =+IFERROR(VLOOKUP(B83,[2]Google!$B$3:$C$99,2,FALSE),"") -> GM
B84: Georgia | C84: =+VLOOKUP($B84,'[2]Pricing Scenario - Maintain'!$B$4:$AM$238,2,FALSE) -> Middle East | D84: Web & IAP | E84: Web & IAP | F84: Web & IAP | G84: Web & IAP | H84: Web | I84: Web | J84: IAP | K84: IAP | L84: IAP | M84: IAP | N84: Web | O84: Web | P84: Web | Q84: =+IFERROR(VLOOKUP(B84,[2]Apple!$B$3:$C$173,2,FALSE),"") -> GE | R84: =+IFERROR(VLOOKUP(B84,[2]Google!$B$3:$C$99,2,FALSE),"") -> GE
B85: Germany | C85: =+VLOOKUP($B85,'[2]Pricing Scenario - Maintain'!$B$4:$AM$238,2,FALSE) -> Europe | D85: Web & IAP | E85: Web & IAP | F85: Web & IAP | G85: Web & IAP | H85: Web | I85: Web | J85: IAP | K85: IAP | L85: IAP | M85: IAP | N85: Web | O85: Web | P85: Web | Q85: =+IFERROR(VLOOKUP(B85,[2]Apple!$B$3:$C$173,2,FALSE),"") -> DE | R85: =+IFERROR(VLOOKUP(B85,[2]Google!$B$3:$C$99,2,FALSE),"") -> DE
B86: Ghana | C86: =+VLOOKUP($B86,'[2]Pricing Scenario - Maintain'!$B$4:$AM$238,2,FALSE) -> Africa | D86: Web & IAP | E86: Web & IAP | F86: Web & IAP | G86: Web & IAP | H86: Web | I86: Web | J86: IAP | K86: IAP | L86: IAP | M86: IAP | N86: Web | O86: Web | P86: Web | Q86: =+IFERROR(VLOOKUP(B86,[2]Apple!$B$3:$C$173,2,FALSE),"") -> GH | R86: =+IFERROR(VLOOKUP(B86,[2]Google!$B$3:$C$99,2,FALSE),"") -> GH
B87: Gibraltar | C87: =+VLOOKUP($B87,'[2]Pricing Scenario - Maintain'!$B$4:$AM$238,2,FALSE) -> Europe | D87: Web & IAP | E87: Web & IAP | F87: Web & IAP | G87: Web & IAP | H87: Web | I87: Web | J87: IAP | K87: IAP | L87: IAP | M87: IAP | N87: Web | O87: Web | P87: Web | Q87: =+IFERROR(VLOOKUP(B87,[2]Apple!$B$3:$C$173,2,FALSE),"") | R87: =+IFERROR(VLOOKUP(B87,[2]Google!$B$3:$C$99,2,FALSE),"") -> GI
B88: Greece | C88: =+VLOOKUP($B88,'[2]Pricing Scenario - Maintain'!$B$4:$AM$238,2,FALSE) -> Europe | D88: Web & IAP | E88: Web & IAP | F88: Web & IAP | G88: Web & IAP | H88: Web | I88: Web | J88: IAP | K88: IAP | L88: IAP | M88: IAP | N88: Web | O88: Web | P88: Web | Q88: =+IFERROR(VLOOKUP(B88,[2]Apple!$B$3:$C$173,2,FALSE),"") -> GR | R88: =+IFERROR(VLOOKUP(B88,[2]Google!$B$3:$C$99,2,FALSE),"") -> GR
B89: Greenland | C89: =+VLOOKUP($B89,'[2]Pricing Scenario - Maintain'!$B$4:$AM$238,2,FALSE) -> Europe | D89: Web / IAP | E89: Web / IAP | F89: Web / IAP | G89: Web / IAP | H89: Web | I89: Web | J89: IAP | K89: IAP | L89: IAP | M89: IAP | N89: Web | O89: Web | P89: Web | Q89: =+IFERROR(VLOOKUP(B89,[2]Apple!$B$3:$C$173,2,FALSE),"") | R89: =+IFERROR(VLOOKUP(B89,[2]Google!$B$3:$C$99,2,FALSE),"")
B90: Grenada | C90: =+VLOOKUP($B90,'[2]Pricing Scenario - Maintain'!$B$4:$AM$238,2,FALSE) -> Latin America | D90: Web & IAP | E90: Web & IAP | F90: Web & IAP | G90: Web & IAP | H90: Web | I90: Web | J90: IAP | K90: IAP | L90: IAP | M90: IAP | N90: Web | O90: Web | P90: Web | Q90: =+IFERROR(VLOOKUP(B90,[2]Apple!$B$3:$C$173,2,FALSE),"") -> GD | R90: =+IFERROR(VLOOKUP(B90,[2]Google!$B$3:$C$99,2,FALSE),"") -> GD
B91: Guadeloupe | C91: Europe | D91: Web / IAP | E91: Web / IAP | F91: Web / IAP | G91: Web / IAP | H91: Web | I91: Web | J91: IAP | K91: IAP | L91: IAP | M91: IAP | N91: Web | O91: Web | P91: Web | Q91: =+IFERROR(VLOOKUP(B91,[2]Apple!$B$3:$C$173,2,FALSE),"") | R91: =+IFERROR(VLOOKUP(B91,[2]Google!$B$3:$C$99,2,FALSE),"")
B92: Guatemala | C92: =+VLOOKUP($B92,'[2]Pricing Scenario - Maintain'!$B$4:$AM$238,2,FALSE) -> Latin America | D92: Web & IAP | E92: Web & IAP | F92: Web & IAP | G92: Web & IAP | H92: Web | I92: Web | J92: IAP | K92: IAP | L92: IAP | M92: IAP | N92: Web | O92: Web | P92: Web | Q92: =+IFERROR(VLOOKUP(B92,[2]Apple!$B$3:$C$173,2,FALSE),"") -> GT | R92: =+IFERROR(VLOOKUP(B92,[2]Google!$B$3:$C$99,2,FALSE),"") -> GT
B93: Guernsey | C93: =+VLOOKUP($B93,'[2]Pricing Scenario - Maintain'!$B$4:$AM$238,2,FALSE) -> Europe | D93: Web / IAP | E93: Web / IAP | F93: Web / IAP | G93: Web / IAP | H93: Web | I93: Web | J93: IAP | K93: IAP | L93: IAP | M93: IAP | N93: Web | O93: Web | P93: Web | Q93: =+IFERROR(VLOOKUP(B93,[2]Apple!$B$3:$C$173,2,FALSE),"") | R93: =+IFERROR(VLOOKUP(B93,[2]Google!$B$3:$C$99,2,FALSE),"")
B94: Guinea | C94: =+VLOOKUP($B94,'[2]Pricing Scenario - Maintain'!$B$4:$AM$238,2,FALSE) -> Africa | D94: Web & IAP | E94: Web & IAP | F94: Web & IAP | G94: Web & IAP | H94: Web | I94: Web | J94: IAP | K94: IAP | L94: IAP | M94: IAP | N94: Web | O94: Web | P94: Web | Q94: =+IFERROR(VLOOKUP(B94,[2]Apple!$B$3:$C$173,2,FALSE),"") | R94: =+IFERROR(VLOOKUP(B94,[2]Google!$B$3:$C$99,2,FALSE),"") -> GN
B95: Guinea-Bissau | C95: =+VLOOKUP($B95,'[2]Pricing Scenario - Maintain'!$B$4:$AM$238,2,FALSE) -> Africa | D95: Web & IAP | E95: Web & IAP | F95: Web & IAP | G95: Web & IAP | H95: Web | I95: Web | J95: IAP | K95: IAP | L95: IAP | M95: IAP | N95: Web | O95: Web | P95: Web | Q95: =+IFERROR(VLOOKUP(B95,[2]Apple!$B$3:$C$173,2,FALSE),"") -> GW | R95: =+IFERROR(VLOOKUP(B95,[2]Google!$B$3:$C$99,2,FALSE),"") -> GW
B96: Guyana | C96: =+VLOOKUP($B96,'[2]Pricing Scenario - Maintain'!$B$4:$AM$238,2,FALSE) -> Latin America | D96: Web & IAP | E96: Web & IAP | F96: Web & IAP | G96: Web & IAP | H96: Web | I96: Web | J96: IAP | K96: IAP | L96: IAP | M96: IAP | N96: Web | O96: Web | P96: Web | Q96: =+IFERROR(VLOOKUP(B96,[2]Apple!$B$3:$C$173,2,FALSE),"") -> GY | R96: =+IFERROR(VLOOKUP(B96,[2]Google!$B$3:$C$99,2,FALSE),"")
B97: Haiti | C97: =+VLOOKUP($B97,'[2]Pricing Scenario - Maintain'!$B$4:$AM$238,2,FALSE) -> Latin America | D97: Web & IAP | E97: Web & IAP | F97: Web & IAP | G97: Web & IAP | H97: Web | I97: Web | J97: IAP | K97: IAP | L97: IAP | M97: IAP | N97: Web | O97: Web | P97: Web | Q97: =+IFERROR(VLOOKUP(B97,[2]Apple!$B$3:$C$173,2,FALSE),"") | R97: =+IFERROR(VLOOKUP(B97,[2]Google!$B$3:$C$99,2,FALSE),"") -> HT
B98: Heard And Mcdonald Islands | C98: =+VLOOKUP($B98,'[2]Pricing Scenario - Maintain'!$B$4:$AM$238,2,FALSE) -> India | D98: Web / IAP | E98: Web / IAP | F98: Web / IAP | G98: Web / IAP | H98: Web | I98: Web | J98: IAP | K98: IAP | L98: IAP | M98: IAP | N98: Web | O98: Web | P98: Web | Q98: =+IFERROR(VLOOKUP(B98,[2]Apple!$B$3:$C$173,2,FALSE),"") | R98: =+IFERROR(VLOOKUP(B98,[2]Google!$B$3:$C$99,2,FALSE),"")
B99: Honduras | C99: =+VLOOKUP($B99,'[2]Pricing Scenario - Maintain'!$B$4:$AM$238,2,FALSE) -> Latin America | D99: Web & IAP | E99: Web & IAP | F99: Web & IAP | G99: Web & IAP | H99: Web | I99: Web | J99: IAP | K99: IAP | L99: IAP | M99: IAP | N99: Web | O99: Web | P99: Web | Q99: =+IFERROR(VLOOKUP(B99,[2]Apple!$B$3:$C$173,2,FALSE),"") -> HN | R99: =+IFERROR(VLOOKUP(B99,[2]Google!$B$3:$C$99,2,FALSE),"") -> HN
B100: Hong Kong | C100: =+VLOOKUP($B100,'[2]Pricing Scenario - Maintain'!$B$4:$AM$238,2,FALSE) -> NBA China | D100: Web & IAP | E100: Web & IAP | F100: Web & IAP | G100: Web & IAP | H100: Web | I100: Web | J100: IAP | K100: IAP | L100: IAP | M100: IAP | N100: Web | O100: Web | P100: Web | Q100: =+IFERROR(VLOOKUP(B100,[2]Apple!$B$3:$C$173,2,FALSE),"") -> HK | R100: =+IFERROR(VLOOKUP(B100,[2]Google!$B$3:$C$99,2,FALSE),"") -> HK
B101: Hungary | C101: =+VLOOKUP($B101,'[2]Pricing Scenario - Maintain'!$B$4:$AM$238,2,FALSE) -> Europe | D101: Web & IAP | E101: Web & IAP | F101: Web & IAP | G101: Web & IAP | H101: Web | I101: Web | J101: IAP | K101: IAP | L101: IAP | M101: IAP | N101: Web | O101: Web | P101: Web | Q101: =+IFERROR(VLOOKUP(B101,[2]Apple!$B$3:$C$173,2,FALSE),"") -> HU | R101: =+IFERROR(VLOOKUP(B101,[2]Google!$B$3:$C$99,2,FALSE),"") -> HU
B102: Iceland | C102: =+VLOOKUP($B102,'[2]Pricing Scenario - Maintain'!$B$4:$AM$238,2,FALSE) -> Europe | D102: Web & IAP | E102: Web & IAP | F102: Web & IAP | G102: Web & IAP | H102: Web | I102: Web | J102: IAP | K102: IAP | L102: IAP | M102: IAP | N102: Web | O102: Web | P102: Web | Q102: =+IFERROR(VLOOKUP(B102,[2]Apple!$B$3:$C$173,2,FALSE),"") -> IS | R102: =+IFERROR(VLOOKUP(B102,[2]Google!$B$3:$C$99,2,FALSE),"") -> IS
B103: India | C103: =+VLOOKUP($B103,'[2]Pricing Scenario - Maintain'!$B$4:$AM$238,2,FALSE) -> India | D103: Web & IAP | E103: Web & IAP | F103: Web & IAP | G103: Web & IAP | H103: Web | I103: Web | J103: IAP | K103: IAP | L103: IAP | M103: IAP | N103: Web | O103: Web | P103: Web | Q103: =+IFERROR(VLOOKUP(B103,[2]Apple!$B$3:$C$173,2,FALSE),"") -> IN | R103: =+IFERROR(VLOOKUP(B103,[2]Google!$B$3:$C$99,2,FALSE),"") -> IN
B104: Indonesia | C104: =+VLOOKUP($B104,'[2]Pricing Scenario - Maintain'!$B$4:$AM$238,2,FALSE) -> Asia | D104: Web & IAP | E104: Web & IAP | F104: Web & IAP | G104: Web & IAP | H104: Web | I104: Web | J104: IAP | K104: IAP | L104: IAP | M104: IAP | N104: Web | O104: Web | P104: Web | Q104: =+IFERROR(VLOOKUP(B104,[2]Apple!$B$3:$C$173,2,FALSE),"") -> ID | R104: =+IFERROR(VLOOKUP(B104,[2]Google!$B$3:$C$99,2,FALSE),"") -> ID
B105: Iraq | C105: =+VLOOKUP($B105,'[2]Pricing Scenario - Maintain'!$B$4:$AM$238,2,FALSE) -> Middle East | D105: Web & IAP | E105: Web & IAP | F105: Web & IAP | G105: Web & IAP | H105: Web | I105: Web | J105: IAP | K105: IAP | L105: IAP | M105: IAP | N105: Web | O105: Web | P105: Web
B106: Ireland | C106: =+VLOOKUP($B106,'[2]Pricing Scenario - Maintain'!$B$4:$AM$238,2,FALSE) -> Europe | D106: Web & IAP | E106: Web & IAP | F106: Web & IAP | G106: Web & IAP | H106: Web | I106: Web | J106: IAP | K106: IAP | L106: IAP | M106: IAP | N106: Web | O106: Web | P106: Web | Q106: =+IFERROR(VLOOKUP(B106,[2]Apple!$B$3:$C$173,2,FALSE),"") -> IE | R106: =+IFERROR(VLOOKUP(B106,[2]Google!$B$3:$C$99,2,FALSE),"") -> IE
B107: Isle Of Man | C107: =+VLOOKUP($B107,'[2]Pricing Scenario - Maintain'!$B$4:$AM$238,2,FALSE) -> Europe | D107: Web / IAP | E107: Web / IAP | F107: Web / IAP | G107: Web / IAP | H107: Web | I107: Web | J107: IAP | K107: IAP | L107: IAP | M107: IAP | N107: Web | O107: Web | P107: Web | Q107: =+IFERROR(VLOOKUP(B107,[2]Apple!$B$3:$C$173,2,FALSE),"") | R107: =+IFERROR(VLOOKUP(B107,[2]Google!$B$3:$C$99,2,FALSE),"")
B108: Israel | C108: =+VLOOKUP($B108,'[2]Pricing Scenario - Maintain'!$B$4:$AM$238,2,FALSE) -> Europe | D108: Web & IAP | E108: Web & IAP | F108: Web & IAP | G108: Web & IAP | H108: Web | I108: Web | J108: IAP | K108: IAP | L108: IAP | M108: IAP | N108: Web | O108: Web | P108: Web | Q108: =+IFERROR(VLOOKUP(B108,[2]Apple!$B$3:$C$173,2,FALSE),"") -> IL | R108: =+IFERROR(VLOOKUP(B108,[2]Google!$B$3:$C$99,2,FALSE),"") -> IL
B109: Italy | C109: =+VLOOKUP($B109,'[2]Pricing Scenario - Maintain'!$B$4:$AM$238,2,FALSE) -> Europe | D109: Web & IAP | E109: Web & IAP | F109: Web & IAP | G109: Web & IAP | H109: Web | I109: Web | J109: IAP | K109: IAP | L109: IAP | M109: IAP | N109: Web | O109: Web | P109: Web | Q109: =+IFERROR(VLOOKUP(B109,[2]Apple!$B$3:$C$173,2,FALSE),"") -> IT | R109: =+IFERROR(VLOOKUP(B109,[2]Google!$B$3:$C$99,2,FALSE),"") -> IT
B110: Jamaica | C110: =+VLOOKUP($B110,'[2]Pricing Scenario - Maintain'!$B$4:$AM$238,2,FALSE) -> Latin America | D110: Web & IAP | E110: Web & IAP | F110: Web & IAP | G110: Web & IAP | H110: Web | I110: Web | J110: IAP | K110: IAP | L110: IAP | M110: IAP | N110: Web | O110: Web | P110: Web | Q110: =+IFERROR(VLOOKUP(B110,[2]Apple!$B$3:$C$173,2,FALSE),"") -> JM | R110: =+IFERROR(VLOOKUP(B110,[2]Google!$B$3:$C$99,2,FALSE),"") -> JM
B111: Japan | C111: Asia | D111: Web & IAP | E111: Web & IAP | F111: Web & IAP | G111: Web & IAP | H111: Web | I111: Web | J111: IAP | K111: IAP | L111: IAP | M111: IAP
B112: Jersey | C112: =+VLOOKUP($B112,'[2]Pricing Scenario - Maintain'!$B$4:$AM$238,2,FALSE) -> Europe | D112: Web / IAP | E112: Web / IAP | F112: Web / IAP | G112: Web / IAP | H112: Web | I112: Web | J112: IAP | K112: IAP | L112: IAP | M112: IAP | N112: Web | O112: Web | P112: Web | Q112: =+IFERROR(VLOOKUP(B112,[2]Apple!$B$3:$C$173,2,FALSE),"") | R112: =+IFERROR(VLOOKUP(B112,[2]Google!$B$3:$C$99,2,FALSE),"")
B113: Jordan | C113: =+VLOOKUP($B113,'[2]Pricing Scenario - Maintain'!$B$4:$AM$238,2,FALSE) -> Middle East | D113: Web & IAP | E113: Web & IAP | F113: Web & IAP | G113: Web & IAP | H113: Web | I113: Web | J113: IAP | K113: IAP | L113: IAP | M113: IAP | N113: Web | O113: Web | P113: Web | Q113: =+IFERROR(VLOOKUP(B113,[2]Apple!$B$3:$C$173,2,FALSE),"") -> JO | R113: =+IFERROR(VLOOKUP(B113,[2]Google!$B$3:$C$99,2,FALSE),"") -> JO
B114: Kazakhstan | C114: =+VLOOKUP($B114,'[2]Pricing Scenario - Maintain'!$B$4:$AM$238,2,FALSE) -> Asia | D114: Web & IAP | E114: Web & IAP | F114: Web & IAP | G114: Web & IAP | H114: Web | I114: Web | J114: IAP | K114: IAP | L114: IAP | M114: IAP | N114: Web | O114: Web | P114: Web | Q114: =+IFERROR(VLOOKUP(B114,[2]Apple!$B$3:$C$173,2,FALSE),"") -> KZ | R114: =+IFERROR(VLOOKUP(B114,[2]Google!$B$3:$C$99,2,FALSE),"") -> KZ
B115: Kenya | C115: =+VLOOKUP($B115,'[2]Pricing Scenario - Maintain'!$B$4:$AM$238,2,FALSE) -> Africa | D115: Web & IAP | E115: Web & IAP | F115: Web & IAP | G115: Web & IAP | H115: Web | I115: Web | J115: IAP | K115: IAP | L115: IAP | M115: IAP | N115: Web | O115: Web | P115: Web | Q115: =+IFERROR(VLOOKUP(B115,[2]Apple!$B$3:$C$173,2,FALSE),"") -> KE | R115: =+IFERROR(VLOOKUP(B115,[2]Google!$B$3:$C$99,2,FALSE),"") -> KE
B116: Kiribati | C116: =+VLOOKUP($B116,'[2]Pricing Scenario - Maintain'!$B$4:$AM$238,2,FALSE) -> Asia | D116: Web / IAP | E116: Web / IAP | F116: Web / IAP | G116: Web / IAP | H116: Web | I116: Web | J116: IAP | K116: IAP | L116: IAP | M116: IAP | N116: Web | O116: Web | P116: Web | Q116: =+IFERROR(VLOOKUP(B116,[2]Apple!$B$3:$C$173,2,FALSE),"") | R116: =+IFERROR(VLOOKUP(B116,[2]Google!$B$3:$C$99,2,FALSE),"")
B117: Kosovo | C117: =+VLOOKUP($B117,'[2]Pricing Scenario - Maintain'!$B$4:$AM$238,2,FALSE) -> Europe | D117: Web & IAP | E117: Web & IAP | F117: Web & IAP | G117: Web & IAP | H117: Web | I117: Web | J117: IAP | K117: IAP | L117: IAP | M117: IAP | Q117: =+IFERROR(VLOOKUP(B117,[2]Apple!$B$3:$C$173,2,FALSE),"") -> XK | R117: =+IFERROR(VLOOKUP(B117,[2]Google!$B$3:$C$99,2,FALSE),"")
B118: Kuwait | C118: =+VLOOKUP($B118,'[2]Pricing Scenario - Maintain'!$B$4:$AM$238,2,FALSE) -> Middle East | D118: Web & IAP | E118: Web & IAP | F118: Web & IAP | G118: Web & IAP | H118: Web | I118: Web | J118: IAP | K118: IAP | L118: IAP | M118: IAP | N118: Web | O118: Web | P118: Web | Q118: =+IFERROR(VLOOKUP(B118,[2]Apple!$B$3:$C$173,2,FALSE),"") -> KW | R118: =+IFERROR(VLOOKUP(B118,[2]Google!$B$3:$C$99,2,FALSE),"") -> KW
B119: Kyrgyzstan | C119: =+VLOOKUP($B119,'[2]Pricing Scenario - Maintain'!$B$4:$AM$238,2,FALSE) -> Asia | D119: Web & IAP | E119: Web & IAP | F119: Web & IAP | G119: Web & IAP | H119: Web | I119: Web | J119: IAP | K119: IAP | L119: IAP | M119: IAP | N119: Web | O119: Web | P119: Web | Q119: =+IFERROR(VLOOKUP(B119,[2]Apple!$B$3:$C$173,2,FALSE),"") -> KG | R119: =+IFERROR(VLOOKUP(B119,[2]Google!$B$3:$C$99,2,FALSE),"") -> KG
B120: Laos | C120: =+VLOOKUP($B120,'[2]Pricing Scenario - Maintain'!$B$4:$AM$238,2,FALSE) -> Asia | D120: Web & IAP | E120: Web & IAP | F120: Web & IAP | G120: Web & IAP | H120: Web | I120: Web | J120: IAP | K120: IAP | L120: IAP | M120: IAP | N120: Web | O120: Web | P120: Web | Q120: =+IFERROR(VLOOKUP(B120,[2]Apple!$B$3:$C$173,2,FALSE),"") -> LA | R120: =+IFERROR(VLOOKUP(B120,[2]Google!$B$3:$C$99,2,FALSE),"") -> LA
B121: Latvia | C121: =+VLOOKUP($B121,'[2]Pricing Scenario - Maintain'!$B$4:$AM$238,2,FALSE) -> Europe | D121: Web & IAP | E121: Web & IAP | F121: Web & IAP | G121: Web & IAP | H121: Web | I121: Web | J121: IAP | K121: IAP | L121: IAP | M121: IAP | N121: Web | O121: Web | P121: Web | Q121: =+IFERROR(VLOOKUP(B121,[2]Apple!$B$3:$C$173,2,FALSE),"") -> LV | R121: =+IFERROR(VLOOKUP(B121,[2]Google!$B$3:$C$99,2,FALSE),"") -> LV
B122: Lebanon | C122: =+VLOOKUP($B122,'[2]Pricing Scenario - Maintain'!$B$4:$AM$238,2,FALSE) -> Middle East | D122: Web & IAP | E122: Web & IAP | F122: Web & IAP | G122: Web & IAP | H122: Web | I122: Web | J122: IAP | K122: IAP | L122: IAP | M122: IAP | N122: Web | O122: Web | P122: Web | Q122: =+IFERROR(VLOOKUP(B122,[2]Apple!$B$3:$C$173,2,FALSE),"") -> LB | R122: =+IFERROR(VLOOKUP(B122,[2]Google!$B$3:$C$99,2,FALSE),"") -> LB
B123: Lesotho | C123: =+VLOOKUP($B123,'[2]Pricing Scenario - Maintain'!$B$4:$AM$238,2,FALSE) -> Africa | D123: Web / IAP | E123: Web / IAP | F123: Web / IAP | G123: Web / IAP | H123: Web | I123: Web | J123: IAP | K123: IAP | L123: IAP | M123: IAP | N123: Web | O123: Web | P123: Web | Q123: =+IFERROR(VLOOKUP(B123,[2]Apple!$B$3:$C$173,2,FALSE),"") | R123: =+IFERROR(VLOOKUP(B123,[2]Google!$B$3:$C$99,2,FALSE),"")
B124: Liberia | C124: =+VLOOKUP($B124,'[2]Pricing Scenario - Maintain'!$B$4:$AM$238,2,FALSE) -> Africa | D124: Web & IAP | E124: Web & IAP | F124: Web & IAP | G124: Web & IAP | H124: Web | I124: Web | J124: IAP | K124: IAP | L124: IAP | M124: IAP | N124: Web | O124: Web | P124: Web | Q124: =+IFERROR(VLOOKUP(B124,[2]Apple!$B$3:$C$173,2,FALSE),"") -> LR | R124: =+IFERROR(VLOOKUP(B124,[2]Google!$B$3:$C$99,2,FALSE),"") -> LR
B125: Libya | C125: =+VLOOKUP($B125,'[2]Pricing Scenario - Maintain'!$B$4:$AM$238,2,FALSE) -> Africa | D125: Web & IAP | E125: Web & IAP | F125: Web & IAP | G125: Web & IAP | H125: Web | I125: Web | J125: IAP | K125: IAP | L125: IAP | M125: IAP | N125: Web | O125: Web | P125: Web
B126: Liechtenstein | C126: =+VLOOKUP($B126,'[2]Pricing Scenario - Maintain'!$B$4:$AM$238,2,FALSE) -> Europe | D126: Web & IAP | E126: Web & IAP | F126: Web & IAP | G126: Web & IAP | H126: Web | I126: Web | J126: IAP | K126: IAP | L126: IAP | M126: IAP | N126: Web | O126: Web | P126: Web | Q126: =+IFERROR(VLOOKUP(B126,[2]Apple!$B$3:$C$173,2,FALSE),"") | R126: =+IFERROR(VLOOKUP(B126,[2]Google!$B$3:$C$99,2,FALSE),"") -> LI
B127: Lithuania | C127: =+VLOOKUP($B127,'[2]Pricing Scenario - Maintain'!$B$4:$AM$238,2,FALSE) -> Europe | D127: Web & IAP | E127: Web & IAP | F127: Web & IAP | G127: Web & IAP | H127: Web | I127: Web | J127: IAP | K127: IAP | L127: IAP | M127: IAP | N127: Web | O127: Web | P127: Web | Q127: =+IFERROR(VLOOKUP(B127,[2]Apple!$B$3:$C$173,2,FALSE),"") -> LT | R127: =+IFERROR(VLOOKUP(B127,[2]Google!$B$3:$C$99,2,FALSE),"") -> LT
B128: Luxembourg | C128: =+VLOOKUP($B128,'[2]Pricing Scenario - Maintain'!$B$4:$AM$238,2,FALSE) -> Europe | D128: Web & IAP | E128: Web & IAP | F128: Web & IAP | G128: Web & IAP | H128: Web | I128: Web | J128: IAP | K128: IAP | L128: IAP | M128: IAP | N128: Web | O128: Web | P128: Web | Q128: =+IFERROR(VLOOKUP(B128,[2]Apple!$B$3:$C$173,2,FALSE),"") -> LU | R128: =+IFERROR(VLOOKUP(B128,[2]Google!$B$3:$C$99,2,FALSE),"") -> LU
B129: Macao | C129: =+VLOOKUP($B129,'[2]Pricing Scenario - Maintain'!$B$4:$AM$238,2,FALSE) -> NBA China | D129: Web & IAP | E129: Web & IAP | F129: Web & IAP | G129: Web & IAP | H129: Web | I129: Web | J129: IAP | K129: IAP | L129: IAP | M129: IAP | N129: Web | O129: Web | P129: Web | Q129: =+IFERROR(VLOOKUP(B129,[2]Apple!$B$3:$C$173,2,FALSE),"") -> MO | R129: =+IFERROR(VLOOKUP(B129,[2]Google!$B$3:$C$99,2,FALSE),"") -> MO
B130: Macedonia | C130: =+VLOOKUP($B130,'[2]Pricing Scenario - Maintain'!$B$4:$AM$238,2,FALSE) -> Europe | D130: Web & IAP | E130: Web & IAP | F130: Web & IAP | G130: Web & IAP | H130: Web | I130: Web | J130: IAP | K130: IAP | L130: IAP | M130: IAP | N130: Web | O130: Web | P130: Web | Q130: =+IFERROR(VLOOKUP(B130,[2]Apple!$B$3:$C$173,2,FALSE),"") -> MK | R130: =+IFERROR(VLOOKUP(B130,[2]Google!$B$3:$C$99,2,FALSE),"") -> MK
B131: Madagascar | C131: =+VLOOKUP($B131,'[2]Pricing Scenario - Maintain'!$B$4:$AM$238,2,FALSE) -> Africa | D131: Web & IAP | E131: Web & IAP | F131: Web & IAP | G131: Web & IAP | H131: Web | I131: Web | J131: IAP | K131: IAP | L131: IAP | M131: IAP | N131: Web | O131: Web | P131: Web | Q131: =+IFERROR(VLOOKUP(B131,[2]Apple!$B$3:$C$173,2,FALSE),"") -> MG | R131: =+IFERROR(VLOOKUP(B131,[2]Google!$B$3:$C$99,2,FALSE),"")
B132: Malawi | C132: =+VLOOKUP($B132,'[2]Pricing Scenario - Maintain'!$B$4:$AM$238,2,FALSE) -> Africa | D132: Web & IAP | E132: Web & IAP | F132: Web & IAP | G132: Web & IAP | H132: Web | I132: Web | J132: IAP | K132: IAP | L132: IAP | M132: IAP | N132: Web | O132: Web | P132: Web | Q132: =+IFERROR(VLOOKUP(B132,[2]Apple!$B$3:$C$173,2,FALSE),"") -> MW | R132: =+IFERROR(VLOOKUP(B132,[2]Google!$B$3:$C$99,2,FALSE),"")
B133: Malaysia | C133: =+VLOOKUP($B133,'[2]Pricing Scenario - Maintain'!$B$4:$AM$238,2,FALSE) -> Asia | D133: Web & IAP | E133: Web & IAP | F133: Web & IAP | G133: Web & IAP | H133: Web | I133: Web | J133: IAP | K133: IAP | L133: IAP | M133: IAP | N133: Web | O133: Web | P133: Web | Q133: =+IFERROR(VLOOKUP(B133,[2]Apple!$B$3:$C$173,2,FALSE),"") -> MY | R133: =+IFERROR(VLOOKUP(B133,[2]Google!$B$3:$C$99,2,FALSE),"") -> MY
B134: Maldives | C134: =+VLOOKUP($B134,'[2]Pricing Scenario - Maintain'!$B$4:$AM$238,2,FALSE) -> Asia | D134: Web & IAP | E134: Web & IAP | F134: Web & IAP | G134: Web & IAP | H134: Web | I134: Web | J134: IAP | K134: IAP | L134: IAP | M134: IAP | N134: Web | O134: Web | P134: Web | Q134: =+IFERROR(VLOOKUP(B134,[2]Apple!$B$3:$C$173,2,FALSE),"") -> MV | R134: =+IFERROR(VLOOKUP(B134,[2]Google!$B$3:$C$99,2,FALSE),"") -> MV
B135: Mali | C135: =+VLOOKUP($B135,'[2]Pricing Scenario - Maintain'!$B$4:$AM$238,2,FALSE) -> Africa | D135: Web & IAP | E135: Web & IAP | F135: Web & IAP | G135: Web & IAP | H135: Web | I135: Web | J135: IAP | K135: IAP | L135: IAP | M135: IAP | N135: Web | O135: Web | P135: Web | Q135: =+IFERROR(VLOOKUP(B135,[2]Apple!$B$3:$C$173,2,FALSE),"") -> ML | R135: =+IFERROR(VLOOKUP(B135,[2]Google!$B$3:$C$99,2,FALSE),"") -> ML
B136: Malta | C136: =+VLOOKUP($B136,'[2]Pricing Scenario - Maintain'!$B$4:$AM$238,2,FALSE) -> Europe | D136: Web & IAP | E136: Web & IAP | F136: Web & IAP | G136: Web & IAP | H136: Web | I136: Web | J136: IAP | K136: IAP | L136: IAP | M136: IAP | N136: Web | O136: Web | P136: Web | Q136: =+IFERROR(VLOOKUP(B136,[2]Apple!$B$3:$C$173,2,FALSE),"") -> MT | R136: =+IFERROR(VLOOKUP(B136,[2]Google!$B$3:$C$99,2,FALSE),"") -> MT
B137: Marshall Islands | C137: =+VLOOKUP($B137,'[2]Pricing Scenario - Maintain'!$B$4:$AM$238,2,FALSE) -> Asia | D137: Web / IAP | E137: Web / IAP | F137: Web / IAP | G137: Web / IAP | H137: Web | I137: Web | J137: IAP | K137: IAP | L137: IAP | M137: IAP | N137: Web | O137: Web | P137: Web | Q137: =+IFERROR(VLOOKUP(B137,[2]Apple!$B$3:$C$173,2,FALSE),"") | R137: =+IFERROR(VLOOKUP(B137,[2]Google!$B$3:$C$99,2,FALSE),"")
B138: Martinique | C138: Europe | D138: Web / IAP | E138: Web / IAP | F138: Web / IAP | G138: Web / IAP | H138: Web | I138: Web | J138: IAP | K138: IAP | L138: IAP | M138: IAP | N138: Web | O138: Web | P138: Web | Q138: =+IFERROR(VLOOKUP(B138,[2]Apple!$B$3:$C$173,2,FALSE),"") | R138: =+IFERROR(VLOOKUP(B138,[2]Google!$B$3:$C$99,2,FALSE),"")
B139: Mauritania | C139: =+VLOOKUP($B139,'[2]Pricing Scenario - Maintain'!$B$4:$AM$238,2,FALSE) -> Africa | D139: Web & IAP | E139: Web & IAP | F139: Web & IAP | G139: Web & IAP | H139: Web | I139: Web | J139: IAP | K139: IAP | L139: IAP | M139: IAP | N139: Web | O139: Web | P139: Web | Q139: =+IFERROR(VLOOKUP(B139,[2]Apple!$B$3:$C$173,2,FALSE),"") -> MR | R139: =+IFERROR(VLOOKUP(B139,[2]Google!$B$3:$C$99,2,FALSE),"")
B140: Mauritius | C140: =+VLOOKUP($B140,'[2]Pricing Scenario - Maintain'!$B$4:$AM$238,2,FALSE) -> Africa | D140: Web & IAP | E140: Web & IAP | F140: Web & IAP | G140: Web & IAP | H140: Web | I140: Web | J140: IAP | K140: IAP | L140: IAP | M140: IAP | N140: Web | O140: Web | P140: Web | Q140: =+IFERROR(VLOOKUP(B140,[2]Apple!$B$3:$C$173,2,FALSE),"") -> MU | R140: =+IFERROR(VLOOKUP(B140,[2]Google!$B$3:$C$99,2,FALSE),"")
B141: Mayotte | C141: Europe | D141: Web / IAP | E141: Web / IAP | F141: Web / IAP | G141: Web / IAP | H141: Web | I141: Web | J141: IAP | K141: IAP | L141: IAP | M141: IAP | N141: Web | O141: Web | P141: Web | Q141: =+IFERROR(VLOOKUP(B141,[2]Apple!$B$3:$C$173,2,FALSE),"") | R141: =+IFERROR(VLOOKUP(B141,[2]Google!$B$3:$C$99,2,FALSE),"")
B142: Mexico | C142: =+VLOOKUP($B142,'[2]Pricing Scenario - Maintain'!$B$4:$AM$238,2,FALSE) -> Latin America | D142: Web & IAP | E142: Web & IAP | F142: Web & IAP | G142: Web & IAP | H142: Web | I142: Web | J142: IAP | K142: IAP | L142: IAP | M142: IAP | N142: Web | O142: Web | P142: Web | Q142: =+IFERROR(VLOOKUP(B142,[2]Apple!$B$3:$C$173,2,FALSE),"") -> MX | R142: =+IFERROR(VLOOKUP(B142,[2]Google!$B$3:$C$99,2,FALSE),"")
B143: Micronesia | C143: =+VLOOKUP($B143,'[2]Pricing Scenario - Maintain'!$B$4:$AM$238,2,FALSE) -> Asia | D143: Web & IAP | E143: Web & IAP | F143: Web & IAP | G143: Web & IAP | H143: Web | I143: Web | J143: IAP | K143: IAP | L143: IAP | M143: IAP | N143: Web | O143: Web | P143: Web | Q143: =+IFERROR(VLOOKUP(B143,[2]Apple!$B$3:$C$173,2,FALSE),"") -> FM | R143: =+IFERROR(VLOOKUP(B143,[2]Google!$B$3:$C$99,2,FALSE),"")
...

Sheet Pricing by Platform ->

Sheet DOM Web
B2: Country | C2: Region | D2: BLPEUSTV | E2: BLPEUSTVMONTHLY | F2: BLPPUSTV | G2: BLPPUSSTVMONTHLY | H2: BTCUS | I2: BTCUSMONTHLY | J2: BLPTV | K2: BLPTVMONTHLY | L2: BLPAUDIO
B3: United States | C3: Domestic | D3: 159.99 | E3: 24.99 | F3: 109.99 | G3: 16.99 | H3: 89.99 | I3: 13.99 | J3: 74.99 | K3: 8.99 | L3: 9.99
B4: Guam | C4: Domestic | D4: =+D$3 -> 159.99 | E4: =+E$3 -> 24.99 | F4: =+F$3 -> 109.99 | G4: =+G$3 -> 16.99 | H4: =+H$3 -> 89.99 | I4: =+I$3 -> 13.99 | J4: =+J$3 -> 74.99 | K4: =+K$3 -> 8.99 | L4: =+L$3 -> 9.99
B5: Puerto Rico | C5: Domestic | D5: =+D$3 -> 159.99 | E5: =+E$3 -> 24.99 | F5: =+F$3 -> 109.99 | G5: =+G$3 -> 16.99 | H5: =+H$3 -> 89.99 | I5: =+I$3 -> 13.99 | J5: =+J$3 -> 74.99 | K5: =+K$3 -> 8.99 | L5: =+L$3 -> 9.99
B6: US Virgin Islands | C6: Domestic | D6: =+D$3 -> 159.99 | E6: =+E$3 -> 24.99 | F6: =+F$3 -> 109.99 | G6: =+G$3 -> 16.99 | H6: =+H$3 -> 89.99 | I6: =+I$3 -> 13.99 | J6: =+J$3 -> 74.99 | K6: =+K$3 -> 8.99 | L6: =+L$3 -> 9.99
B7: US Minor Outlying Islands | C7: Domestic | D7: =+D$3 -> 159.99 | E7: =+E$3 -> 24.99 | F7: =+F$3 -> 109.99 | G7: =+G$3 -> 16.99 | H7: =+H$3 -> 89.99 | I7: =+I$3 -> 13.99 | J7: =+J$3 -> 74.99 | K7: =+K$3 -> 8.99 | L7: =+L$3 -> 9.99

Sheet INT Web
B1: 1 | C1: =+B1+1 -> 2 | D1: =+C1+1 -> 3 | E1: =+D1+1 -> 4 | F1: =+E1+1 -> 5 | G1: =+F1+1 -> 6 | H1: =+G1+1 -> 7 | I1: =+H1+1 -> 8 | J1: =+I1+1 -> 9 | ... AQ1: =+AP1+1 -> 42
R2: BLPE | S2: BLPEMONTHLY | T2: BLPP | U2: BLPPMONTHLY | V2: BTC | W2: BTCMONTHLY | AK2: 46209 | AL2: BLPE | AM2: BLPEMONTHLY | AN2: BLPP | AO2: BLPPMONTHLY | AP2: BTC | AQ2: BTCMONTHLY
D3: Old Priority Mkt | E3: FY26 Start of Season Pricing (in Local Currency) | L3: FY26 Start of Season Sub. Length and SKU Ratios | Q3: FY27 Start of Season Pricing (in Local Currency) | X3: FY27 Start of Season Sub. Length and SKU Ratios | AD3: YoY FY27 vs. FY26 Start of Season Pricing | AK3: FY27 Start of Season Pricing (in USD)
B4: Country | C4: Region | D4: Segment | E4: Currency | F4: LPP Annual | G4: LPP Monthly | H4: LP Annual | I4: LP Monthly | J4: TC Annual | K4: TC Monthly | L4: LPP SubL. | M4: LPP SKU | N4: LP SubL. | O4: TP SubL. | P4: TP SKU | Q4: Currency | R4: LPP Annual | S4: LPP Monthly | T4: LP Annual | U4: LP Monthly | V4: TC Annual | W4: TC Monthly | X4: LPP SubL. | Y4: LPP SKU | Z4: LP SubL. | AA4: TP SubL. | AB4: TP SKU | AD4: LPP Annual | AE4: LPP Monthly | AF4: LP Annual | AG4: LP Monthly | AH4: TC Annual | AI4: TC Monthly | AK4: FX to USD | AL4: LPP Annual | AM4: LPP Monthly | AN4: LP Annual | AO4: LP Monthly | AP4: TC Annual | AQ4: TC Monthly | AS4: Two Digit Country Code
B5: Afghanistan | C5: Asia | E5: =+VLOOKUP($B5,'[3]INT Web'!$B$5:$W$247,'[3]INT Web'!Q$1,FALSE) -> USD | F5: =+VLOOKUP($B5,'[3]INT Web'!$B$5:$W$247,'[3]INT Web'!R$1,FALSE) -> 71.99 | G5: =+VLOOKUP($B5,'[3]INT Web'!$B$5:$W$247,'[3]INT Web'!S$1,FALSE) -> 11.99 | H5: =+VLOOKUP($B5,'[3]INT Web'!$B$5:$W$247,'[3]INT Web'!T$1,FALSE) -> 53.99 | I5: =+VLOOKUP($B5,'[3]INT Web'!$B$5:$W$247,'[3]INT Web'!U$1,FALSE) -> 8.99 | J5: =+VLOOKUP($B5,'[3]INT Web'!$B$5:$W$247,'[3]INT Web'!V$1,FALSE) -> 47.99 | K5: =+VLOOKUP($B5,'[3]INT Web'!$B$5:$W$247,'[3]INT Web'!W$1,FALSE) -> 7.99 | L5: =+F5/G5 -> 6.0041701 | M5: =+G5/I5 -> 1.3337041 | N5: =+H5/I5 -> 6.0055617 | O5: =+J5/K5 -> 6.0062578 | P5: =+K5/I5 -> 0.88876529 | Q5: =+E5 -> USD | R5: =+VLOOKUP($B5,'Country-Level Tactics'!$B$5:$AL$248,'Country-Level Tactics'!AH$1,FALSE) -> 71.99 | S5: =+VLOOKUP($B5,'Country-Level Tactics'!$B$5:$AL$248,'Country-Level Tactics'!X$1,FALSE) -> 11.99 | T5: =+VLOOKUP($B5,'Country-Level Tactics'!$B$5:$AL$248,'Country-Level Tactics'!AC$1,FALSE) -> 53.99 | U5: =+VLOOKUP($B5,'Country-Level Tactics'!$B$5:$AL$248,'Country-Level Tactics'!T$1,FALSE) -> 8.99 | V5: =+J5 -> 47.99 | W5: =+K5 -> 7.99 | X5: =+R5/S5 -> 6.0041701 | Y5: =+S5/U5 -> 1.3337041 | Z5: =+T5/U5 -> 6.0055617 | AA5: =+V5/W5 -> 6.0062578 | AB5: =+W5/U5 -> 0.88876529 | AD5: =+R5/F5-1 -> 0 | AE5: =+S5/G5-1 -> 0 | AF5: =+T5/H5-1 -> 0 | AG5: =+U5/I5-1 -> 0 | AH5: =+V5/J5-1 -> 0 | AI5: =+W5/K5-1 -> 0 | AK5: {=_xll.FDS("","P_EXCH_RATE("&Q5&",USD,"&$AK$2&")")} -> 1 | AL5: =+R5*$AK5 -> 71.99 | AM5: =+S5*$AK5 -> 11.99 | AN5: =+T5*$AK5 -> 53.99 | AO5: =+U5*$AK5 -> 8.99 | AP5: =+V5*$AK5 -> 47.99 | AQ5: =+W5*$AK5 -> 7.99 | AS5: =+VLOOKUP(B5,'Country & Code Abbreviation'!$B$3:$C$245,2,FALSE) -> AF
B6: Aland Islands | C6: Europe | E6: =+VLOOKUP($B6,'[3]INT Web'!$B$5:$W$247,'[3]INT Web'!Q$1,FALSE) -> EUR | F6: =+VLOOKUP($B6,'[3]INT Web'!$B$5:$W$247,'[3]INT Web'!R$1,FALSE) -> 119.99 | G6: =+VLOOKUP($B6,'[3]INT Web'!$B$5:$W$247,'[3]INT Web'!S$1,FALSE) -> 19.99 | H6: =+VLOOKUP($B6,'[3]INT Web'!$B$5:$W$247,'[3]INT Web'!T$1,FALSE) -> 89.99 | I6: =+VLOOKUP($B6,'[3]INT Web'!$B$5:$W$247,'[3]INT Web'!U$1,FALSE) -> 14.99 | J6: =+VLOOKUP($B6,'[3]INT Web'!$B$5:$W$247,'[3]INT Web'!V$1,FALSE) -> 79.99 | K6: =+VLOOKUP($B6,'[3]INT Web'!$B$5:$W$247,'[3]INT Web'!W$1,FALSE) -> 12.99 | L6: =+F6/G6 -> 6.0025013 | M6: =+G6/I6 -> 1.3335557 | N6: =+H6/I6 -> 6.0033356 | O6: =+J6/K6 -> 6.1578137 | P6: =+K6/I6 -> 0.86657772 | Q6: =+E6 -> EUR | R6: =+VLOOKUP($B6,'Country-Level Tactics'!$B$5:$AL$248,'Country-Level Tactics'!AH$1,FALSE) -> 119.99 | S6: =+VLOOKUP($B6,'Country-Level Tactics'!$B$5:$AL$248,'Country-Level Tactics'!X$1,FALSE) -> 19.99 | T6: =+VLOOKUP($B6,'Country-Level Tactics'!$B$5:$AL$248,'Country-Level Tactics'!AC$1,FALSE) -> 89.99 | U6: =+VLOOKUP($B6,'Country-Level Tactics'!$B$5:$AL$248,'Country-Level Tactics'!T$1,FALSE) -> 14.99 | V6: =+J6 -> 79.99 | W6: =+K6 -> 12.99 | X6: =+R6/S6 -> 6.0025013 | Y6: =+S6/U6 -> 1.3335557 | Z6: =+T6/U6 -> 6.0033356 | AA6: =+V6/W6 -> 6.1578137 | AB6: =+W6/U6 -> 0.86657772 | AD6: =+R6/F6-1 -> 0 | AE6: =+S6/G6-1 -> 0 | AF6: =+T6/H6-1 -> 0 | AG6: =+U6/I6-1 -> 0 | AH6: =+V6/J6-1 -> 0 | AI6: =+W6/K6-1 -> 0 | AK6: {=_xll.FDS("","P_EXCH_RATE("&Q6&",USD,"&$AK$2&")")} -> 1.14175 | AL6: =+R6*$AK6 -> 136.99858 | AM6: =+S6*$AK6 -> 22.823583 | AN6: =+T6*$AK6 -> 102.74608 | AO6: =+U6*$AK6 -> 17.114833 | AP6: =+V6*$AK6 -> 91.328582 | AQ6: =+W6*$AK6 -> 14.831333 | AS6: =+VLOOKUP(B6,'Country & Code Abbreviation'!$B$3:$C$245,2,FALSE) -> AX
B7: Albania | C7: Europe | E7: =+VLOOKUP($B7,'[3]INT Web'!$B$5:$W$247,'[3]INT Web'!Q$1,FALSE) -> ALL | F7: =+VLOOKUP($B7,'[3]INT Web'!$B$5:$W$247,'[3]INT Web'!R$1,FALSE) -> 9719.99 | G7: =+VLOOKUP($B7,'[3]INT Web'!$B$5:$W$247,'[3]INT Web'!S$1,FALSE) -> 1619.99 | H7: =+VLOOKUP($B7,'[3]INT Web'!$B$5:$W$247,'[3]INT Web'!T$1,FALSE) -> 7199.99 | I7: =+VLOOKUP($B7,'[3]INT Web'!$B$5:$W$247,'[3]INT Web'!U$1,FALSE) -> 1199.99 | J7: =+VLOOKUP($B7,'[3]INT Web'!$B$5:$W$247,'[3]INT Web'!V$1,FALSE) -> 6479.99 | K7: =+VLOOKUP($B7,'[3]INT Web'!$B$5:$W$247,'[3]INT Web'!W$1,FALSE) -> 1079.99 | L7: =+F7/G7 -> 6.0000309 | M7: =+G7/I7 -> 1.3500029 | N7: =+H7/I7 -> 6.0000417 | O7: =+J7/K7 -> 6.0000463 | P7: =+K7/I7 -> 0.89999917 | Q7: =+E7 -> ALL | R7: =+VLOOKUP($B7,'Country-Level Tactics'!$B$5:$AL$248,'Country-Level Tactics'!AH$1,FALSE) -> 9719.99 | S7: =+VLOOKUP($B7,'Country-Level Tactics'!$B$5:$AL$248,'Country-Level Tactics'!X$1,FALSE) -> 1619.99 | T7: =+VLOOKUP($B7,'Country-Level Tactics'!$B$5:$AL$248,'Country-Level Tactics'!AC$1,FALSE) -> 7199.99 | U7: =+VLOOKUP($B7,'Country-Level Tactics'!$B$5:$AL$248,'Country-Level Tactics'!T$1,FALSE) -> 1199.99 | V7: =+J7 -> 6479.99 | W7: =+K7 -> 1079.99 | X7: =+R7/S7 -> 6.0000309 | Y7: =+S7/U7 -> 1.3500029 | Z7: =+T7/U7 -> 6.0000417 | AA7: =+V7/W7 -> 6.0000463 | AB7: =+W7/U7 -> 0.89999917 | AD7: =+R7/F7-1 -> 0 | AE7: =+S7/G7-1 -> 0 | AF7: =+T7/H7-1 -> 0 | AG7: =+U7/I7-1 -> 0 | AH7: =+V7/J7-1 -> 0 | AI7: =+W7/K7-1 -> 0 | AK7: {=_xll.FDS("","P_EXCH_RATE("&Q7&",USD,"&$AK$2&")")} -> 0.012172114 | AL7: =+R7*$AK7 -> 118.31283 | AM7: =+S7*$AK7 -> 19.718703 | AN7: =+T7*$AK7 -> 87.639099 | AO7: =+U7*$AK7 -> 14.606415 | AP7: =+V7*$AK7 -> 78.875177 | AQ7: =+W7*$AK7 -> 13.145761 | AS7: =+VLOOKUP(B7,'Country & Code Abbreviation'!$B$3:$C$245,2,FALSE) -> AL
B8: Algeria | C8: Africa | E8: =+VLOOKUP($B8,'[3]INT Web'!$B$5:$W$247,'[3]INT Web'!Q$1,FALSE) -> DZD | F8: =+VLOOKUP($B8,'[3]INT Web'!$B$5:$W$247,'[3]INT Web'!R$1,FALSE) -> 8099.99 | G8: =+VLOOKUP($B8,'[3]INT Web'!$B$5:$W$247,'[3]INT Web'!S$1,FALSE) -> 1349.99 | H8: =+VLOOKUP($B8,'[3]INT Web'!$B$5:$W$247,'[3]INT Web'!T$1,FALSE) -> 5999.99 | I8: =+VLOOKUP($B8,'[3]INT Web'!$B$5:$W$247,'[3]INT Web'!U$1,FALSE) -> 999.99 | J8: =+VLOOKUP($B8,'[3]INT Web'!$B$5:$W$247,'[3]INT Web'!V$1,FALSE) -> 5399.99 | K8: =+VLOOKUP($B8,'[3]INT Web'!$B$5:$W$247,'[3]INT Web'!W$1,FALSE) -> 899.99 | L8: =+F8/G8 -> 6.000037 | M8: =+G8/I8 -> 1.3500035 | N8: =+H8/I8 -> 6.00005 | O8: =+J8/K8 -> 6.0000556 | P8: =+K8/I8 -> 0.899999 | Q8: =+E8 -> DZD | R8: =+VLOOKUP($B8,'Country-Level Tactics'!$B$5:$AL$248,'Country-Level Tactics'!AH$1,FALSE) -> 8099.99 | S8: =+VLOOKUP($B8,'Country-Level Tactics'!$B$5:$AL$248,'Country-Level Tactics'!X$1,FALSE) -> 1349.99 | T8: =+VLOOKUP($B8,'Country-Level Tactics'!$B$5:$AL$248,'Country-Level Tactics'!AC$1,FALSE) -> 5999.99 | U8: =+VLOOKUP($B8,'Country-Level Tactics'!$B$5:$AL$248,'Country-Level Tactics'!T$1,FALSE) -> 999.99 | V8: =+J8 -> 5399.99 | W8: =+K8 -> 899.99 | X8: =+R8/S8 -> 6.000037 | Y8: =+S8/U8 -> 1.3500035 | Z8: =+T8/U8 -> 6.00005 | AA8: =+V8/W8 -> 6.0000556 | AB8: =+W8/U8 -> 0.899999 | AD8: =+R8/F8-1 -> 0 | AE8: =+S8/G8-1 -> 0 | AF8: =+T8/H8-1 -> 0 | AG8: =+U8/I8-1 -> 0 | AH8: =+V8/J8-1 -> 0 | AI8: =+W8/K8-1 -> 0 | AK8: {=_xll.FDS("","P_EXCH_RATE("&Q8&",USD,"&$AK$2&")")} -> 0.007511675 | AL8: =+R8*$AK8 -> 60.844492 | AM8: =+S8*$AK8 -> 10.140686 | AN8: =+T8*$AK8 -> 45.069975 | AO8: =+U8*$AK8 -> 7.5115999 | AP8: =+V8*$AK8 -> 40.56297 | AQ8: =+W8*$AK8 -> 6.7604324 | AS8: =+VLOOKUP(B8,'Country & Code Abbreviation'!$B$3:$C$245,2,FALSE) -> DZ
B9: American Samoa | C9: Asia | E9: =+VLOOKUP($B9,'[3]INT Web'!$B$5:$W$247,'[3]INT Web'!Q$1,FALSE) -> USD | F9: =+VLOOKUP($B9,'[3]INT Web'!$B$5:$W$247,'[3]INT Web'!R$1,FALSE) -> 129.99 | G9: =+VLOOKUP($B9,'[3]INT Web'!$B$5:$W$247,'[3]INT Web'!S$1,FALSE) -> 18.99 | H9: =+VLOOKUP($B9,'[3]INT Web'!$B$5:$W$247,'[3]INT Web'!T$1,FALSE) -> 83.99 | I9: =+VLOOKUP($B9,'[3]INT Web'!$B$5:$W$247,'[3]INT Web'!U$1,FALSE) -> 13.99 | J9: =+VLOOKUP($B9,'[3]INT Web'!$B$5:$W$247,'[3]INT Web'!V$1,FALSE) -> 77.99 | K9: =+VLOOKUP($B9,'[3]INT Web'!$B$5:$W$247,'[3]INT Web'!W$1,FALSE) -> 12.99 | L9: =+F9/G9 -> 6.8451817 | M9: =+G9/I9 -> 1.3573981 | N9: =+H9/I9 -> 6.003574 | O9: =+J9/K9 -> 6.0038491 | P9: =+K9/I9 -> 0.92852037 | Q9: =+E9 -> USD | R9: =+VLOOKUP($B9,'Country-Level Tactics'!$B$5:$AL$248,'Country-Level Tactics'!AH$1,FALSE) -> 129.99 | S9: =+VLOOKUP($B9,'Country-Level Tactics'!$B$5:$AL$248,'Country-Level Tactics'!X$1,FALSE) -> 18.99 | T9: =+VLOOKUP($B9,'Country-Level Tactics'!$B$5:$AL$248,'Country-Level Tactics'!AC$1,FALSE) -> 83.99 | U9: =+VLOOKUP($B9,'Country-Level Tactics'!$B$5:$AL$248,'Country-Level Tactics'!T$1,FALSE) -> 13.99 | V9: =+J9 -> 77.99 | W9: =+K9 -> 12.99 | X9: =+R9/S9 -> 6.8451817 | Y9: =+S9/U9 -> 1.3573981 | Z9: =+T9/U9 -> 6.003574 | AA9: =+V9/W9 -> 6.0038491 | AB9: =+W9/U9 -> 0.92852037 | AD9: =+R9/F9-1 -> 0 | AE9: =+S9/G9-1 -> 0 | AF9: =+T9/H9-1 -> 0 | AG9: =+U9/I9-1 -> 0 | AH9: =+V9/J9-1 -> 0 | AI9: =+W9/K9-1 -> 0 | AK9: {=_xll.FDS("","P_EXCH_RATE("&Q9&",USD,"&$AK$2&")")} -> 1 | AL9: =+R9*$AK9 -> 129.99 | AM9: =+S9*$AK9 -> 18.99 | AN9: =+T9*$AK9 -> 83.99 | AO9: =+U9*$AK9 -> 13.99 | AP9: =+V9*$AK9 -> 77.99 | AQ9: =+W9*$AK9 -> 12.99 | AS9: =+VLOOKUP(B9,'Country & Code Abbreviation'!$B$3:$C$245,2,FALSE) -> AS
B10: Andorra | C10: Europe | E10: =+VLOOKUP($B10,'[3]INT Web'!$B$5:$W$247,'[3]INT Web'!Q$1,FALSE) -> EUR | F10: =+VLOOKUP($B10,'[3]INT Web'!$B$5:$W$247,'[3]INT Web'!R$1,FALSE) -> 159.99 | G10: =+VLOOKUP($B10,'[3]INT Web'!$B$5:$W$247,'[3]INT Web'!S$1,FALSE) -> 22.99 | H10: =+VLOOKUP($B10,'[3]INT Web'!$B$5:$W$247,'[3]INT Web'!T$1,FALSE) -> 109.99 | I10: =+VLOOKUP($B10,'[3]INT Web'!$B$5:$W$247,'[3]INT Web'!U$1,FALSE) -> 17.99 | J10: =+VLOOKUP($B10,'[3]INT Web'!$B$5:$W$247,'[3]INT Web'!V$1,FALSE) -> 99.99 | K10: =+VLOOKUP($B10,'[3]INT Web'!$B$5:$W$247,'[3]INT Web'!W$1,FALSE) -> 15.99 | L10: =+F10/G10 -> 6.9591127 | M10: =+G10/I10 -> 1.2779322 | N10: =+H10/I10 -> 6.1139522 | O10: =+J10/K10 -> 6.2532833 | P10: =+K10/I10 -> 0.88882713 | Q10: =+E10 -> EUR | R10: =+VLOOKUP($B10,'Country-Level Tactics'!$B$5:$AL$248,'Country-Level Tactics'!AH$1,FALSE) -> 159.99 | S10: =+VLOOKUP($B10,'Country-Level Tactics'!$B$5:$AL$248,'Country-Level Tactics'!X$1,FALSE) -> 22.99 | T10: =+VLOOKUP($B10,'Country-Level Tactics'!$B$5:$AL$248,'Country-Level Tactics'!AC$1,FALSE) -> 109.99 | U10: =+VLOOKUP($B10,'Country-Level Tactics'!$B$5:$AL$248,'Country-Level Tactics'!T$1,FALSE) -> 17.99 | V10: =+J10 -> 99.99 | W10: =+K10 -> 15.99 | X10: =+R10/S10 -> 6.9591127 | Y10: =+S10/U10 -> 1.2779322 | Z10: =+T10/U10 -> 6.1139522 | AA10: =+V10/W10 -> 6.2532833 | AB10: =+W10/U10 -> 0.88882713 | AD10: =+R10/F10-1 -> 0 | AE10: =+S10/G10-1 -> 0 | AF10: =+T10/H10-1 -> 0 | AG10: =+U10/I10-1 -> 0 | AH10: =+V10/J10-1 -> 0 | AI10: =+W10/K10-1 -> 0 | AK10: {=_xll.FDS("","P_EXCH_RATE("&Q10&",USD,"&$AK$2&")")} -> 1.14175 | AL10: =+R10*$AK10 -> 182.66858 | AM10: =+S10*$AK10 -> 26.248832 | AN10: =+T10*$AK10 -> 125.58108 | AO10: =+U10*$AK10 -> 20.540083 | AP10: =+V10*$AK10 -> 114.16358 | AQ10: =+W10*$AK10 -> 18.256583 | AS10: =+VLOOKUP(B10,'Country & Code Abbreviation'!$B$3:$C$245,2,FALSE) -> AD
B11: Angola | C11: Africa | E11: =+VLOOKUP($B11,'[3]INT Web'!$B$5:$W$247,'[3]INT Web'!Q$1,FALSE) -> USD | F11: =+VLOOKUP($B11,'[3]INT Web'!$B$5:$W$247,'[3]INT Web'!R$1,FALSE) -> 71.99 | G11: =+VLOOKUP($B11,'[3]INT Web'!$B$5:$W$247,'[3]INT Web'!S$1,FALSE) -> 11.99 | H11: =+VLOOKUP($B11,'[3]INT Web'!$B$5:$W$247,'[3]INT Web'!T$1,FALSE) -> 53.99 | I11: =+VLOOKUP($B11,'[3]INT Web'!$B$5:$W$247,'[3]INT Web'!U$1,FALSE) -> 8.99 | J11: =+VLOOKUP($B11,'[3]INT Web'!$B$5:$W$247,'[3]INT Web'!V$1,FALSE) -> 47.99 | K11: =+VLOOKUP($B11,'[3]INT Web'!$B$5:$W$247,'[3]INT Web'!W$1,FALSE) -> 7.99 | L11: =+F11/G11 -> 6.0041701 | M11: =+G11/I11 -> 1.3337041 | N11: =+H11/I11 -> 6.0055617 | O11: =+J11/K11 -> 6.0062578 | P11: =+K11/I11 -> 0.88876529 | Q11: =+E11 -> USD | R11: =+VLOOKUP($B11,'Country-Level Tactics'!$B$5:$AL$248,'Country-Level Tactics'!AH$1,FALSE) -> 71.99 | S11: =+VLOOKUP($B11,'Country-Level Tactics'!$B$5:$AL$248,'Country-Level Tactics'!X$1,FALSE) -> 11.99 | T11: =+VLOOKUP($B11,'Country-Level Tactics'!$B$5:$AL$248,'Country-Level Tactics'!AC$1,FALSE) -> 53.99 | U11: =+VLOOKUP($B11,'Country-Level Tactics'!$B$5:$AL$248,'Country-Level Tactics'!T$1,FALSE) -> 8.99 | V11: =+J11 -> 47.99 | W11: =+K11 -> 7.99 | X11: =+R11/S11 -> 6.0041701 | Y11: =+S11/U11 -> 1.3337041 | Z11: =+T11/U11 -> 6.0055617 | AA11: =+V11/W11 -> 6.0062578 | AB11: =+W11/U11 -> 0.88876529 | AD11: =+R11/F11-1 -> 0 | AE11: =+S11/G11-1 -> 0 | AF11: =+T11/H11-1 -> 0 | AG11: =+U11/I11-1 -> 0 | AH11: =+V11/J11-1 -> 0 | AI11: =+W11/K11-1 -> 0 | AK11: {=_xll.FDS("","P_EXCH_RATE("&Q11&",USD,"&$AK$2&")")} -> 1 | AL11: =+R11*$AK11 -> 71.99 | AM11: =+S11*$AK11 -> 11.99 | AN11: =+T11*$AK11 -> 53.99 | AO11: =+U11*$AK11 -> 8.99 | AP11: =+V11*$AK11 -> 47.99 | AQ11: =+W11*$AK11 -> 7.99 | AS11: =+VLOOKUP(B11,'Country & Code Abbreviation'!$B$3:$C$245,2,FALSE) -> AO
B12: Anguilla | C12: Latin America | E12: =+VLOOKUP($B12,'[3]INT Web'!$B$5:$W$247,'[3]INT Web'!Q$1,FALSE) -> XCD | F12: =+VLOOKUP($B12,'[3]INT Web'!$B$5:$W$247,'[3]INT Web'!R$1,FALSE) -> 269.99 | G12: =+VLOOKUP($B12,'[3]INT Web'!$B$5:$W$247,'[3]INT Web'!S$1,FALSE) -> 44.99 | H12: =+VLOOKUP($B12,'[3]INT Web'!$B$5:$W$247,'[3]INT Web'!T$1,FALSE) -> 197.99 | I12: =+VLOOKUP($B12,'[3]INT Web'!$B$5:$W$247,'[3]INT Web'!U$1,FALSE) -> 32.99 | J12: =+VLOOKUP($B12,'[3]INT Web'!$B$5:$W$247,'[3]INT Web'!V$1,FALSE) -> 179.99 | K12: =+VLOOKUP($B12,'[3]INT Web'!$B$5:$W$247,'[3]INT Web'!W$1,FALSE) -> 29.99 | L12: =+F12/G12 -> 6.0011114 | M12: =+G12/I12 -> 1.3637466 | N12: =+H12/I12 -> 6.0015156 | O12: =+J12/K12 -> 6.0016672 | P12: =+K12/I12 -> 0.90906335 | Q12: =+E12 -> XCD | R12: =+VLOOKUP($B12,'Country-Level Tactics'!$B$5:$AL$248,'Country-Level Tactics'!AH$1,FALSE) -> 269.99 | S12: =+VLOOKUP($B12,'Country-Level Tactics'!$B$5:$AL$248,'Country-Level Tactics'!X$1,FALSE) -> 44.99 | T12: =+VLOOKUP($B12,'Country-Level Tactics'!$B$5:$AL$248,'Country-Level Tactics'!AC$1,FALSE) -> 197.99 | U12: =+VLOOKUP($B12,'Country-Level Tactics'!$B$5:$AL$248,'Country-Level Tactics'!T$1,FALSE) -> 32.99 | V12: =+J12 -> 179.99 | W12: =+K12 -> 29.99 | X12: =+R12/S12 -> 6.0011114 | Y12: =+S12/U12 -> 1.3637466 | Z12: =+T12/U12 -> 6.0015156 | AA12: =+V12/W12 -> 6.0016672 | AB12: =+W12/U12 -> 0.90906335 | AD12: =+R12/F12-1 -> 0 | AE12: =+S12/G12-1 -> 0 | AF12: =+T12/H12-1 -> 0 | AG12: =+U12/I12-1 -> 0 | AH12: =+V12/J12-1 -> 0 | AI12: =+W12/K12-1 -> 0 | AK12: {=_xll.FDS("","P_EXCH_RATE("&Q12&",USD,"&$AK$2&")")} -> 0.37037036 | AL12: =+R12*$AK12 -> 99.996293 | AM12: =+S12*$AK12 -> 16.662962 | AN12: =+T12*$AK12 -> 73.329628 | AO12: =+U12*$AK12 -> 12.218518 | AP12: =+V12*$AK12 -> 66.662961 | AQ12: =+W12*$AK12 -> 11.107407 | AS12: =+VLOOKUP(B12,'Country & Code Abbreviation'!$B$3:$C$245,2,FALSE) -> AI
B13: Antarctica | C13: Europe | E13: =+VLOOKUP($B13,'[3]INT Web'!$B$5:$W$247,'[3]INT Web'!Q$1,FALSE) -> USD | F13: =+VLOOKUP($B13,'[3]INT Web'!$B$5:$W$247,'[3]INT Web'!R$1,FALSE) -> 154.99 | G13: =+VLOOKUP($B13,'[3]INT Web'!$B$5:$W$247,'[3]INT Web'!S$1,FALSE) -> 21.99 | H13: =+VLOOKUP($B13,'[3]INT Web'!$B$5:$W$247,'[3]INT Web'!T$1,FALSE) -> 99.99 | I13: =+VLOOKUP($B13,'[3]INT Web'!$B$5:$W$247,'[3]INT Web'!U$1,FALSE) -> 16.99 | J13: =+VLOOKUP($B13,'[3]INT Web'!$B$5:$W$247,'[3]INT Web'!V$1,FALSE) -> 89.99 | K13: =+VLOOKUP($B13,'[3]INT Web'!$B$5:$W$247,'[3]INT Web'!W$1,FALSE) -> 14.99 | L13: =+F13/G13 -> 7.0482037 | M13: =+G13/I13 -> 1.2942908 | N13: =+H13/I13 -> 5.8852266 | O13: =+J13/K13 -> 6.0033356 | P13: =+K13/I13 -> 0.8822837 | Q13: =+E13 -> USD | R13: =+VLOOKUP($B13,'Country-Level Tactics'!$B$5:$AL$248,'Country-Level Tactics'!AH$1,FALSE) -> 154.99 | S13: =+VLOOKUP($B13,'Country-Level Tactics'!$B$5:$AL$248,'Country-Level Tactics'!X$1,FALSE) -> 21.99 | T13: =+VLOOKUP($B13,'Country-Level Tactics'!$B$5:$AL$248,'Country-Level Tactics'!AC$1,FALSE) -> 99.99 | U13: =+VLOOKUP($B13,'Country-Level Tactics'!$B$5:$AL$248,'Country-Level Tactics'!T$1,FALSE) -> 16.99 | V13: =+J13 -> 89.99 | W13: =+K13 -> 14.99 | X13: =+R13/S13 -> 7.0482037 | Y13: =+S13/U13 -> 1.2942908 | Z13: =+T13/U13 -> 5.8852266 | AA13: =+V13/W13 -> 6.0033356 | AB13: =+W13/U13 -> 0.8822837 | AD13: =+R13/F13-1 -> 0 | AE13: =+S13/G13-1 -> 0 | AF13: =+T13/H13-1 -> 0 | AG13: =+U13/I13-1 -> 0 | AH13: =+V13/J13-1 -> 0 | AI13: =+W13/K13-1 -> 0 | AK13: {=_xll.FDS("","P_EXCH_RATE("&Q13&",USD,"&$AK$2&")")} -> 1 | AL13: =+R13*$AK13 -> 154.99 | AM13: =+S13*$AK13 -> 21.99 | AN13: =+T13*$AK13 -> 99.99 | AO13: =+U13*$AK13 -> 16.99 | AP13: =+V13*$AK13 -> 89.99 | AQ13: =+W13*$AK13 -> 14.99 | AS13: =+VLOOKUP(B13,'Country & Code Abbreviation'!$B$3:$C$245,2,FALSE) -> AQ
B14: Antigua And Barbuda | C14: Latin America | E14: =+VLOOKUP($B14,'[3]INT Web'!$B$5:$W$247,'[3]INT Web'!Q$1,FALSE) -> XCD | F14: =+VLOOKUP($B14,'[3]INT Web'!$B$5:$W$247,'[3]INT Web'!R$1,FALSE) -> 305.99 | G14: =+VLOOKUP($B14,'[3]INT Web'!$B$5:$W$247,'[3]INT Web'!S$1,FALSE) -> 50.99 | H14: =+VLOOKUP($B14,'[3]INT Web'!$B$5:$W$247,'[3]INT Web'!T$1,FALSE) -> 227.99 | I14: =+VLOOKUP($B14,'[3]INT Web'!$B$5:$W$247,'[3]INT Web'!U$1,FALSE) -> 37.99 | J14: =+VLOOKUP($B14,'[3]INT Web'!$B$5:$W$247,'[3]INT Web'!V$1,FALSE) -> 203.99 | K14: =+VLOOKUP($B14,'[3]INT Web'!$B$5:$W$247,'[3]INT Web'!W$1,FALSE) -> 33.99 | L14: =+F14/G14 -> 6.0009806 | M14: =+G14/I14 -> 1.3421953 | N14: =+H14/I14 -> 6.0013161 | O14: =+J14/K14 -> 6.001471 | P14: =+K14/I14 -> 0.89470913 | Q14: =+E14 -> XCD | R14: =+VLOOKUP($B14,'Country-Level Tactics'!$B$5:$AL$248,'Country-Level Tactics'!AH$1,FALSE) -> 305.99 | S14: =+VLOOKUP($B14,'Country-Level Tactics'!$B$5:$AL$248,'Country-Level Tactics'!X$1,FALSE) -> 50.99 | T14: =+VLOOKUP($B14,'Country-Level Tactics'!$B$5:$AL$248,'Country-Level Tactics'!AC$1,FALSE) -> 227.99 | U14: =+VLOOKUP($B14,'Country-Level Tactics'!$B$5:$AL$248,'Country-Level Tactics'!T$1,FALSE) -> 37.99 | V14: =+J14 -> 203.99 | W14: =+K14 -> 33.99 | X14: =+R14/S14 -> 6.0009806 | Y14: =+S14/U14 -> 1.3421953 | Z14: =+T14/U14 -> 6.0013161 | AA14: =+V14/W14 -> 6.001471 | AB14: =+W14/U14 -> 0.89470913 | AD14: =+R14/F14-1 -> 0 | AE14: =+S14/G14-1 -> 0 | AF14: =+T14/H14-1 -> 0 | AG14: =+U14/I14-1 -> 0 | AH14: =+V14/J14-1 -> 0 | AI14: =+W14/K14-1 -> 0 | AK14: {=_xll.FDS("","P_EXCH_RATE("&Q14&",USD,"&$AK$2&")")} -> 0.37037036 | AL14: =+R14*$AK14 -> 113.32963 | AM14: =+S14*$AK14 -> 18.885185 | AN14: =+T14*$AK14 -> 84.440738 | AO14: =+U14*$AK14 -> 14.07037 | AP14: =+V14*$AK14 -> 75.55185 | AQ14: =+W14*$AK14 -> 12.588889 | AS14: =+VLOOKUP(B14,'Country & Code Abbreviation'!$B$3:$C$245,2,FALSE) -> AG
B15: Argentina | C15: Latin America | D15: C | E15: =+VLOOKUP($B15,'[3]INT Web'!$B$5:$W$247,'[3]INT Web'!Q$1,FALSE) -> ARS | F15: =+VLOOKUP($B15,'[3]INT Web'!$B$5:$W$247,'[3]INT Web'!R$1,FALSE) -> 206519.99 | G15: =+VLOOKUP($B15,'[3]INT Web'!$B$5:$W$247,'[3]INT Web'!S$1,FALSE) -> 34419.99 | H15: =+VLOOKUP($B15,'[3]INT Web'!$B$5:$W$247,'[3]INT Web'!T$1,FALSE) -> 163899.99 | I15: =+VLOOKUP($B15,'[3]INT Web'!$B$5:$W$247,'[3]INT Web'!U$1,FALSE) -> 26819.985 | J15: =+VLOOKUP($B15,'[3]INT Web'!$B$5:$W$247,'[3]INT Web'!V$1,FALSE) -> 145279.99 | K15: =+VLOOKUP($B15,'[3]INT Web'!$B$5:$W$247,'[3]INT Web'!W$1,FALSE) -> 23839.985 | L15: =+F15/G15 -> 6.0000015 | M15: =+G15/I15 -> 1.283371 | N15: =+H15/I15 -> 6.111114 | O15: =+J15/K15 -> 6.0939631 | P15: =+K15/I15 -> 0.88888883 | Q15: USD | R15: =+VLOOKUP($B15,'Country-Level Tactics'!$B$5:$AL$248,'Country-Level Tactics'!AH$1,FALSE) -> 79.99 | S15: =+VLOOKUP($B15,'Country-Level Tactics'!$B$5:$AL$248,'Country-Level Tactics'!X$1,FALSE) -> 12.99 | T15: =+VLOOKUP($B15,'Country-Level Tactics'!$B$5:$AL$248,'Country-Level Tactics'!AC$1,FALSE) -> 59.99 | U15: =+VLOOKUP($B15,'Country-Level Tactics'!$B$5:$AL$248,'Country-Level Tactics'!T$1,FALSE) -> 9.99 | V15: =+MROUND(T15*P15,1)-0.01 -> 52.99 | W15: =+MROUND(U15*P15,1)-0.01 -> 8.99 | X15: =+R15/S15 -> 6.1578137 | Y15: =+S15/U15 -> 1.3003003 | Z15: =+T15/U15 -> 6.005005 | AA15: =+V15/W15 -> 5.894327 | AB15: =+W15/U15 -> 0.8998999 | AD15: =+R15/F15-1 -> -0.99961268 | AE15: =+S15/G15-1 -> -0.9996226 | AF15: =+T15/H15-1 -> -0.99963398 | AG15: =+U15/I15-1 -> -0.99962752 | AH15: =+V15/J15-1 -> -0.99963526 | AI15: =+W15/K15-1 -> -0.9996229 | AK15: {=_xll.FDS("","P_EXCH_RATE("&Q15&",USD,"&$AK$2&")")} -> 1 | AL15: =+R15*$AK15 -> 79.99 | AM15: =+S15*$AK15 -> 12.99 | AN15: =+T15*$AK15 -> 59.99 | AO15: =+U15*$AK15 -> 9.99 | AP15: =+V15*$AK15 -> 52.99 | AQ15: =+W15*$AK15 -> 8.99 | AS15: =+VLOOKUP(B15,'Country & Code Abbreviation'!$B$3:$C$245,2,FALSE) -> AR
B16: Armenia | C16: Middle East | E16: =+VLOOKUP($B16,'[3]INT Web'!$B$5:$W$247,'[3]INT Web'!Q$1,FALSE) -> AMD | F16: =+VLOOKUP($B16,'[3]INT Web'!$B$5:$W$247,'[3]INT Web'!R$1,FALSE) -> 54269.99 | G16: =+VLOOKUP($B16,'[3]INT Web'!$B$5:$W$247,'[3]INT Web'!S$1,FALSE) -> 9039.99 | H16: =+VLOOKUP($B16,'[3]INT Web'!$B$5:$W$247,'[3]INT Web'!T$1,FALSE) -> 40199.99 | I16: =+VLOOKUP($B16,'[3]INT Web'!$B$5:$W$247,'[3]INT Web'!U$1,FALSE) -> 6699.99 | J16: =+VLOOKUP($B16,'[3]INT Web'!$B$5:$W$247,'[3]INT Web'!V$1,FALSE) -> 36179.99 | K16: =+VLOOKUP($B16,'[3]INT Web'!$B$5:$W$247,'[3]INT Web'!W$1,FALSE) -> 6029.99 | L16: =+F16/G16 -> 6.0033241 | M16: =+G16/I16 -> 1.3492543 | N16: =+H16/I16 -> 6.0000075 | O16: =+J16/K16 -> 6.0000083 | P16: =+K16/I16 -> 0.89999985 | Q16: =+E16 -> AMD | R16: =+VLOOKUP($B16,'Country-Level Tactics'!$B$5:$AL$248,'Country-Level Tactics'!AH$1,FALSE) -> 54269.99 | S16: =+VLOOKUP($B16,'Country-Level Tactics'!$B$5:$AL$248,'Country-Level Tactics'!X$1,FALSE) -> 9039.99 | T16: =+VLOOKUP($B16,'Country-Level Tactics'!$B$5:$AL$248,'Country-Level Tactics'!AC$1,FALSE) -> 40199.99 | U16: =+VLOOKUP($B16,'Country-Level Tactics'!$B$5:$AL$248,'Country-Level Tactics'!T$1,FALSE) -> 6699.99 | V16: =+J16 -> 36179.99 | W16: =+K16 -> 6029.99 | X16: =+R16/S16 -> 6.0033241 | Y16: =+S16/U16 -> 1.3492543 | Z16: =+T16/U16 -> 6.0000075 | AA16: =+V16/W16 -> 6.0000083 | AB16: =+W16/U16 -> 0.89999985 | AD16: =+R16/F16-1 -> 0 | AE16: =+S16/G16-1 -> 0 | AF16: =+T16/H16-1 -> 0 | AG16: =+U16/I16-1 -> 0 | AH16: =+V16/J16-1 -> 0 | AI16: =+W16/K16-1 -> 0 | AK16: {=_xll.FDS("","P_EXCH_RATE("&Q16&",USD,"&$AK$2&")")} -> 0.0027159413 | AL16: =+R16*$AK16 -> 147.39411 | AM16: =+S16*$AK16 -> 24.552082 | AN16: =+T16*$AK16 -> 109.18081 | AO16: =+U16*$AK16 -> 18.19678 | AP16: =+V16*$AK16 -> 98.262729 | AQ16: =+W15*$AK16 -> 0.024416312 | AS16: =+VLOOKUP(B16,'Country & Code Abbreviation'!$B$3:$C$245,2,FALSE) -> AM
B17: Aruba | C17: Latin America | E17: =+VLOOKUP($B17,'[3]INT Web'!$B$5:$W$247,'[3]INT Web'!Q$1,FALSE) -> AWG | F17: =+VLOOKUP($B17,'[3]INT Web'!$B$5:$W$247,'[3]INT Web'!R$1,FALSE) -> 179.99 | G17: =+VLOOKUP($B17,'[3]INT Web'!$B$5:$W$247,'[3]INT Web'!S$1,FALSE) -> 29.99 | H17: =+VLOOKUP($B17,'[3]INT Web'!$B$5:$W$247,'[3]INT Web'!T$1,FALSE) -> 131.99 | I17: =+VLOOKUP($B17,'[3]INT Web'!$B$5:$W$247,'[3]INT Web'!U$1,FALSE) -> 21.99 | J17: =+VLOOKUP($B17,'[3]INT Web'!$B$5:$W$247,'[3]INT Web'!V$1,FALSE) -> 119.99 | K17: =+VLOOKUP($B17,'[3]INT Web'!$B$5:$W$247,'[3]INT Web'!W$1,FALSE) -> 19.99 | L17: =+F17/G17 -> 6.0016672 | M17: =+G17/I17 -> 1.3638017 | N17: =+H17/I17 -> 6.0022738 | O17: =+J17/K17 -> 6.0025013 | P17: =+K17/I17 -> 0.90904957 | Q17: =+E17 -> AWG | R17: =+VLOOKUP($B17,'Country-Level Tactics'!$B$5:$AL$248,'Country-Level Tactics'!AH$1,FALSE) -> 179.99 | S17: =+VLOOKUP($B17,'Country-Level Tactics'!$B$5:$AL$248,'Country-Level Tactics'!X$1,FALSE) -> 29.99 | T17: =+VLOOKUP($B17,'Country-Level Tactics'!$B$5:$AL$248,'Country-Level Tactics'!AC$1,FALSE) -> 131.99 | U17: =+VLOOKUP($B17,'Country-Level Tactics'!$B$5:$AL$248,'Country-Level Tactics'!T$1,FALSE) -> 21.99 | V17: =+J17 -> 119.99 | W17: =+K17 -> 19.99 | X17: =+R17/S17 -> 6.0016672 | Y17: =+S17/U17 -> 1.3638017 | Z17: =+T17/U17 -> 6.0022738 | AA17: =+V17/W17 -> 6.0025013 | AB17: =+W17/U17 -> 0.90904957 | AD17: =+R17/F17-1 -> 0 | AE17: =+S17/G17-1 -> 0 | AF17: =+T17/H17-1 -> 0 | AG17: =+U17/I17-1 -> 0 | AH17: =+V17/J17-1 -> 0 | AI17: =+W17/K17-1 -> 0 | AK17: {=_xll.FDS("","P_EXCH_RATE("&Q17&",USD,"&$AK$2&")")} -> 0.55865926 | AL17: =+R17*$AK17 -> 100.55308 | AM17: =+S17*$AK17 -> 16.754191 | AN17: =+T17*$AK17 -> 73.737436 | AO17: =+U17*$AK17 -> 12.284917 | AP17: =+V17*$AK17 -> 67.033525 | AQ17: =+W17*$AK17 -> 11.167599 | AS17: =+VLOOKUP(B17,'Country & Code Abbreviation'!$B$3:$C$245,2,FALSE) -> AW
B18: Australia | C18: Asia | D18: B | E18: =+VLOOKUP($B18,'[3]INT Web'!$B$5:$W$247,'[3]INT Web'!Q$1,FALSE) -> AUD | F18: =+VLOOKUP($B18,'[3]INT Web'!$B$5:$W$247,'[3]INT Web'!R$1,FALSE) -> 229.99 | G18: =+VLOOKUP($B18,'[3]INT Web'!$B$5:$W$247,'[3]INT Web'!S$1,FALSE) -> 32.99 | H18: =+VLOOKUP($B18,'[3]INT Web'!$B$5:$W$247,'[3]INT Web'!T$1,FALSE) -> 174.99 | I18: =+VLOOKUP($B18,'[3]INT Web'!$B$5:$W$247,'[3]INT Web'!U$1,FALSE) -> 24.99 | J18: =+VLOOKUP($B18,'[3]INT Web'!$B$5:$W$247,'[3]INT Web'!V$1,FALSE) -> 153.99 | K18: =+VLOOKUP($B18,'[3]INT Web'!$B$5:$W$247,'[3]INT Web'!W$1,FALSE) -> 21.99 | L18: =+F18/G18 -> 6.9715065 | M18: =+G18/I18 -> 1.3201281 | N18: =+H18/I18 -> 7.002401 | O18: =+J18/K18 -> 7.0027285 | P18: =+K18/I18 -> 0.87995198 | Q18: =+E18 -> AUD | R18: =+VLOOKUP($B18,'Country-Level Tactics'!$B$5:$AL$248,'Country-Level Tactics'!AH$1,FALSE) -> 244.99 | S18: =+VLOOKUP($B18,'Country-Level Tactics'!$B$5:$AL$248,'Country-Level Tactics'!X$1,FALSE) -> 34.99 | T18: =+VLOOKUP($B18,'Country-Level Tactics'!$B$5:$AL$248,'Country-Level Tactics'!AC$1,FALSE) -> 174.99 | U18: =+VLOOKUP($B18,'Country-Level Tactics'!$B$5:$AL$248,'Country-Level Tactics'!T$1,FALSE) -> 24.99 | V18: =+J18 -> 153.99 | W18: =+K18 -> 21.99 | X18: =+R18/S18 -> 7.0017148 | Y18: =+S18/U18 -> 1.4001601 | Z18: =+T18/U18 -> 7.002401 | AA18: =+V18/W18 -> 7.0027285 | AB18: =+W18/U18 -> 0.87995198 | AD18: =+R18/F18-1 -> 0.065220227 | AE18: =+S18/G18-1 -> 0.060624432 | AF18: =+T18/H18-1 -> 0 | AG18: =+U18/I18-1 -> 0 | AH18: =+V18/J18-1 -> 0 | AI18: =+W18/K18-1 -> 0 | AK18: {=_xll.FDS("","P_EXCH_RATE("&Q18&",USD,"&$AK$2&")")} -> 0.69375 | AL18: =+R18*$AK18 -> 169.96181 | AM18: =+S18*$AK18 -> 24.274313 | AN18: =+T18*$AK18 -> 121.39931 | AO18: =+U18*$AK18 -> 17.336812 | AP18: =+V18*$AK18 -> 106.83056 | AQ18: =+W18*$AK18 -> 15.255562 | AS18: =+VLOOKUP(B18,'Country & Code Abbreviation'!$B$3:$C$245,2,FALSE) -> AU
B19: Austria | C19: Europe | E19: =+VLOOKUP($B19,'[3]INT Web'!$B$5:$W$247,'[3]INT Web'!Q$1,FALSE) -> EUR | F19: =+VLOOKUP($B19,'[3]INT Web'!$B$5:$W$247,'[3]INT Web'!R$1,FALSE) -> 159.99 | G19: =+VLOOKUP($B19,'[3]INT Web'!$B$5:$W$247,'[3]INT Web'!S$1,FALSE) -> 23.99 | H19: =+VLOOKUP($B19,'[3]INT Web'!$B$5:$W$247,'[3]INT Web'!T$1,FALSE) -> 116.99 | I19: =+VLOOKUP($B19,'[3]INT Web'!$B$5:$W$247,'[3]INT Web'!U$1,FALSE) -> 17.99 | J19: =+VLOOKUP($B19,'[3]INT Web'!$B$5:$W$247,'[3]INT Web'!V$1,FALSE) -> 104.99 | K19: =+VLOOKUP($B19,'[3]INT Web'!$B$5:$W$247,'[3]INT Web'!W$1,FALSE) -> 15.99 | L19: =+F19/G19 -> 6.6690288 | M19: =+G19/I19 -> 1.3335186 | N19: =+H19/I19 -> 6.5030573 | O19: =+J19/K19 -> 6.5659787 | P19: =+K19/I19 -> 0.88882713 | Q19: =+E19 -> EUR | R19: =+VLOOKUP($B19,'Country-Level Tactics'!$B$5:$AL$248,'Country-Level Tactics'!AH$1,FALSE) -> 159.99 | S19: =+VLOOKUP($B19,'Country-Level Tactics'!$B$5:$AL$248,'Country-Level Tactics'!X$1,FALSE) -> 23.99 | T19: =+VLOOKUP($B19,'Country-Level Tactics'!$B$5:$AL$248,'Country-Level Tactics'!AC$1,FALSE) -> 116.99 | U19: =+VLOOKUP($B19,'Country-Level Tactics'!$B$5:$AL$248,'Country-Level Tactics'!T$1,FALSE) -> 17.99 | V19: =+J19 -> 104.99 | W19: =+K19 -> 15.99 | X19: =+R19/S19 -> 6.6690288 | Y19: =+S19/U19 -> 1.3335186 | Z19: =+T19/U19 -> 6.5030573 | AA19: =+V19/W19 -> 6.5659787 | AB19: =+W19/U19 -> 0.88882713 | AD19: =+R19/F19-1 -> 0 | AE19: =+S19/G19-1 -> 0 | AF19: =+T19/H19-1 -> 0 | AG19: =+U19/I19-1 -> 0 | AH19: =+V19/J19-1 -> 0 | AI19: =+W19/K19-1 -> 0 | AK19: {=_xll.FDS("","P_EXCH_RATE("&Q19&",USD,"&$AK$2&")")} -> 1.14175 | AL19: =+R19*$AK19 -> 182.66858 | AM19: =+S19*$AK19 -> 27.390583 | AN19: =+T19*$AK19 -> 133.57333 | AO19: =+U19*$AK19 -> 20.540083 | AP19: =+V19*$AK19 -> 119.87233 | AQ19: =+W19*$AK19 -> 18.256583 | AS19: =+VLOOKUP(B19,'Country & Code Abbreviation'!$B$3:$C$245,2,FALSE) -> AT
B20: Azerbaijan | C20: Middle East | E20: =+VLOOKUP($B20,'[3]INT Web'!$B$5:$W$247,'[3]INT Web'!Q$1,FALSE) -> AZN | F20: =+VLOOKUP($B20,'[3]INT Web'!$B$5:$W$247,'[3]INT Web'!R$1,FALSE) -> 179.99 | G20: =+VLOOKUP($B20,'[3]INT Web'!$B$5:$W$247,'[3]INT Web'!S$1,FALSE) -> 29.99 | H20: =+VLOOKUP($B20,'[3]INT Web'!$B$5:$W$247,'[3]INT Web'!T$1,FALSE) -> 129.99 | I20: =+VLOOKUP($B20,'[3]INT Web'!$B$5:$W$247,'[3]INT Web'!U$1,FALSE) -> 21.99 | J20: =+VLOOKUP($B20,'[3]INT Web'!$B$5:$W$247,'[3]INT Web'!V$1,FALSE) -> 119.99 | K20: =+VLOOKUP($B20,'[3]INT Web'!$B$5:$W$247,'[3]INT Web'!W$1,FALSE) -> 19.99 | L20: =+F20/G20 -> 6.0016672 | M20: =+G20/I20 -> 1.3638017 | N20: =+H20/I20 -> 5.9113233 | O20: =+J20/K20 -> 6.0025013 | P20: =+K20/I20 -> 0.90904957 | Q20: =+E20 -> AZN | R20: =+VLOOKUP($B20,'Country-Level Tactics'!$B$5:$AL$248,'Country-Level Tactics'!AH$1,FALSE) -> 179.99 | S20: =+VLOOKUP($B20,'Country-Level Tactics'!$B$5:$AL$248,'Country-Level Tactics'!X$1,FALSE) -> 29.99 | T20: =+VLOOKUP($B20,'Country-Level Tactics'!$B$5:$AL$248,'Country-Level Tactics'!AC$1,FALSE) -> 129.99 | U20: =+VLOOKUP($B20,'Country-Level Tactics'!$B$5:$AL$248,'Country-Level Tactics'!T$1,FALSE) -> 21.99 | V20: =+J20 -> 119.99 | W20: =+K20 -> 19.99 | X20: =+R20/S20 -> 6.0016672 | Y20: =+S20/U20 -> 1.3638017 | Z20: =+T20/U20 -> 5.9113233 | AA20: =+V20/W20 -> 6.0025013 | AB20: =+W20/U20 -> 0.90904957 | AD20: =+R20/F20-1 -> 0 | AE20: =+S20/G20-1 -> 0 | AF20: =+T20/H20-1 -> 0 | AG20: =+U20/I20-1 -> 0 | AH20: =+V20/J20-1 -> 0 | AI20: =+W20/K20-1 -> 0 | AK20: {=_xll.FDS("","P_EXCH_RATE("&Q20&",USD,"&$AK$2&")")} -> 0.58823526 | AL20: =+R20*$AK20 -> 105.87646 | AM20: =+S20*$AK20 -> 17.641175 | AN20: =+T20*$AK20 -> 76.464701 | AO20: =+U20*$AK20 -> 12.935293 | AP20: =+V20*$AK20 -> 70.582349 | AQ20: =+W20*$AK20 -> 11.758823 | AS20: =+VLOOKUP(B20,'Country & Code Abbreviation'!$B$3:$C$245,2,FALSE) -> AZ
B21: Bahamas | C21: Latin America | E21: =+VLOOKUP($B21,'[3]INT Web'!$B$5:$W$247,'[3]INT Web'!Q$1,FALSE) -> BSD | F21: =+VLOOKUP($B21,'[3]INT Web'!$B$5:$W$247,'[3]INT Web'!R$1,FALSE) -> 95.99 | G21: =+VLOOKUP($B21,'[3]INT Web'!$B$5:$W$247,'[3]INT Web'!S$1,FALSE) -> 15.99 | H21: =+VLOOKUP($B21,'[3]INT Web'!$B$5:$W$247,'[3]INT Web'!T$1,FALSE) -> 71.99 | I21: =+VLOOKUP($B21,'[3]INT Web'!$B$5:$W$247,'[3]INT Web'!U$1,FALSE) -> 11.99 | J21: =+VLOOKUP($B21,'[3]INT Web'!$B$5:$W$247,'[3]INT Web'!V$1,FALSE) -> 65.99 | K21: =+VLOOKUP($B21,'[3]INT Web'!$B$5:$W$247,'[3]INT Web'!W$1,FALSE) -> 10.99 | L21: =+F21/G21 -> 6.003127 | M21: =+G21/I21 -> 1.3336113 | N21: =+H21/I21 -> 6.0041701 | O21: =+J21/K21 -> 6.0045496 | P21: =+K21/I21 -> 0.91659716 | Q21: =+E21 -> BSD | R21: =+VLOOKUP($B21,'Country-Level Tactics'!$B$5:$AL$248,'Country-Level Tactics'!AH$1,FALSE) -> 95.99 | S21: =+VLOOKUP($B21,'Country-Level Tactics'!$B$5:$AL$248,'Country-Level Tactics'!X$1,FALSE) -> 15.99 | T21: =+VLOOKUP($B21,'Country-Level Tactics'!$B$5:$AL$248,'Country-Level Tactics'!AC$1,FALSE) -> 71.99 | U21: =+VLOOKUP($B21,'Country-Level Tactics'!$B$5:$AL$248,'Country-Level Tactics'!T$1,FALSE) -> 11.99 | V21: =+J21 -> 65.99 | W21: =+K21 -> 10.99 | X21: =+R21/S21 -> 6.003127 | Y21: =+S21/U21 -> 1.3336113 | Z21: =+T21/U21 -> 6.0041701 | AA21: =+V21/W21 -> 6.0045496 | AB21: =+W21/U21 -> 0.91659716 | AD21: =+R21/F21-1 -> 0 | AE21: =+S21/G21-1 -> 0 | AF21: =+T21/H21-1 -> 0 | AG21: =+U21/I21-1 -> 0 | AH21: =+V21/J21-1 -> 0 | AI21: =+W21/K21-1 -> 0 | AK21: {=_xll.FDS("","P_EXCH_RATE("&Q21&",USD,"&$AK$2&")")} -> 1 | AL21: =+R21*$AK21 -> 95.99 | AM21: =+S21*$AK21 -> 15.99 | AN21: =+T21*$AK21 -> 71.99 | AO21: =+U21*$AK21 -> 11.99 | AP21: =+V21*$AK21 -> 65.99 | AQ21: =+W21*$AK21 -> 10.99 | AS21: =+VLOOKUP(B21,'Country & Code Abbreviation'!$B$3:$C$245,2,FALSE) -> BS
B22: Bahrain | C22: Middle East | E22: =+VLOOKUP($B22,'[3]INT Web'!$B$5:$W$247,'[3]INT Web'!Q$1,FALSE) -> BHD | F22: =+VLOOKUP($B22,'[3]INT Web'!$B$5:$W$247,'[3]INT Web'!R$1,FALSE) -> 59.999 | G22: =+VLOOKUP($B22,'[3]INT Web'!$B$5:$W$247,'[3]INT Web'!S$1,FALSE) -> 8.999 | H22: =+VLOOKUP($B22,'[3]INT Web'!$B$5:$W$247,'[3]INT Web'!T$1,FALSE) -> 49.999 | I22: =+VLOOKUP($B22,'[3]INT Web'!$B$5:$W$247,'[3]INT Web'!U$1,FALSE) -> 6.999 | J22: =+VLOOKUP($B22,'[3]INT Web'!$B$5:$W$247,'[3]INT Web'!V$1,FALSE) -> 39.999 | K22: =+VLOOKUP($B22,'[3]INT Web'!$B$5:$W$247,'[3]INT Web'!W$1,FALSE) -> 5.999 | L22: =+F22/G22 -> 6.6672964 | M22: =+G22/I22 -> 1.2857551 | N22: =+H22/I22 -> 7.1437348 | O22: =+J22/K22 -> 6.6676113 | P22: =+K22/I22 -> 0.85712245 | Q22: =+E22 -> BHD | R22: =+VLOOKUP($B22,'Country-Level Tactics'!$B$5:$AL$248,'Country-Level Tactics'!AH$1,FALSE) -> 59.999 | S22: =+VLOOKUP($B22,'Country-Level Tactics'!$B$5:$AL$248,'Country-Level Tactics'!X$1,FALSE) -> 8.999 | T22: =+VLOOKUP($B22,'Country-Level Tactics'!$B$5:$AL$248,'Country-Level Tactics'!AC$1,FALSE) -> 49.999 | U22: =+VLOOKUP($B22,'Country-Level Tactics'!$B$5:$AL$248,'Country-Level Tactics'!T$1,FALSE) -> 6.999 | V22: =+J22 -> 39.999 | W22: =+K22 -> 5.999 | X22: =+R22/S22 -> 6.6672964 | Y22: =+S22/U22 -> 1.2857551 | Z22: =+T22/U22 -> 7.1437348 | AA22: =+V22/W22 -> 6.6676113 | AB22: =+W22/U22 -> 0.85712245 | AD22: =+R22/F22-1 -> 0 | AE22: =+S22/G22-1 -> 0 | AF22: =+T22/H22-1 -> 0 | AG22: =+U22/I22-1 -> 0 | AH22: =+V22/J22-1 -> 0 | AI22: =+W22/K22-1 -> 0 | AK22: {=_xll.FDS("","P_EXCH_RATE("&Q22&",USD,"&$AK$2&")")} -> 2.65252 | AL22: =+R22*$AK22 -> 159.14855 | AM22: =+S22*$AK22 -> 23.870027 | AN22: =+T22*$AK22 -> 132.62335 | AO22: =+U22*$AK22 -> 18.564987 | AP22: =+V22*$AK22 -> 106.09815 | AQ22: =+W22*$AK22 -> 15.912467 | AS22: =+VLOOKUP(B22,'Country & Code Abbreviation'!$B$3:$C$245,2,FALSE) -> BH
B23: Bangladesh | C23: Asia | E23: =+VLOOKUP($B23,'[3]INT Web'!$B$5:$W$247,'[3]INT Web'!Q$1,FALSE) -> BDT | F23: =+VLOOKUP($B23,'[3]INT Web'!$B$5:$W$247,'[3]INT Web'!R$1,FALSE) -> 6071.99 | G23: =+VLOOKUP($B23,'[3]INT Web'!$B$5:$W$247,'[3]INT Web'!S$1,FALSE) -> 1011.99 | H23: =+VLOOKUP($B23,'[3]INT Web'!$B$5:$W$247,'[3]INT Web'!T$1,FALSE) -> 4499.99 | I23: =+VLOOKUP($B23,'[3]INT Web'!$B$5:$W$247,'[3]INT Web'!U$1,FALSE) -> 749.99 | J23: =+VLOOKUP($B23,'[3]INT Web'!$B$5:$W$247,'[3]INT Web'!V$1,FALSE) -> 4049.99 | K23: =+VLOOKUP($B23,'[3]INT Web'!$B$5:$W$247,'[3]INT Web'!W$1,FALSE) -> 674.99 | L23: =+F23/G23 -> 6.0000494 | M23: =+G23/I23 -> 1.349338 | N23: =+H23/I23 -> 6.0000667 | O23: =+J23/K23 -> 6.0000741 | P23: =+K23/I23 -> 0.89999867 | Q23: =+E23 -> BDT | R23: =+VLOOKUP($B23,'Country-Level Tactics'!$B$5:$AL$248,'Country-Level Tactics'!AH$1,FALSE) -> 6071.99 | S23: =+VLOOKUP($B23,'Country-Level Tactics'!$B$5:$AL$248,'Country-Level Tactics'!X$1,FALSE) -> 1011.99 | T23: =+VLOOKUP($B23,'Country-Level Tactics'!$B$5:$AL$248,'Country-Level Tactics'!AC$1,FALSE) -> 4499.99 | U23: =+VLOOKUP($B23,'Country-Level Tactics'!$B$5:$AL$248,'Country-Level Tactics'!T$1,FALSE) -> 749.99 | V23: =+J23 -> 4049.99 | W23: =+K23 -> 674.99 | X23: =+R23/S23 -> 6.0000494 | Y23: =+S23/U23 -> 1.349338 | Z23: =+T23/U23 -> 6.0000667 | AA23: =+V23/W23 -> 6.0000741 | AB23: =+W23/U23 -> 0.89999867 | AD23: =+R23/F23-1 -> 0 | AE23: =+S23/G23-1 -> 0 | AF23: =+T23/H23-1 -> 0 | AG23: =+U23/I23-1 -> 0 | AH23: =+V23/J23-1 -> 0 | AI23: =+W23/K23-1 -> 0 | AK23: 0.00811359 | AL23: =+R23*$AK23 -> 49.265637 | AM23: =+S23*$AK23 -> 8.2108719 | AN23: =+T23*$AK23 -> 36.511074 | AO23: =+U23*$AK23 -> 6.0851114 | AP23: =+V23*$AK23 -> 32.859958 | AQ23: =+W23*$AK23 -> 5.4765921 | AS23: =+VLOOKUP(B23,'Country & Code Abbreviation'!$B$3:$C$245,2,FALSE) -> BD
B24: Barbados | C24: Latin America | E24: =+VLOOKUP($B24,'[3]INT Web'!$B$5:$W$247,'[3]INT Web'!Q$1,FALSE) -> BBD | F24: =+VLOOKUP($B24,'[3]INT Web'!$B$5:$W$247,'[3]INT Web'!R$1,FALSE) -> 209.99 | G24: =+VLOOKUP($B24,'[3]INT Web'!$B$5:$W$247,'[3]INT Web'!S$1,FALSE) -> 34.99 | H24: =+VLOOKUP($B24,'[3]INT Web'!$B$5:$W$247,'[3]INT Web'!T$1,FALSE) -> 155.99 | I24: =+VLOOKUP($B24,'[3]INT Web'!$B$5:$W$247,'[3]INT Web'!U$1,FALSE) -> 25.99 | J24: =+VLOOKUP($B24,'[3]INT Web'!$B$5:$W$247,'[3]INT Web'!V$1,FALSE) -> 137.99 | K24: =+VLOOKUP($B24,'[3]INT Web'!$B$5:$W$247,'[3]INT Web'!W$1,FALSE) -> 22.99 | L24: =+F24/G24 -> 6.001429 | M24: =+G24/I24 -> 1.346287 | N24: =+H24/I24 -> 6.0019238 | O24: =+J24/K24 -> 6.0021749 | P24: =+K24/I24 -> 0.88457099 | Q24: =+E24 -> BBD | R24: =+VLOOKUP($B24,'Country-Level Tactics'!$B$5:$AL$248,'Country-Level Tactics'!AH$1,FALSE) -> 209.99 | S24: =+VLOOKUP($B24,'Country-Level Tactics'!$B$5:$AL$248,'Country-Level Tactics'!X$1,FALSE) -> 34.99 | T24: =+VLOOKUP($B24,'Country-Level Tactics'!$B$5:$AL$248,'Country-Level Tactics'!AC$1,FALSE) -> 155.99 | U24: =+VLOOKUP($B24,'Country-Level Tactics'!$B$5:$AL$248,'Country-Level Tactics'!T$1,FALSE) -> 25.99 | V24: =+J24 -> 137.99 | W24: =+K24 -> 22.99 | X24: =+R24/S24 -> 6.001429 | Y24: =+S24/U24 -> 1.346287 | Z24: =+T24/U24 -> 6.0019238 | AA24: =+V24/W24 -> 6.0021749 | AB24: =+W24/U24 -> 0.88457099 | AD24: =+R24/F24-1 -> 0 | AE24: =+S24/G24-1 -> 0 | AF24: =+T24/H24-1 -> 0 | AG24: =+U24/I24-1 -> 0 | AH24: =+V24/J24-1 -> 0 | AI24: =+W24/K24-1 -> 0 | AK24: 0.5 | AL24: =+R24*$AK24 -> 104.995 | AM24: =+S24*$AK24 -> 17.495 | AN24: =+T24*$AK24 -> 77.995 | AO24: =+U24*$AK24 -> 12.995 | AP24: =+V24*$AK24 -> 68.995 | AQ24: =+W24*$AK24 -> 11.495 | AS24: =+VLOOKUP(B24,'Country & Code Abbreviation'!$B$3:$C$245,2,FALSE) -> BB
B25: Belarus | C25: Europe | E25: =+VLOOKUP($B25,'[3]INT Web'!$B$5:$W$247,'[3]INT Web'!Q$1,FALSE) -> BYN | F25: =+VLOOKUP($B25,'[3]INT Web'!$B$5:$W$247,'[3]INT Web'!R$1,FALSE) -> 0 | G25: =+VLOOKUP($B25,'[3]INT Web'!$B$5:$W$247,'[3]INT Web'!S$1,FALSE) -> 0 | H25: =+VLOOKUP($B25,'[3]INT Web'!$B$5:$W$247,'[3]INT Web'!T$1,FALSE) -> 0 | I25: =+VLOOKUP($B25,'[3]INT Web'!$B$5:$W$247,'[3]INT Web'!U$1,FALSE) -> 0 | J25: =+VLOOKUP($B25,'[3]INT Web'!$B$5:$W$247,'[3]INT Web'!V$1,FALSE) -> 0 | K25: =+VLOOKUP($B25,'[3]INT Web'!$B$5:$W$247,'[3]INT Web'!W$1,FALSE) -> 0 | Q25: =+E25 -> BYN | R25: =+VLOOKUP($B25,'Country-Level Tactics'!$B$5:$AL$248,'Country-Level Tactics'!AH$1,FALSE) -> 0 | S25: =+VLOOKUP($B25,'Country-Level Tactics'!$B$5:$AL$248,'Country-Level Tactics'!X$1,FALSE) -> 0 | T25: =+VLOOKUP($B25,'Country-Level Tactics'!$B$5:$AL$248,'Country-Level Tactics'!AC$1,FALSE) -> 0 | U25: =+VLOOKUP($B25,'Country-Level Tactics'!$B$5:$AL$248,'Country-Level Tactics'!T$1,FALSE) -> 0 | V25: =+J25 -> 0 | W25: =+K25 -> 0 | X25: =+R25/S25 -> #DIV/0! | Y25: =+S25/U25 -> #DIV/0! | Z25: =+T25/U25 -> #DIV/0! | AA25: =+V25/W25 -> #DIV/0! | AB25: =+W25/U25 -> #DIV/0! | AD25: =+R25/F25-1 -> #DIV/0! | AE25: =+S25/G25-1 -> #DIV/0! | AF25: =+T25/H25-1 -> #DIV/0! | AG25: =+U25/I25-1 -> #DIV/0! | AH25: =+V25/J25-1 -> #DIV/0! | AI25: =+W25/K25-1 -> #DIV/0! | AK25: 0.34619445 | AS25: =+VLOOKUP(B25,'Country & Code Abbreviation'!$B$3:$C$245,2,FALSE) -> BY
B26: Belgium | C26: Europe | D26: E~ | E26: =+VLOOKUP($B26,'[3]INT Web'!$B$5:$W$247,'[3]INT Web'!Q$1,FALSE) -> EUR | F26: =+VLOOKUP($B26,'[3]INT Web'!$B$5:$W$247,'[3]INT Web'!R$1,FALSE) -> 169.99 | G26: =+VLOOKUP($B26,'[3]INT Web'!$B$5:$W$247,'[3]INT Web'!S$1,FALSE) -> 25.99 | H26: =+VLOOKUP($B26,'[3]INT Web'!$B$5:$W$247,'[3]INT Web'!T$1,FALSE) -> 124.99 | I26: =+VLOOKUP($B26,'[3]INT Web'!$B$5:$W$247,'[3]INT Web'!U$1,FALSE) -> 18.99 | J26: =+VLOOKUP($B26,'[3]INT Web'!$B$5:$W$247,'[3]INT Web'!V$1,FALSE) -> 109.99 | K26: =+VLOOKUP($B26,'[3]INT Web'!$B$5:$W$247,'[3]INT Web'!W$1,FALSE) -> 16.99 | L26: =+F26/G26 -> 6.5405925 | M26: =+G26/I26 -> 1.3686151 | N26: =+H26/I26 -> 6.5818852 | O26: =+J26/K26 -> 6.4738081 | P26: =+K26/I26 -> 0.89468141 | Q26: =+E26 -> EUR | R26: =+VLOOKUP($B26,'Country-Level Tactics'!$B$5:$AL$248,'Country-Level Tactics'!AH$1,FALSE) -> 169.99 | S26: =+VLOOKUP($B26,'Country-Level Tactics'!$B$5:$AL$248,'Country-Level Tactics'!X$1,FALSE) -> 25.99 | T26: =+VLOOKUP($B26,'Country-Level Tactics'!$B$5:$AL$248,'Country-Level Tactics'!AC$1,FALSE) -> 124.99 | U26: =+VLOOKUP($B26,'Country-Level Tactics'!$B$5:$AL$248,'Country-Level Tactics'!T$1,FALSE) -> 18.99 | V26: =+J26 -> 109.99 | W26: =+K26 -> 16.99 | X26: =+R26/S26 -> 6.5405925 | Y26: =+S26/U26 -> 1.3686151 | Z26: =+T26/U26 -> 6.5818852 | AA26: =+V26/W26 -> 6.4738081 | AB26: =+W26/U26 -> 0.89468141 | AD26: =+R26/F26-1 -> 0 | AE26: =+S26/G26-1 -> 0 | AF26: =+T26/H26-1 -> 0 | AG26: =+U26/I26-1 -> 0 | AH26: =+V26/J26-1 -> 0 | AI26: =+W26/K26-1 -> 0 | AK26: 1.14175 | AL26: =+R26*$AK26 -> 194.08608 | AM26: =+S26*$AK26 -> 29.674083 | AN26: =+T26*$AK26 -> 142.70733 | AO26: =+U26*$AK26 -> 21.681832 | AP26: =+V26*$AK26 -> 125.58108 | AQ26: =+W26*$AK26 -> 19.398332 | AS26: =+VLOOKUP(B26,'Country & Code Abbreviation'!$B$3:$C$245,2,FALSE) -> BE
B27: Belize | C27: Latin America | E27: =+VLOOKUP($B27,'[3]INT Web'!$B$5:$W$247,'[3]INT Web'!Q$1,FALSE) -> BZD | F27: =+VLOOKUP($B27,'[3]INT Web'!$B$5:$W$247,'[3]INT Web'!R$1,FALSE) -> 149.99 | G27: =+VLOOKUP($B27,'[3]INT Web'!$B$5:$W$247,'[3]INT Web'!S$1,FALSE) -> 24.99 | H27: =+VLOOKUP($B27,'[3]INT Web'!$B$5:$W$247,'[3]INT Web'!T$1,FALSE) -> 107.99 | I27: =+VLOOKUP($B27,'[3]INT Web'!$B$5:$W$247,'[3]INT Web'!U$1,FALSE) -> 17.99 | J27: =+VLOOKUP($B27,'[3]INT Web'!$B$5:$W$247,'[3]INT Web'!V$1,FALSE) -> 95.99 | K27: =+VLOOKUP($B27,'[3]INT Web'!$B$5:$W$247,'[3]INT Web'!W$1,FALSE) -> 15.99 | L27: =+F27/G27 -> 6.0020008 | M27: =+G27/I27 -> 1.3891051 | N27: =+H27/I27 -> 6.0027793 | O27: =+J27/K27 -> 6.003127 | P27: =+K27/I27 -> 0.88882713 | Q27: =+E27 -> BZD | R27: =+VLOOKUP($B27,'Country-Level Tactics'!$B$5:$AL$248,'Country-Level Tactics'!AH$1,FALSE) -> 149.99 | S27: =+VLOOKUP($B27,'Country-Level Tactics'!$B$5:$AL$248,'Country-Level Tactics'!X$1,FALSE) -> 24.99 | T27: =+VLOOKUP($B27,'Country-Level Tactics'!$B$5:$AL$248,'Country-Level Tactics'!AC$1,FALSE) -> 107.99 | U27: =+VLOOKUP($B27,'Country-Level Tactics'!$B$5:$AL$248,'Country-Level Tactics'!T$1,FALSE) -> 17.99 | V27: =+J27 -> 95.99 | W27: =+K27 -> 15.99 | X27: =+R27/S27 -> 6.0020008 | Y27: =+S27/U27 -> 1.3891051 | Z27: =+T27/U27 -> 6.0027793 | AA27: =+V27/W27 -> 6.003127 | AB27: =+W27/U27 -> 0.88882713 | AD27: =+R27/F27-1 -> 0 | AE27: =+S27/G27-1 -> 0 | AF27: =+T27/H27-1 -> 0 | AG27: =+U27/I27-1 -> 0 | AH27: =+V27/J27-1 -> 0 | AI27: =+W27/K27-1 -> 0 | AK27: 0.5 | AL27: =+R27*$AK27 -> 74.995 | AM27: =+S27*$AK27 -> 12.495 | AN27: =+T27*$AK27 -> 53.995 | AO27: =+U27*$AK27 -> 8.995 | AP27: =+V27*$AK27 -> 47.995 | AQ27: =+W27*$AK27 -> 7.995 | AS27: =+VLOOKUP(B27,'Country & Code Abbreviation'!$B$3:$C$245,2,FALSE) -> BZ
B28: Benin | C28: Africa | E28: =+VLOOKUP($B28,'[3]INT Web'!$B$5:$W$247,'[3]INT Web'!Q$1,FALSE) -> XOF | F28: =+VLOOKUP($B28,'[3]INT Web'!$B$5:$W$247,'[3]INT Web'!R$1,FALSE) -> 43740 | G28: =+VLOOKUP($B28,'[3]INT Web'!$B$5:$W$247,'[3]INT Web'!S$1,FALSE) -> 7290 | H28: =+VLOOKUP($B28,'[3]INT Web'!$B$5:$W$247,'[3]INT Web'!T$1,FALSE) -> 32400 | I28: =+VLOOKUP($B28,'[3]INT Web'!$B$5:$W$247,'[3]INT Web'!U$1,FALSE) -> 5400 | J28: =+VLOOKUP($B28,'[3]INT Web'!$B$5:$W$247,'[3]INT Web'!V$1,FALSE) -> 29160 | K28: =+VLOOKUP($B28,'[3]INT Web'!$B$5:$W$247,'[3]INT Web'!W$1,FALSE) -> 4860 | L28: =+F28/G28 -> 6 | M28: =+G28/I28 -> 1.35 | N28: =+H28/I28 -> 6 | O28: =+J28/K28 -> 6 | P28: =+K28/I28 -> 0.9 | Q28: =+E28 -> XOF | R28: =+VLOOKUP($B28,'Country-Level Tactics'!$B$5:$AL$248,'Country-Level Tactics'!AH$1,FALSE) -> 43740 | S28: =+VLOOKUP($B28,'Country-Level Tactics'!$B$5:$AL$248,'Country-Level Tactics'!X$1,FALSE) -> 7290 | T28: =+VLOOKUP($B28,'Country-Level Tactics'!$B$5:$AL$248,'Country-Level Tactics'!AC$1,FALSE) -> 32400 | U28: =+VLOOKUP($B28,'Country-Level Tactics'!$B$5:$AL$248,'Country-Level Tactics'!T$1,FALSE) -> 5400 | V28: =+J28 -> 29160 | W28: =+K28 -> 4860 | X28: =+R28/S28 -> 6 | Y28: =+S28/U28 -> 1.35 | Z28: =+T28/U28 -> 6 | AA28: =+V28/W28 -> 6 | AB28: =+W28/U28 -> 0.9 | AD28: =+R28/F28-1 -> 0 | AE28: =+S28/G28-1 -> 0 | AF28: =+T28/H28-1 -> 0 | AG28: =+U28/I28-1 -> 0 | AH28: =+V28/J28-1 -> 0 | AI28: =+W28/K28-1 -> 0 | AK28: 0.0017405867 | AL28: =+R28*$AK28 -> 76.133262 | AM28: =+S28*$AK28 -> 12.688877 | AN28: =+T28*$AK28 -> 56.395009 | AO28: =+U28*$AK28 -> 9.3991682 | AP28: =+V28*$AK28 -> 50.755508 | AQ28: =+W28*$AK28 -> 8.4592514 | AS28: =+VLOOKUP(B28,'Country & Code Abbreviation'!$B$3:$C$245,2,FALSE) -> BJ
B29: Bermuda | C29: Latin America | E29: =+VLOOKUP($B29,'[3]INT Web'!$B$5:$W$247,'[3]INT Web'!Q$1,FALSE) -> BMD | F29: =+VLOOKUP($B29,'[3]INT Web'!$B$5:$W$247,'[3]INT Web'!R$1,FALSE) -> 95.99 | G29: =+VLOOKUP($B29,'[3]INT Web'!$B$5:$W$247,'[3]INT Web'!S$1,FALSE) -> 15.99 | H29: =+VLOOKUP($B29,'[3]INT Web'!$B$5:$W$247,'[3]INT Web'!T$1,FALSE) -> 71.99 | I29: =+VLOOKUP($B29,'[3]INT Web'!$B$5:$W$247,'[3]INT Web'!U$1,FALSE) -> 11.99 | J29: =+VLOOKUP($B29,'[3]INT Web'!$B$5:$W$247,'[3]INT Web'!V$1,FALSE) -> 65.99 | K29: =+VLOOKUP($B29,'[3]INT Web'!$B$5:$W$247,'[3]INT Web'!W$1,FALSE) -> 10.99 | L29: =+F29/G29 -> 6.003127 | M29: =+G29/I29 -> 1.3336113 | N29: =+H29/I29 -> 6.0041701 | O29: =+J29/K29 -> 6.0045496 | P29: =+K29/I29 -> 0.91659716 | Q29: =+E29 -> BMD | R29: =+VLOOKUP($B29,'Country-Level Tactics'!$B$5:$AL$248,'Country-Level Tactics'!AH$1,FALSE) -> 95.99 | S29: =+VLOOKUP($B29,'Country-Level Tactics'!$B$5:$AL$248,'Country-Level Tactics'!X$1,FALSE) -> 15.99 | T29: =+VLOOKUP($B29,'Country-Level Tactics'!$B$5:$AL$248,'Country-Level Tactics'!AC$1,FALSE) -> 71.99 | U29: =+VLOOKUP($B29,'Country-Level Tactics'!$B$5:$AL$248,'Country-Level Tactics'!T$1,FALSE) -> 11.99 | V29: =+J29 -> 65.99 | W29: =+K29 -> 10.99 | X29: =+R29/S29 -> 6.003127 | Y29: =+S29/U29 -> 1.3336113 | Z29: =+T29/U29 -> 6.0041701 | AA29: =+V29/W29 -> 6.0045496 | AB29: =+W29/U29 -> 0.91659716 | AD29: =+R29/F29-1 -> 0 | AE29: =+S29/G29-1 -> 0 | AF29: =+T29/H29-1 -> 0 | AG29: =+U29/I29-1 -> 0 | AH29: =+V29/J29-1 -> 0 | AI29: =+W29/K29-1 -> 0 | AK29: 1 | AL29: =+R29*$AK29 -> 95.99 | AM29: =+S29*$AK29 -> 15.99 | AN29: =+T29*$AK29 -> 71.99 | AO29: =+U29*$AK29 -> 11.99 | AP29: =+V29*$AK29 -> 65.99 | AQ29: =+W29*$AK29 -> 10.99 | AS29: =+VLOOKUP(B29,'Country & Code Abbreviation'!$B$3:$C$245,2,FALSE) -> BM
B30: Bhutan | C30: Asia | E30: =+VLOOKUP($B30,'[3]INT Web'!$B$5:$W$247,'[3]INT Web'!Q$1,FALSE) -> USD | F30: =+VLOOKUP($B30,'[3]INT Web'!$B$5:$W$247,'[3]INT Web'!R$1,FALSE) -> 71.99 | G30: =+VLOOKUP($B30,'[3]INT Web'!$B$5:$W$247,'[3]INT Web'!S$1,FALSE) -> 11.99 | H30: =+VLOOKUP($B30,'[3]INT Web'!$B$5:$W$247,'[3]INT Web'!T$1,FALSE) -> 53.99 | I30: =+VLOOKUP($B30,'[3]INT Web'!$B$5:$W$247,'[3]INT Web'!U$1,FALSE) -> 8.99 | J30: =+VLOOKUP($B30,'[3]INT Web'!$B$5:$W$247,'[3]INT Web'!V$1,FALSE) -> 47.99 | K30: =+VLOOKUP($B30,'[3]INT Web'!$B$5:$W$247,'[3]INT Web'!W$1,FALSE) -> 7.99 | L30: =+F30/G30 -> 6.0041701 | M30: =+G30/I30 -> 1.3337041 | N30: =+H30/I30 -> 6.0055617 | O30: =+J30/K30 -> 6.0062578 | P30: =+K30/I30 -> 0.88876529 | Q30: =+E30 -> USD | R30: =+VLOOKUP($B30,'Country-Level Tactics'!$B$5:$AL$248,'Country-Level Tactics'!AH$1,FALSE) -> 71.99 | S30: =+VLOOKUP($B30,'Country-Level Tactics'!$B$5:$AL$248,'Country-Level Tactics'!X$1,FALSE) -> 11.99 | T30: =+VLOOKUP($B30,'Country-Level Tactics'!$B$5:$AL$248,'Country-Level Tactics'!AC$1,FALSE) -> 53.99 | U30: =+VLOOKUP($B30,'Country-Level Tactics'!$B$5:$AL$248,'Country-Level Tactics'!T$1,FALSE) -> 8.99 | V30: =+J30 -> 47.99 | W30: =+K30 -> 7.99 | X30: =+R30/S30 -> 6.0041701 | Y30: =+S30/U30 -> 1.3337041 | Z30: =+T30/U30 -> 6.0055617 | AA30: =+V30/W30 -> 6.0062578 | AB30: =+W30/U30 -> 0.88876529 | AD30: =+R30/F30-1 -> 0 | AE30: =+S30/G30-1 -> 0 | AF30: =+T30/H30-1 -> 0 | AG30: =+U30/I30-1 -> 0 | AH30: =+V30/J30-1 -> 0 | AI30: =+W30/K30-1 -> 0 | AK30: 1 | AL30: =+R30*$AK30 -> 71.99 | AM30: =+S30*$AK30 -> 11.99 | AN30: =+T30*$AK30 -> 53.99 | AO30: =+U30*$AK30 -> 8.99 | AP30: =+V30*$AK30 -> 47.99 | AQ30: =+W30*$AK30 -> 7.99 | AS30: =+VLOOKUP(B30,'Country & Code Abbreviation'!$B$3:$C$245,2,FALSE) -> BT
B31: Bolivia | C31: Latin America | E31: =+VLOOKUP($B31,'[3]INT Web'!$B$5:$W$247,'[3]INT Web'!Q$1,FALSE) -> BOB | F31: =+VLOOKUP($B31,'[3]INT Web'!$B$5:$W$247,'[3]INT Web'!R$1,FALSE) -> 559.99 | G31: =+VLOOKUP($B31,'[3]INT Web'!$B$5:$W$247,'[3]INT Web'!S$1,FALSE) -> 92.99 | H31: =+VLOOKUP($B31,'[3]INT Web'!$B$5:$W$247,'[3]INT Web'!T$1,FALSE) -> 409.99 | I31: =+VLOOKUP($B31,'[3]INT Web'!$B$5:$W$247,'[3]INT Web'!U$1,FALSE) -> 68.99 | J31: =+VLOOKUP($B31,'[3]INT Web'!$B$5:$W$247,'[3]INT Web'!V$1,FALSE) -> 369.99 | K31: =+VLOOKUP($B31,'[3]INT Web'!$B$5:$W$247,'[3]INT Web'!W$1,FALSE) -> 61.99 | L31: =+F31/G31 -> 6.0220454 | M31: =+G31/I31 -> 1.3478765 | N31: =+H31/I31 -> 5.9427453 | O31: =+J31/K31 -> 5.9685433 | P31: =+K31/I31 -> 0.89853602 | Q31: =+E31 -> BOB | R31: =+VLOOKUP($B31,'Country-Level Tactics'!$B$5:$AL$248,'Country-Level Tactics'!AH$1,FALSE) -> 559.99 | S31: =+VLOOKUP($B31,'Country-Level Tactics'!$B$5:$AL$248,'Country-Level Tactics'!X$1,FALSE) -> 92.99 | T31: =+VLOOKUP($B31,'Country-Level Tactics'!$B$5:$AL$248,'Country-Level Tactics'!AC$1,FALSE) -> 409.99 | U31: =+VLOOKUP($B31,'Country-Level Tactics'!$B$5:$AL$248,'Country-Level Tactics'!T$1,FALSE) -> 68.99 | V31: =+J31 -> 369.99 | W31: =+K31 -> 61.99 | X31: =+R31/S31 -> 6.0220454 | Y31: =+S31/U31 -> 1.3478765 | Z31: =+T31/U31 -> 5.9427453 | AA31: =+V31/W31 -> 5.9685433 | AB31: =+W31/U31 -> 0.89853602 | AD31: =+R31/F31-1 -> 0 | AE31: =+S31/G31-1 -> 0 | AF31: =+T31/H31-1 -> 0 | AG31: =+U31/I31-1 -> 0 | AH31: =+V31/J31-1 -> 0 | AI31: =+W31/K31-1 -> 0 | AK31: 0.1447178 | AL31: =+R31*$AK31 -> 81.040521 | AM31: =+S31*$AK31 -> 13.457308 | AN31: =+T31*$AK31 -> 59.332851 | AO31: =+U31*$AK31 -> 9.984081 | AP31: =+V31*$AK31 -> 53.544139 | AQ31: =+W31*$AK31 -> 8.9710564 | AS31: =+VLOOKUP(B31,'Country & Code Abbreviation'!$B$3:$C$245,2,FALSE) -> BO
B32: Bonaire, St. Eustatius, & Saba | C32: Europe | E32: =+VLOOKUP($B32,'[3]INT Web'!$B$5:$W$247,'[3]INT Web'!Q$1,FALSE) -> USD | F32: =+VLOOKUP($B32,'[3]INT Web'!$B$5:$W$247,'[3]INT Web'!R$1,FALSE) -> 89.99 | G32: =+VLOOKUP($B32,'[3]INT Web'!$B$5:$W$247,'[3]INT Web'!S$1,FALSE) -> 14.99 | H32: =+VLOOKUP($B32,'[3]INT Web'!$B$5:$W$247,'[3]INT Web'!T$1,FALSE) -> 69.99 | I32: =+VLOOKUP($B32,'[3]INT Web'!$B$5:$W$247,'[3]INT Web'!U$1,FALSE) -> 10.99 | J32: =+VLOOKUP($B32,'[3]INT Web'!$B$5:$W$247,'[3]INT Web'!V$1,FALSE) -> 59.99 | K32: =+VLOOKUP($B32,'[3]INT Web'!$B$5:$W$247,'[3]INT Web'!W$1,FALSE) -> 9.99 | L32: =+F32/G32 -> 6.0033356 | M32: =+G32/I32 -> 1.3639672 | N32: =+H32/I32 -> 6.3685168 | O32: =+J32/K32 -> 6.005005 | P32: =+K32/I32 -> 0.90900819 | Q32: =+E32 -> USD | R32: =+VLOOKUP($B32,'Country-Level Tactics'!$B$5:$AL$248,'Country-Level Tactics'!AH$1,FALSE) -> 89.99 | S32: =+VLOOKUP($B32,'Country-Level Tactics'!$B$5:$AL$248,'Country-Level Tactics'!X$1,FALSE) -> 14.99 | T32: =+VLOOKUP($B32,'Country-Level Tactics'!$B$5:$AL$248,'Country-Level Tactics'!AC$1,FALSE) -> 69.99 | U32: =+VLOOKUP($B32,'Country-Level Tactics'!$B$5:$AL$248,'Country-Level Tactics'!T$1,FALSE) -> 10.99 | V32: =+J32 -> 59.99 | W32: =+K32 -> 9.99 | X32: =+R32/S32 -> 6.0033356 | Y32: =+S32/U32 -> 1.3639672 | Z32: =+T32/U32 -> 6.3685168 | AA32: =+V32/W32 -> 6.005005 | AB32: =+W32/U32 -> 0.90900819 | AD32: =+R32/F32-1 -> 0 | AE32: =+S32/G32-1 -> 0 | AF32: =+T32/H32-1 -> 0 | AG32: =+U32/I32-1 -> 0 | AH32: =+V32/J32-1 -> 0 | AI32: =+W32/K32-1 -> 0 | AK32: 1 | AL32: =+R32*$AK32 -> 89.99 | AM32: =+S32*$AK32 -> 14.99 | AN32: =+T32*$AK32 -> 69.99 | AO32: =+U32*$AK32 -> 10.99 | AP32: =+V32*$AK32 -> 59.99 | AQ32: =+W32*$AK32 -> 9.99 | AS32: =+VLOOKUP(B32,'Country & Code Abbreviation'!$B$3:$C$245,2,FALSE) -> BQ
B33: Bosnia And Herzegovina | C33: Europe | E33: =+VLOOKUP($B33,'[3]INT Web'!$B$5:$W$247,'[3]INT Web'!Q$1,FALSE) -> BAM | F33: =+VLOOKUP($B33,'[3]INT Web'!$B$5:$W$247,'[3]INT Web'!R$1,FALSE) -> 149.99 | G33: =+VLOOKUP($B33,'[3]INT Web'!$B$5:$W$247,'[3]INT Web'!S$1,FALSE) -> 24.99 | H33: =+VLOOKUP($B33,'[3]INT Web'!$B$5:$W$247,'[3]INT Web'!T$1,FALSE) -> 109.99 | I33: =+VLOOKUP($B33,'[3]INT Web'!$B$5:$W$247,'[3]INT Web'!U$1,FALSE) -> 17.99 | J33: =+VLOOKUP($B33,'[3]INT Web'!$B$5:$W$247,'[3]INT Web'!V$1,FALSE) -> 99.99 | K33: =+VLOOKUP($B33,'[3]INT Web'!$B$5:$W$247,'[3]INT Web'!W$1,FALSE) -> 15.99 | L33: =+F33/G33 -> 6.0020008 | M33: =+G33/I33 -> 1.3891051 | N33: =+H33/I33 -> 6.1139522 | O33: =+J33/K33 -> 6.2532833 | P33: =+K33/I33 -> 0.88882713 | Q33: =+E33 -> BAM | R33: =+VLOOKUP($B33,'Country-Level Tactics'!$B$5:$AL$248,'Country-Level Tactics'!AH$1,FALSE) -> 149.99 | S33: =+VLOOKUP($B33,'Country-Level Tactics'!$B$5:$AL$248,'Country-Level Tactics'!X$1,FALSE) -> 24.99 | T33: =+VLOOKUP($B33,'Country-Level Tactics'!$B$5:$AL$248,'Country-Level Tactics'!AC$1,FALSE) -> 109.99 | U33: =+VLOOKUP($B33,'Country-Level Tactics'!$B$5:$AL$248,'Country-Level Tactics'!T$1,FALSE) -> 17.99 | V33: =+J33 -> 99.99 | W33: =+K33 -> 15.99 | X33: =+R33/S33 -> 6.0020008 | Y33: =+S33/U33 -> 1.3891051 | Z33: =+T33/U33 -> 6.1139522 | AA33: =+V33/W33 -> 6.2532833 | AB33: =+W33/U33 -> 0.88882713 | AD33: =+R33/F33-1 -> 0 | AE33: =+S33/G33-1 -> 0 | AF33: =+T33/H33-1 -> 0 | AG33: =+U33/I33-1 -> 0 | AH33: =+V33/J33-1 -> 0 | AI33: =+W33/K33-1 -> 0 | AK33: 0.58377117 | AL33: =+R33*$AK33 -> 87.559838 | AM33: =+S33*$AK33 -> 14.588442 | AN33: =+T33*$AK33 -> 64.208991 | AO33: =+U33*$AK33 -> 10.502043 | AP33: =+V33*$AK33 -> 58.371279 | AQ33: =+W33*$AK33 -> 9.334501 | AS33: =+VLOOKUP(B33,'Country & Code Abbreviation'!$B$3:$C$245,2,FALSE) -> BA
B34: Botswana | C34: Africa | E34: =+VLOOKUP($B34,'[3]INT Web'!$B$5:$W$247,'[3]INT Web'!Q$1,FALSE) -> BWP | F34: =+VLOOKUP($B34,'[3]INT Web'!$B$5:$W$247,'[3]INT Web'!R$1,FALSE) -> 665.99 | G34: =+VLOOKUP($B34,'[3]INT Web'!$B$5:$W$247,'[3]INT Web'!S$1,FALSE) -> 110.99 | H34: =+VLOOKUP($B34,'[3]INT Web'!$B$5:$W$247,'[3]INT Web'!T$1,FALSE) -> 491.99 | I34: =+VLOOKUP($B34,'[3]INT Web'!$B$5:$W$247,'[3]INT Web'!U$1,FALSE) -> 81.99 | J34: =+VLOOKUP($B34,'[3]INT Web'!$B$5:$W$247,'[3]INT Web'!V$1,FALSE) -> 443.99 | K34: =+VLOOKUP($B34,'[3]INT Web'!$B$5:$W$247,'[3]INT Web'!W$1,FALSE) -> 73.99 | L34: =+F34/G34 -> 6.0004505 | M34: =+G34/I34 -> 1.3537017 | N34: =+H34/I34 -> 6.0006098 | O34: =+J34/K34 -> 6.0006758 | P34: =+K34/I34 -> 0.90242713 | Q34: =+E34 -> BWP | R34: =+VLOOKUP($B34,'Country-Level Tactics'!$B$5:$AL$248,'Country-Level Tactics'!AH$1,FALSE) -> 665.99 | S34: =+VLOOKUP($B34,'Country-Level Tactics'!$B$5:$AL$248,'Country-Level Tactics'!X$1,FALSE) -> 110.99 | T34: =+VLOOKUP($B34,'Country-Level Tactics'!$B$5:$AL$248,'Country-Level Tactics'!AC$1,FALSE) -> 491.99 | U34: =+VLOOKUP($B34,'Country-Level Tactics'!$B$5:$AL$248,'Country-Level Tactics'!T$1,FALSE) -> 81.99 | V34: =+J34 -> 443.99 | W34: =+K34 -> 73.99 | X34: =+R34/S34 -> 6.0004505 | Y34: =+S34/U34 -> 1.3537017 | Z34: =+T34/U34 -> 6.0006098 | AA34: =+V34/W34 -> 6.0006758 | AB34: =+W34/U34 -> 0.90242713 | AD34: =+R34/F34-1 -> 0 | AE34: =+S34/G34-1 -> 0 | AF34: =+T34/H34-1 -> 0 | AG34: =+U34/I34-1 -> 0 | AH34: =+V34/J34-1 -> 0 | AI34: =+W34/K34-1 -> 0 | AK34: 0.071 | AL34: =+R34*$AK34 -> 47.28529 | AM34: =+S34*$AK34 -> 7.88029 | AN34: =+T34*$AK34 -> 34.93129 | AO34: =+U34*$AK34 -> 5.82129 | AP34: =+V34*$AK34 -> 31.52329 | AQ34: =+W34*$AK34 -> 5.25329 | AS34: =+VLOOKUP(B34,'Country & Code Abbreviation'!$B$3:$C$245,2,FALSE) -> BW
B35: Bouvet Island | C35: Europe | E35: =+VLOOKUP($B35,'[3]INT Web'!$B$5:$W$247,'[3]INT Web'!Q$1,FALSE) -> NOK | F35: =+VLOOKUP($B35,'[3]INT Web'!$B$5:$W$247,'[3]INT Web'!R$1,FALSE) -> 1399.99 | G35: =+VLOOKUP($B35,'[3]INT Web'!$B$5:$W$247,'[3]INT Web'!S$1,FALSE) -> 199.99 | H35: =+VLOOKUP($B35,'[3]INT Web'!$B$5:$W$247,'[3]INT Web'!T$1,FALSE) -> 899.99 | I35: =+VLOOKUP($B35,'[3]INT Web'!$B$5:$W$247,'[3]INT Web'!U$1,FALSE) -> 149.99 | J35: =+VLOOKUP($B35,'[3]INT Web'!$B$5:$W$247,'[3]INT Web'!V$1,FALSE) -> 839.99 | K35: =+VLOOKUP($B35,'[3]INT Web'!$B$5:$W$247,'[3]INT Web'!W$1,FALSE) -> 139.99 | L35: =+F35/G35 -> 7.0003 | M35: =+G35/I35 -> 1.3333556 | N35: =+H35/I35 -> 6.0003334 | O35: =+J35/K35 -> 6.0003572 | P35: =+K35/I35 -> 0.93332889 | Q35: =+E35 -> NOK | R35: =+VLOOKUP($B35,'Country-Level Tactics'!$B$5:$AL$248,'Country-Level Tactics'!AH$1,FALSE) -> 1399.99 | S35: =+VLOOKUP($B35,'Country-Level Tactics'!$B$5:$AL$248,'Country-Level Tactics'!X$1,FALSE) -> 199.99 | T35: =+VLOOKUP($B35,'Country-Level Tactics'!$B$5:$AL$248,'Country-Level Tactics'!AC$1,FALSE) -> 899.99 | U35: =+VLOOKUP($B35,'Country-Level Tactics'!$B$5:$AL$248,'Country-Level Tactics'!T$1,FALSE) -> 149.99 | V35: =+J35 -> 839.99 | W35: =+K35 -> 139.99 | X35: =+R35/S35 -> 7.0003 | Y35: =+S35/U35 -> 1.3333556 | Z35: =+T35/U35 -> 6.0003334 | AA35: =+V35/W35 -> 6.0003572 | AB35: =+W35/U35 -> 0.93332889 | AD35: =+R35/F35-1 -> 0 | AE35: =+S35/G35-1 -> 0 | AF35: =+T35/H35-1 -> 0 | AG35: =+U35/I35-1 -> 0 | AH35: =+V35/J35-1 -> 0 | AI35: =+W35/K35-1 -> 0 | AK35: 0.1016534 | AL35: =+R35*$AK35 -> 142.31374 | AM35: =+S35*$AK35 -> 20.329663 | AN35: =+T35*$AK35 -> 91.487043 | AO35: =+U35*$AK35 -> 15.246993 | AP35: =+V35*$AK35 -> 85.387839 | AQ35: =+W35*$AK35 -> 14.230459 | AS35: =+VLOOKUP(B35,'Country & Code Abbreviation'!$B$3:$C$245,2,FALSE) -> BV
B36: Brazil | C36: Latin America | D36: C | E36: =+VLOOKUP($B36,'[3]INT Web'!$B$5:$W$247,'[3]INT Web'!Q$1,FALSE) -> BRL | F36: =+VLOOKUP($B36,'[3]INT Web'!$B$5:$W$247,'[3]INT Web'!R$1,FALSE) -> 489.99 | G36: =+VLOOKUP($B36,'[3]INT Web'!$B$5:$W$247,'[3]INT Web'!S$1,FALSE) -> 69.99 | H36: =+VLOOKUP($B36,'[3]INT Web'!$B$5:$W$247,'[3]INT Web'!T$1,FALSE) -> 384.99 | I36: =+VLOOKUP($B36,'[3]INT Web'!$B$5:$W$247,'[3]INT Web'!U$1,FALSE) -> 54.99 | J36: =+VLOOKUP($B36,'[3]INT Web'!$B$5:$W$247,'[3]INT Web'!V$1,FALSE) -> 349.99 | K36: =+VLOOKUP($B36,'[3]INT Web'!$B$5:$W$247,'[3]INT Web'!W$1,FALSE) -> 49.99 | L36: =+F36/G36 -> 7.0008573 | M36: =+G36/I36 -> 1.2727769 | N36: =+H36/I36 -> 7.0010911 | O36: =+J36/K36 -> 7.0012002 | P36: =+K36/I36 -> 0.90907438 | Q36: =+E36 -> BRL | R36: =+VLOOKUP($B36,'Country-Level Tactics'!$B$5:$AL$248,'Country-Level Tactics'!AH$1,FALSE) -> 489.99 | S36: =+VLOOKUP($B36,'Country-Level Tactics'!$B$5:$AL$248,'Country-Level Tactics'!X$1,FALSE) -> 69.99 | T36: =+VLOOKUP($B36,'Country-Level Tactics'!$B$5:$AL$248,'Country-Level Tactics'!AC$1,FALSE) -> 384.99 | U36: =+VLOOKUP($B36,'Country-Level Tactics'!$B$5:$AL$248,'Country-Level Tactics'!T$1,FALSE) -> 54.99 | V36: =+J36 -> 349.99 | W36: =+K36 -> 49.99 | X36: =+R36/S36 -> 7.0008573 | Y36: =+S36/U36 -> 1.2727769 | Z36: =+T36/U36 -> 7.0010911 | AA36: =+V36/W36 -> 7.0012002 | AB36: =+W36/U36 -> 0.90907438 | AD36: =+R36/F36-1 -> 0 | AE36: =+S36/G36-1 -> 0 | AF36: =+T36/H36-1 -> 0 | AG36: =+U36/I36-1 -> 0 | AH36: =+V36/J36-1 -> 0 | AI36: =+W36/K36-1 -> 0 | AK36: 0.19347599 | AL36: =+R36*$AK36 -> 94.8013 | AM36: =+S36*$AK36 -> 13.541385 | AN36: =+T36*$AK36 -> 74.486321 | AO36: =+U36*$AK36 -> 10.639245 | AP36: =+V36*$AK36 -> 67.714662 | AQ36: =+W36*$AK36 -> 9.6718647 | AS36: =+VLOOKUP(B36,'Country & Code Abbreviation'!$B$3:$C$245,2,FALSE) -> BR
B37: British Indian Ocean Territory | C37: Asia | E37: =+VLOOKUP($B37,'[3]INT Web'!$B$5:$W$247,'[3]INT Web'!Q$1,FALSE) -> USD | F37: =+VLOOKUP($B37,'[3]INT Web'!$B$5:$W$247,'[3]INT Web'!R$1,FALSE) -> 77.99 | G37: =+VLOOKUP($B37,'[3]INT Web'!$B$5:$W$247,'[3]INT Web'!S$1,FALSE) -> 12.99 | H37: =+VLOOKUP($B37,'[3]INT Web'!$B$5:$W$247,'[3]INT Web'!T$1,FALSE) -> 59.99 | I37: =+VLOOKUP($B37,'[3]INT Web'!$B$5:$W$247,'[3]INT Web'!U$1,FALSE) -> 9.99 | J37: =+VLOOKUP($B37,'[3]INT Web'!$B$5:$W$247,'[3]INT Web'!V$1,FALSE) -> 53.99 | K37: =+VLOOKUP($B37,'[3]INT Web'!$B$5:$W$247,'[3]INT Web'!W$1,FALSE) -> 8.99 | L37: =+F37/G37 -> 6.0038491 | M37: =+G37/I37 -> 1.3003003 | N37: =+H37/I37 -> 6.005005 | O37: =+J37/K37 -> 6.0055617 | P37: =+K37/I37 -> 0.8998999 | Q37: =+E37 -> USD | R37: =+VLOOKUP($B37,'Country-Level Tactics'!$B$5:$AL$248,'Country-Level Tactics'!AH$1,FALSE) -> 77.99 | S37: =+VLOOKUP($B37,'Country-Level Tactics'!$B$5:$AL$248,'Country-Level Tactics'!X$1,FALSE) -> 12.99 | T37: =+VLOOKUP($B37,'Country-Level Tactics'!$B$5:$AL$248,'Country-Level Tactics'!AC$1,FALSE) -> 59.99 | U37: =+VLOOKUP($B37,'Country-Level Tactics'!$B$5:$AL$248,'Country-Level Tactics'!T$1,FALSE) -> 9.99 | V37: =+J37 -> 53.99 | W37: =+K37 -> 8.99 | X37: =+R37/S37 -> 6.0038491 | Y37: =+S37/U37 -> 1.3003003 | Z37: =+T37/U37 -> 6.005005 | AA37: =+V37/W37 -> 6.0055617 | AB37: =+W37/U37 -> 0.8998999 | AD37: =+R37/F37-1 -> 0 | AE37: =+S37/G37-1 -> 0 | AF37: =+T37/H37-1 -> 0 | AG37: =+U37/I37-1 -> 0 | AH37: =+V37/J37-1 -> 0 | AI37: =+W37/K37-1 -> 0 | AK37: 1 | AL37: =+R37*$AK37 -> 77.99 | AM37: =+S37*$AK37 -> 12.99 | AN37: =+T37*$AK37 -> 59.99 | AO37: =+U37*$AK37 -> 9.99 | AP37: =+V37*$AK37 -> 53.99 | AQ37: =+W37*$AK37 -> 8.99 | AS37: =+VLOOKUP(B37,'Country & Code Abbreviation'!$B$3:$C$245,2,FALSE) -> IO
B38: British Virgin Islands | C38: Latin America | E38: =+VLOOKUP($B38,'[3]INT Web'!$B$5:$W$247,'[3]INT Web'!Q$1,FALSE) -> USD | F38: =+VLOOKUP($B38,'[3]INT Web'!$B$5:$W$247,'[3]INT Web'!R$1,FALSE) -> 102.99 | G38: =+VLOOKUP($B38,'[3]INT Web'!$B$5:$W$247,'[3]INT Web'!S$1,FALSE) -> 16.99 | H38: =+VLOOKUP($B38,'[3]INT Web'!$B$5:$W$247,'[3]INT Web'!T$1,FALSE) -> 71.99 | I38: =+VLOOKUP($B38,'[3]INT Web'!$B$5:$W$247,'[3]INT Web'!U$1,FALSE) -> 11.99 | J38: =+VLOOKUP($B38,'[3]INT Web'!$B$5:$W$247,'[3]INT Web'!V$1,FALSE) -> 65.99 | K38: =+VLOOKUP($B38,'[3]INT Web'!$B$5:$W$247,'[3]INT Web'!W$1,FALSE) -> 10.99 | L38: =+F38/G38 -> 6.0618011 | M38: =+G38/I38 -> 1.4170142 | N38: =+H38/I38 -> 6.0041701 | O38: =+J38/K38 -> 6.0045496 | P38: =+K38/I38 -> 0.91659716 | Q38: =+E38 -> USD | R38: =+VLOOKUP($B38,'Country-Level Tactics'!$B$5:$AL$248,'Country-Level Tactics'!AH$1,FALSE) -> 102.99 | S38: =+VLOOKUP($B38,'Country-Level Tactics'!$B$5:$AL$248,'Country-Level Tactics'!X$1,FALSE) -> 16.99 | T38: =+VLOOKUP($B38,'Country-Level Tactics'!$B$5:$AL$248,'Country-Level Tactics'!AC$1,FALSE) -> 71.99 | U38: =+VLOOKUP($B38,'Country-Level Tactics'!$B$5:$AL$248,'Country-Level Tactics'!T$1,FALSE) -> 11.99 | V38: =+J38 -> 65.99 | W38: =+K38 -> 10.99 | X38: =+R38/S38 -> 6.0618011 | Y38: =+S38/U38 -> 1.4170142 | Z38: =+T38/U38 -> 6.0041701 | AA38: =+V38/W38 -> 6.0045496 | AB38: =+W38/U38 -> 0.91659716 | AD38: =+R38/F38-1 -> 0 | AE38: =+S38/G38-1 -> 0 | AF38: =+T38/H38-1 -> 0 | AG38: =+U38/I38-1 -> 0 | AH38: =+V38/J38-1 -> 0 | AI38: =+W38/K38-1 -> 0 | AK38: 1 | AL38: =+R38*$AK38 -> 102.99 | AM38: =+S38*$AK38 -> 16.99 | AN38: =+T38*$AK38 -> 71.99 | AO38: =+U38*$AK38 -> 11.99 | AP38: =+V38*$AK38 -> 65.99 | AQ38: =+W38*$AK38 -> 10.99 | AS38: =+VLOOKUP(B38,'Country & Code Abbreviation'!$B$3:$C$245,2,FALSE) -> VG
B39: Brunei | C39: Asia | E39: =+VLOOKUP($B39,'[3]INT Web'!$B$5:$W$247,'[3]INT Web'!Q$1,FALSE) -> BND | F39: =+VLOOKUP($B39,'[3]INT Web'!$B$5:$W$247,'[3]INT Web'!R$1,FALSE) -> 107.99 | G39: =+VLOOKUP($B39,'[3]INT Web'!$B$5:$W$247,'[3]INT Web'!S$1,FALSE) -> 17.99 | H39: =+VLOOKUP($B39,'[3]INT Web'!$B$5:$W$247,'[3]INT Web'!T$1,FALSE) -> 77.99 | I39: =+VLOOKUP($B39,'[3]INT Web'!$B$5:$W$247,'[3]INT Web'!U$1,FALSE) -> 12.99 | J39: =+VLOOKUP($B39,'[3]INT Web'!$B$5:$W$247,'[3]INT Web'!V$1,FALSE) -> 71.99 | K39: =+VLOOKUP($B39,'[3]INT Web'!$B$5:$W$247,'[3]INT Web'!W$1,FALSE) -> 11.99 | L39: =+F39/G39 -> 6.0027793 | M39: =+G39/I39 -> 1.3849115 | N39: =+H39/I39 -> 6.0038491 | O39: =+J39/K39 -> 6.0041701 | P39: =+K39/I39 -> 0.92301771 | Q39: =+E39 -> BND | R39: =+VLOOKUP($B39,'Country-Level Tactics'!$B$5:$AL$248,'Country-Level Tactics'!AH$1,FALSE) -> 107.99 | S39: =+VLOOKUP($B39,'Country-Level Tactics'!$B$5:$AL$248,'Country-Level Tactics'!X$1,FALSE) -> 17.99 | T39: =+VLOOKUP($B39,'Country-Level Tactics'!$B$5:$AL$248,'Country-Level Tactics'!AC$1,FALSE) -> 77.99 | U39: =+VLOOKUP($B39,'Country-Level Tactics'!$B$5:$AL$248,'Country-Level Tactics'!T$1,FALSE) -> 12.99 | V39: =+J39 -> 71.99 | W39: =+K39 -> 11.99 | X39: =+R39/S39 -> 6.0027793 | Y39: =+S39/U39 -> 1.3849115 | Z39: =+T39/U39 -> 6.0038491 | AA39: =+V39/W39 -> 6.0041701 | AB39: =+W39/U39 -> 0.92301771 | AD39: =+R39/F39-1 -> 0 | AE39: =+S39/G39-1 -> 0 | AF39: =+T39/H39-1 -> 0 | AG39: =+U39/I39-1 -> 0 | AH39: =+V39/J39-1 -> 0 | AI39: =+W39/K39-1 -> 0 | AK39: 0.7730066 | AL39: =+R39*$AK39 -> 83.476983 | AM39: =+S39*$AK39 -> 13.906389 | AN39: =+T39*$AK39 -> 60.286785 | AO39: =+U39*$AK39 -> 10.041356 | AP39: =+V39*$AK39 -> 55.648745 | AQ39: =+W39*$AK39 -> 9.2683491 | AS39: =+VLOOKUP(B39,'Country & Code Abbreviation'!$B$3:$C$245,2,FALSE) -> BN
B40: Bulgaria | C40: Europe | E40: =+VLOOKUP($B40,'[3]INT Web'!$B$5:$W$247,'[3]INT Web'!Q$1,FALSE) -> BGN | F40: =+VLOOKUP($B40,'[3]INT Web'!$B$5:$W$247,'[3]INT Web'!R$1,FALSE) -> 184.99 | G40: =+VLOOKUP($B40,'[3]INT Web'!$B$5:$W$247,'[3]INT Web'!S$1,FALSE) -> 28.99 | H40: =+VLOOKUP($B40,'[3]INT Web'!$B$5:$W$247,'[3]INT Web'!T$1,FALSE) -> 136.99 | I40: =+VLOOKUP($B40,'[3]INT Web'!$B$5:$W$247,'[3]INT Web'!U$1,FALSE) -> 20.99 | J40: =+VLOOKUP($B40,'[3]INT Web'!$B$5:$W$247,'[3]INT Web'!V$1,FALSE) -> 119.99 | K40: =+VLOOKUP($B40,'[3]INT Web'!$B$5:$W$247,'[3]INT Web'!W$1,FALSE) -> 18.99 | L40: =+F40/G40 -> 6.3811659 | M40: =+G40/I40 -> 1.3811339 | N40: =+H40/I40 -> 6.5264412 | O40: =+J40/K40 -> 6.3185887 | P40: =+K40/I40 -> 0.90471653 | Q40: EUR | R40: 94.99 | S40: =+VLOOKUP($B40,'Country-Level Tactics'!$B$5:$AL$248,'Country-Level Tactics'!X$1,FALSE) -> 14.99 | T40: =+MROUND(U40*N40,1)-0.01 -> 71.99 | U40: =+VLOOKUP($B40,'Country-Level Tactics'!$B$5:$AL$248,'Country-Level Tactics'!T$1,FALSE) -> 10.99 | V40: =+MROUND(W40*O40,1)-0.01 -> 62.99 | W40: =+MROUND(U40*P40,1)-0.01 -> 9.99 | X40: =+R40/S40 -> 6.3368913 | Y40: =+S40/U40 -> 1.3639672 | Z40: =+T40/U40 -> 6.5505005 | AA40: =+V40/W40 -> 6.3053053 | AB40: =+W40/U40 -> 0.90900819 | AD40: =+R40/F40-1 -> -0.48651278 | AE40: =+S40/G40-1 -> -0.48292515 | AF40: =+T40/H40-1 -> -0.47448719 | AG40: =+U40/I40-1 -> -0.47641734 | AH40: =+V40/J40-1 -> -0.47503959 | AI40: =+W40/K40-1 -> -0.47393365 | AK40: 1.14175 | AL40: =+R40*$AK40 -> 108.45483 | AM40: =+S40*$AK40 -> 17.114833 | AN40: =+T40*$AK40 -> 82.194582 | AO40: =+U40*$AK40 -> 12.547833 | AP40: =+V40*$AK40 -> 71.918833 | AQ40: =+W40*$AK40 -> 11.406083 | AS40: =+VLOOKUP(B40,'Country & Code Abbreviation'!$B$3:$C$245,2,FALSE) -> BG
B41: Burkina Faso | C41: Africa | E41: =+VLOOKUP($B41,'[3]INT Web'!$B$5:$W$247,'[3]INT Web'!Q$1,FALSE) -> XOF | F41: =+VLOOKUP($B41,'[3]INT Web'!$B$5:$W$247,'[3]INT Web'!R$1,FALSE) -> 43740 | G41: =+VLOOKUP($B41,'[3]INT Web'!$B$5:$W$247,'[3]INT Web'!S$1,FALSE) -> 7290 | H41: =+VLOOKUP($B41,'[3]INT Web'!$B$5:$W$247,'[3]INT Web'!T$1,FALSE) -> 32400 | I41: =+VLOOKUP($B41,'[3]INT Web'!$B$5:$W$247,'[3]INT Web'!U$1,FALSE) -> 5400 | J41: =+VLOOKUP($B41,'[3]INT Web'!$B$5:$W$247,'[3]INT Web'!V$1,FALSE) -> 29160 | K41: =+VLOOKUP($B41,'[3]INT Web'!$B$5:$W$247,'[3]INT Web'!W$1,FALSE) -> 4860 | L41: =+F41/G41 -> 6 | M41: =+G41/I41 -> 1.35 | N41: =+H41/I41 -> 6 | O41: =+J41/K41 -> 6 | P41: =+K41/I41 -> 0.9 | Q41: =+E41 -> XOF | R41: =+VLOOKUP($B41,'Country-Level Tactics'!$B$5:$AL$248,'Country-Level Tactics'!AH$1,FALSE) -> 43740 | S41: =+VLOOKUP($B41,'Country-Level Tactics'!$B$5:$AL$248,'Country-Level Tactics'!X$1,FALSE) -> 7290 | T41: =+VLOOKUP($B41,'Country-Level Tactics'!$B$5:$AL$248,'Country-Level Tactics'!AC$1,FALSE) -> 32400 | U41: =+VLOOKUP($B41,'Country-Level Tactics'!$B$5:$AL$248,'Country-Level Tactics'!T$1,FALSE) -> 5400 | V41: =+J41 -> 29160 | W41: =+K41 -> 4860 | X41: =+R41/S41 -> 6 | Y41: =+S41/U41 -> 1.35 | Z41: =+T41/U41 -> 6 | AA41: =+V41/W41 -> 6 | AB41: =+W41/U41 -> 0.9 | AD41: =+R41/F41-1 -> 0 | AE41: =+S41/G41-1 -> 0 | AF41: =+T41/H41-1 -> 0 | AG41: =+U41/I41-1 -> 0 | AH41: =+V41/J41-1 -> 0 | AI41: =+W41/K41-1 -> 0 | AK41: 0.0017405867 | AL41: =+R41*$AK41 -> 76.133262 | AM41: =+S41*$AK41 -> 12.688877 | AN41: =+T41*$AK41 -> 56.395009 | AO41: =+U41*$AK41 -> 9.3991682 | AP41: =+V41*$AK41 -> 50.755508 | AQ41: =+W41*$AK41 -> 8.4592514 | AS41: =+VLOOKUP(B41,'Country & Code Abbreviation'!$B$3:$C$245,2,FALSE) -> BF
B42: Burundi | C42: Africa | E42: =+VLOOKUP($B42,'[3]INT Web'!$B$5:$W$247,'[3]INT Web'!Q$1,FALSE) -> USD | F42: =+VLOOKUP($B42,'[3]INT Web'!$B$5:$W$247,'[3]INT Web'!R$1,FALSE) -> 71.99 | G42: =+VLOOKUP($B42,'[3]INT Web'!$B$5:$W$247,'[3]INT Web'!S$1,FALSE) -> 11.99 | H42: =+VLOOKUP($B42,'[3]INT Web'!$B$5:$W$247,'[3]INT Web'!T$1,FALSE) -> 53.99 | I42: =+VLOOKUP($B42,'[3]INT Web'!$B$5:$W$247,'[3]INT Web'!U$1,FALSE) -> 8.99 | J42: =+VLOOKUP($B42,'[3]INT Web'!$B$5:$W$247,'[3]INT Web'!V$1,FALSE) -> 47.99 | K42: =+VLOOKUP($B42,'[3]INT Web'!$B$5:$W$247,'[3]INT Web'!W$1,FALSE) -> 7.99 | L42: =+F42/G42 -> 6.0041701 | M42: =+G42/I42 -> 1.3337041 | N42: =+H42/I42 -> 6.0055617 | O42: =+J42/K42 -> 6.0062578 | P42: =+K42/I42 -> 0.88876529 | Q42: =+E42 -> USD | R42: =+VLOOKUP($B42,'Country-Level Tactics'!$B$5:$AL$248,'Country-Level Tactics'!AH$1,FALSE) -> 71.99 | S42: =+VLOOKUP($B42,'Country-Level Tactics'!$B$5:$AL$248,'Country-Level Tactics'!X$1,FALSE) -> 11.99 | T42: =+VLOOKUP($B42,'Country-Level Tactics'!$B$5:$AL$248,'Country-Level Tactics'!AC$1,FALSE) -> 53.99 | U42: =+VLOOKUP($B42,'Country-Level Tactics'!$B$5:$AL$248,'Country-Level Tactics'!T$1,FALSE) -> 8.99 | V42: =+J42 -> 47.99 | W42: =+K42 -> 7.99 | X42: =+R42/S42 -> 6.0041701 | Y42: =+S42/U42 -> 1.3337041 | Z42: =+T42/U42 -> 6.0055617 | AA42: =+V42/W42 -> 6.0062578 | AB42: =+W42/U42 -> 0.88876529 | AD42: =+R42/F42-1 -> 0 | AE42: =+S42/G42-1 -> 0 | AF42: =+T42/H42-1 -> 0 | AG42: =+U42/I42-1 -> 0 | AH42: =+V42/J42-1 -> 0 | AI42: =+W42/K42-1 -> 0 | AK42: 1 | AL42: =+R42*$AK42 -> 71.99 | AM42: =+S42*$AK42 -> 11.99 | AN42: =+T42*$AK42 -> 53.99 | AO42: =+U42*$AK42 -> 8.99 | AP42: =+V42*$AK42 -> 47.99 | AQ42: =+W42*$AK42 -> 7.99 | AS42: =+VLOOKUP(B42,'Country & Code Abbreviation'!$B$3:$C$245,2,FALSE) -> BI
B43: Cambodia | C43: Asia | E43: =+VLOOKUP($B43,'[3]INT Web'!$B$5:$W$247,'[3]INT Web'!Q$1,FALSE) -> KHR | F43: =+VLOOKUP($B43,'[3]INT Web'!$B$5:$W$247,'[3]INT Web'!R$1,FALSE) -> 294180 | G43: =+VLOOKUP($B43,'[3]INT Web'!$B$5:$W$247,'[3]INT Web'!S$1,FALSE) -> 49030 | H43: =+VLOOKUP($B43,'[3]INT Web'!$B$5:$W$247,'[3]INT Web'!T$1,FALSE) -> 217920 | I43: =+VLOOKUP($B43,'[3]INT Web'!$B$5:$W$247,'[3]INT Web'!U$1,FALSE) -> 36320 | J43: =+VLOOKUP($B43,'[3]INT Web'!$B$5:$W$247,'[3]INT Web'!V$1,FALSE) -> 196140 | K43: =+VLOOKUP($B43,'[3]INT Web'!$B$5:$W$247,'[3]INT Web'!W$1,FALSE) -> 32690 | L43: =+F43/G43 -> 6 | M43: =+G43/I43 -> 1.3499449 | N43: =+H43/I43 -> 6 | O43: =+J43/K43 -> 6 | P43: =+K43/I43 -> 0.90005507 | Q43: =+E43 -> KHR | R43: =+VLOOKUP($B43,'Country-Level Tactics'!$B$5:$AL$248,'Country-Level Tactics'!AH$1,FALSE) -> 294180 | S43: =+VLOOKUP($B43,'Country-Level Tactics'!$B$5:$AL$248,'Country-Level Tactics'!X$1,FALSE) -> 49030 | T43: =+VLOOKUP($B43,'Country-Level Tactics'!$B$5:$AL$248,'Country-Level Tactics'!AC$1,FALSE) -> 217920 | U43: =+VLOOKUP($B43,'Country-Level Tactics'!$B$5:$AL$248,'Country-Level Tactics'!T$1,FALSE) -> 36320 | V43: =+J43 -> 196140 | W43: =+K43 -> 32690 | X43: =+R43/S43 -> 6 | Y43: =+S43/U43 -> 1.3499449 | Z43: =+T43/U43 -> 6 | AA43: =+V43/W43 -> 6 | AB43: =+W43/U43 -> 0.90005507 | AD43: =+R43/F43-1 -> 0 | AE43: =+S43/G43-1 -> 0 | AF43: =+T43/H43-1 -> 0 | AG43: =+U43/I43-1 -> 0 | AH43: =+V43/J43-1 -> 0 | AI43: =+W43/K43-1 -> 0 | AK43: 0.00024915455 | AL43: =+R43*$AK43 -> 73.296286 | AM43: =+S43*$AK43 -> 12.216048 | AN43: =+T43*$AK43 -> 54.29576 | AO43: =+U43*$AK43 -> 9.0492933 | AP43: =+V43*$AK43 -> 48.869173 | AQ43: =+W43*$AK43 -> 8.1448622 | AS43: =+VLOOKUP(B43,'Country & Code Abbreviation'!$B$3:$C$245,2,FALSE) -> KH
B44: Cameroon | C44: Africa | E44: =+VLOOKUP($B44,'[3]INT Web'!$B$5:$W$247,'[3]INT Web'!Q$1,FALSE) -> XAF | F44: =+VLOOKUP($B44,'[3]INT Web'!$B$5:$W$247,'[3]INT Web'!R$1,FALSE) -> 43740 | G44: =+VLOOKUP($B44,'[3]INT Web'!$B$5:$W$247,'[3]INT Web'!S$1,FALSE) -> 7290 | H44: =+VLOOKUP($B44,'[3]INT Web'!$B$5:$W$247,'[3]INT Web'!T$1,FALSE) -> 32400 | I44: =+VLOOKUP($B44,'[3]INT Web'!$B$5:$W$247,'[3]INT Web'!U$1,FALSE) -> 5400 | J44: =+VLOOKUP($B44,'[3]INT Web'!$B$5:$W$247,'[3]INT Web'!V$1,FALSE) -> 29160 | K44: =+VLOOKUP($B44,'[3]INT Web'!$B$5:$W$247,'[3]INT Web'!W$1,FALSE) -> 4860 | L44: =+F44/G44 -> 6 | M44: =+G44/I44 -> 1.35 | N44: =+H44/I44 -> 6 | O44: =+J44/K44 -> 6 | P44: =+K44/I44 -> 0.9 | Q44: =+E44 -> XAF | R44: =+VLOOKUP($B44,'Country-Level Tactics'!$B$5:$AL$248,'Country-Level Tactics'!AH$1,FALSE) -> 43740 | S44: =+VLOOKUP($B44,'Country-Level Tactics'!$B$5:$AL$248,'Country-Level Tactics'!X$1,FALSE) -> 7290 | T44: =+VLOOKUP($B44,'Country-Level Tactics'!$B$5:$AL$248,'Country-Level Tactics'!AC$1,FALSE) -> 32400 | U44: =+VLOOKUP($B44,'Country-Level Tactics'!$B$5:$AL$248,'Country-Level Tactics'!T$1,FALSE) -> 5400 | V44: =+J44 -> 29160 | W44: =+K44 -> 4860 | X44: =+R44/S44 -> 6 | Y44: =+S44/U44 -> 1.35 | Z44: =+T44/U44 -> 6 | AA44: =+V44/W44 -> 6 | AB44: =+W44/U44 -> 0.9 | AD44: =+R44/F44-1 -> 0 | AE44: =+S44/G44-1 -> 0 | AF44: =+T44/H44-1 -> 0 | AG44: =+U44/I44-1 -> 0 | AH44: =+V44/J44-1 -> 0 | AI44: =+W44/K44-1 -> 0 | AK44: 0.0017405867 | AL44: =+R44*$AK44 -> 76.133262 | AM44: =+S44*$AK44 -> 12.688877 | AN44: =+T44*$AK44 -> 56.395009 | AO44: =+U44*$AK44 -> 9.3991682 | AP44: =+V44*$AK44 -> 50.755508 | AQ44: =+W44*$AK44 -> 8.4592514 | AS44: =+VLOOKUP(B44,'Country & Code Abbreviation'!$B$3:$C$245,2,FALSE) -> CM
B45: Canada | C45: Canada | D45: A | E45: =+VLOOKUP($B45,'[3]INT Web'!$B$5:$W$247,'[3]INT Web'!Q$1,FALSE) -> CAD | F45: =+VLOOKUP($B45,'[3]INT Web'!$B$5:$W$247,'[3]INT Web'!R$1,FALSE) -> 184.99 | G45: =+VLOOKUP($B45,'[3]INT Web'!$B$5:$W$247,'[3]INT Web'!S$1,FALSE) -> 27.99 | H45: =+VLOOKUP($B45,'[3]INT Web'!$B$5:$W$247,'[3]INT Web'!T$1,FALSE) -> 129.99 | I45: =+VLOOKUP($B45,'[3]INT Web'!$B$5:$W$247,'[3]INT Web'!U$1,FALSE) -> 19.99 | J45: =+VLOOKUP($B45,'[3]INT Web'!$B$5:$W$247,'[3]INT Web'!V$1,FALSE) -> 114.99 | K45: =+VLOOKUP($B45,'[3]INT Web'!$B$5:$W$247,'[3]INT Web'!W$1,FALSE) -> 17.99 | L45: =+F45/G45 -> 6.6091461 | M45: =+G45/I45 -> 1.4002001 | N45: =+H45/I45 -> 6.5027514 | O45: =+J45/K45 -> 6.3918844 | P45: =+K45/I45 -> 0.89994997 | Q45: =+E45 -> CAD | R45: =+VLOOKUP($B45,'Country-Level Tactics'!$B$5:$AL$248,'Country-Level Tactics'!AH$1,FALSE) -> 184.99 | S45: =+VLOOKUP($B45,'Country-Level Tactics'!$B$5:$AL$248,'Country-Level Tactics'!X$1,FALSE) -> 27.99 | T45: =+VLOOKUP($B45,'Country-Level Tactics'!$B$5:$AL$248,'Country-Level Tactics'!AC$1,FALSE) -> 129.99 | U45: =+VLOOKUP($B45,'Country-Level Tactics'!$B$5:$AL$248,'Country-Level Tactics'!T$1,FALSE) -> 19.99 | V45: =+J45 -> 114.99 | W45: =+K45 -> 17.99 | X45: =+R45/S45 -> 6.6091461 | Y45: =+S45/U45 -> 1.4002001 | Z45: =+T45/U45 -> 6.5027514 | AA45: =+V45/W45 -> 6.3918844 | AB45: =+W45/U45 -> 0.89994997 | AD45: =+R45/F45-1 -> 0 | AE45: =+S45/G45-1 -> 0 | AF45: =+T45/H45-1 -> 0 | AG45: =+U45/I45-1 -> 0 | AH45: =+V45/J45-1 -> 0 | AI45: =+W45/K45-1 -> 0 | AK45: 0.70303714 | AL45: =+R45*$AK45 -> 130.05484 | AM45: =+S45*$AK45 -> 19.67801 | AN45: =+T45*$AK45 -> 91.387798 | AO45: =+U45*$AK45 -> 14.053712 | AP45: =+V45*$AK45 -> 80.842241 | AQ45: =+W45*$AK45 -> 12.647638 | AS45: =+VLOOKUP(B45,'Country & Code Abbreviation'!$B$3:$C$245,2,FALSE) -> CA
B46: Cape Verde | C46: Africa | E46: =+VLOOKUP($B46,'[3]INT Web'!$B$5:$W$247,'[3]INT Web'!Q$1,FALSE) -> CVE | F46: =+VLOOKUP($B46,'[3]INT Web'!$B$5:$W$247,'[3]INT Web'!R$1,FALSE) -> 7369 | G46: =+VLOOKUP($B46,'[3]INT Web'!$B$5:$W$247,'[3]INT Web'!S$1,FALSE) -> 1229 | H46: =+VLOOKUP($B46,'[3]INT Web'!$B$5:$W$247,'[3]INT Web'!T$1,FALSE) -> 5459 | I46: =+VLOOKUP($B46,'[3]INT Web'!$B$5:$W$247,'[3]INT Web'!U$1,FALSE) -> 909 | J46: =+VLOOKUP($B46,'[3]INT Web'!$B$5:$W$247,'[3]INT Web'!V$1,FALSE) -> 4919 | K46: =+VLOOKUP($B46,'[3]INT Web'!$B$5:$W$247,'[3]INT Web'!W$1,FALSE) -> 819 | L46: =+F46/G46 -> 5.9959317 | M46: =+G46/I46 -> 1.3520352 | N46: =+H46/I46 -> 6.0055006 | O46: =+J46/K46 -> 6.006105 | P46: =+K46/I46 -> 0.9009901 | Q46: =+E46 -> CVE | R46: =+VLOOKUP($B46,'Country-Level Tactics'!$B$5:$AL$248,'Country-Level Tactics'!AH$1,FALSE) -> 7369 | S46: =+VLOOKUP($B46,'Country-Level Tactics'!$B$5:$AL$248,'Country-Level Tactics'!X$1,FALSE) -> 1229 | T46: =+VLOOKUP($B46,'Country-Level Tactics'!$B$5:$AL$248,'Country-Level Tactics'!AC$1,FALSE) -> 5459 | U46: =+VLOOKUP($B46,'Country-Level Tactics'!$B$5:$AL$248,'Country-Level Tactics'!T$1,FALSE) -> 909 | V46: =+J46 -> 4919 | W46: =+K46 -> 819 | X46: =+R46/S46 -> 5.9959317 | Y46: =+S46/U46 -> 1.3520352 | Z46: =+T46/U46 -> 6.0055006 | AA46: =+V46/W46 -> 6.006105 | AB46: =+W46/U46 -> 0.9009901 | AD46: =+R46/F46-1 -> 0 | AE46: =+S46/G46-1 -> 0 | AF46: =+T46/H46-1 -> 0 | AG46: =+U46/I46-1 -> 0 | AH46: =+V46/J46-1 -> 0 | AI46: =+W46/K46-1 -> 0 | AK46: 0.010356478 | AL46: =+R46*$AK46 -> 76.316886 | AM46: =+S46*$AK46 -> 12.728111 | AN46: =+T46*$AK46 -> 56.536013 | AO46: =+U46*$AK46 -> 9.4140385 | AP46: =+V46*$AK46 -> 50.943515 | AQ46: =+W46*$AK46 -> 8.4819555 | AS46: =+VLOOKUP(B46,'Country & Code Abbreviation'!$B$3:$C$245,2,FALSE) -> CV
B47: Cayman Islands | C47: Latin America | E47: =+VLOOKUP($B47,'[3]INT Web'!$B$5:$W$247,'[3]INT Web'!Q$1,FALSE) -> USD | F47: =+VLOOKUP($B47,'[3]INT Web'!$B$5:$W$247,'[3]INT Web'!R$1,FALSE) -> 102.99 | G47: =+VLOOKUP($B47,'[3]INT Web'!$B$5:$W$247,'[3]INT Web'!S$1,FALSE) -> 16.99 | H47: =+VLOOKUP($B47,'[3]INT Web'!$B$5:$W$247,'[3]INT Web'!T$1,FALSE) -> 71.99 | I47: =+VLOOKUP($B47,'[3]INT Web'!$B$5:$W$247,'[3]INT Web'!U$1,FALSE) -> 11.99 | J47: =+VLOOKUP($B47,'[3]INT Web'!$B$5:$W$247,'[3]INT Web'!V$1,FALSE) -> 65.99 | K47: =+VLOOKUP($B47,'[3]INT Web'!$B$5:$W$247,'[3]INT Web'!W$1,FALSE) -> 10.99 | L47: =+F47/G47 -> 6.0618011 | M47: =+G47/I47 -> 1.4170142 | N47: =+H47/I47 -> 6.0041701 | O47: =+J47/K47 -> 6.0045496 | P47: =+K47/I47 -> 0.91659716 | Q47: =+E47 -> USD | R47: =+VLOOKUP($B47,'Country-Level Tactics'!$B$5:$AL$248,'Country-Level Tactics'!AH$1,FALSE) -> 102.99 | S47: =+VLOOKUP($B47,'Country-Level Tactics'!$B$5:$AL$248,'Country-Level Tactics'!X$1,FALSE) -> 16.99 | T47: =+VLOOKUP($B47,'Country-Level Tactics'!$B$5:$AL$248,'Country-Level Tactics'!AC$1,FALSE) -> 71.99 | U47: =+VLOOKUP($B47,'Country-Level Tactics'!$B$5:$AL$248,'Country-Level Tactics'!T$1,FALSE) -> 11.99 | V47: =+J47 -> 65.99 | W47: =+K47 -> 10.99 | X47: =+R47/S47 -> 6.0618011 | Y47: =+S47/U47 -> 1.4170142 | Z47: =+T47/U47 -> 6.0041701 | AA47: =+V47/W47 -> 6.0045496 | AB47: =+W47/U47 -> 0.91659716 | AD47: =+R47/F47-1 -> 0 | AE47: =+S47/G47-1 -> 0 | AF47: =+T47/H47-1 -> 0 | AG47: =+U47/I47-1 -> 0 | AH47: =+V47/J47-1 -> 0 | AI47: =+W47/K47-1 -> 0 | AK47: 1 | AL47: =+R47*$AK47 -> 102.99 | AM47: =+S47*$AK47 -> 16.99 | AN47: =+T47*$AK47 -> 71.99 | AO47: =+U47*$AK47 -> 11.99 | AP47: =+V47*$AK47 -> 65.99 | AQ47: =+W47*$AK47 -> 10.99 | AS47: =+VLOOKUP(B47,'Country & Code Abbreviation'!$B$3:$C$245,2,FALSE) -> KY
B48: Central African Republic | C48: Africa | E48: =+VLOOKUP($B48,'[3]INT Web'!$B$5:$W$247,'[3]INT Web'!Q$1,FALSE) -> XAF | F48: =+VLOOKUP($B48,'[3]INT Web'!$B$5:$W$247,'[3]INT Web'!R$1,FALSE) -> 44580 | G48: =+VLOOKUP($B48,'[3]INT Web'!$B$5:$W$247,'[3]INT Web'!S$1,FALSE) -> 7430 | H48: =+VLOOKUP($B48,'[3]INT Web'!$B$5:$W$247,'[3]INT Web'!T$1,FALSE) -> 33000 | I48: =+VLOOKUP($B48,'[3]INT Web'!$B$5:$W$247,'[3]INT Web'!U$1,FALSE) -> 5500 | J48: =+VLOOKUP($B48,'[3]INT Web'!$B$5:$W$247,'[3]INT Web'!V$1,FALSE) -> 29700 | K48: =+VLOOKUP($B48,'[3]INT Web'!$B$5:$W$247,'[3]INT Web'!W$1,FALSE) -> 4950 | L48: =+F48/G48 -> 6 | M48: =+G48/I48 -> 1.3509091 | N48: =+H48/I48 -> 6 | O48: =+J48/K48 -> 6 | P48: =+K48/I48 -> 0.9 | Q48: =+E48 -> XAF | R48: =+VLOOKUP($B48,'Country-Level Tactics'!$B$5:$AL$248,'Country-Level Tactics'!AH$1,FALSE) -> 44580 | S48: =+VLOOKUP($B48,'Country-Level Tactics'!$B$5:$AL$248,'Country-Level Tactics'!X$1,FALSE) -> 7430 | T48: =+VLOOKUP($B48,'Country-Level Tactics'!$B$5:$AL$248,'Country-Level Tactics'!AC$1,FALSE) -> 33000 | U48: =+VLOOKUP($B48,'Country-Level Tactics'!$B$5:$AL$248,'Country-Level Tactics'!T$1,FALSE) -> 5500 | V48: =+J48 -> 29700 | W48: =+K48 -> 4950 | X48: =+R48/S48 -> 6 | Y48: =+S48/U48 -> 1.3509091 | Z48: =+T48/U48 -> 6 | AA48: =+V48/W48 -> 6 | AB48: =+W48/U48 -> 0.9 | AD48: =+R48/F48-1 -> 0 | AE48: =+S48/G48-1 -> 0 | AF48: =+T48/H48-1 -> 0 | AG48: =+U48/I48-1 -> 0 | AH48: =+V48/J48-1 -> 0 | AI48: =+W48/K48-1 -> 0 | AK48: 0.0017405867 | AL48: =+R48*$AK48 -> 77.595355 | AM48: =+S48*$AK48 -> 12.932559 | AN48: =+T48*$AK48 -> 57.439361 | AO48: =+U48*$AK48 -> 9.5732268 | AP48: =+V48*$AK48 -> 51.695425 | AQ48: =+W48*$AK48 -> 8.6159042 | AS48: =+VLOOKUP(B48,'Country & Code Abbreviation'!$B$3:$C$245,2,FALSE) -> CF
B49: Chad | C49: Africa | E49: =+VLOOKUP($B49,'[3]INT Web'!$B$5:$W$247,'[3]INT Web'!Q$1,FALSE) -> XAF | F49: =+VLOOKUP($B49,'[3]INT Web'!$B$5:$W$247,'[3]INT Web'!R$1,FALSE) -> 43740 | G49: =+VLOOKUP($B49,'[3]INT Web'!$B$5:$W$247,'[3]INT Web'!S$1,FALSE) -> 7290 | H49: =+VLOOKUP($B49,'[3]INT Web'!$B$5:$W$247,'[3]INT Web'!T$1,FALSE) -> 32400 | I49: =+VLOOKUP($B49,'[3]INT Web'!$B$5:$W$247,'[3]INT Web'!U$1,FALSE) -> 5400 | J49: =+VLOOKUP($B49,'[3]INT Web'!$B$5:$W$247,'[3]INT Web'!V$1,FALSE) -> 29160 | K49: =+VLOOKUP($B49,'[3]INT Web'!$B$5:$W$247,'[3]INT Web'!W$1,FALSE) -> 4860 | L49: =+F49/G49 -> 6 | M49: =+G49/I49 -> 1.35 | N49: =+H49/I49 -> 6 | O49: =+J49/K49 -> 6 | P49: =+K49/I49 -> 0.9 | Q49: =+E49 -> XAF | R49: =+VLOOKUP($B49,'Country-Level Tactics'!$B$5:$AL$248,'Country-Level Tactics'!AH$1,FALSE) -> 43740 | S49: =+VLOOKUP($B49,'Country-Level Tactics'!$B$5:$AL$248,'Country-Level Tactics'!X$1,FALSE) -> 7290 | T49: =+VLOOKUP($B49,'Country-Level Tactics'!$B$5:$AL$248,'Country-Level Tactics'!AC$1,FALSE) -> 32400 | U49: =+VLOOKUP($B49,'Country-Level Tactics'!$B$5:$AL$248,'Country-Level Tactics'!T$1,FALSE) -> 5400 | V49: =+J49 -> 29160 | W49: =+K49 -> 4860 | X49: =+R49/S49 -> 6 | Y49: =+S49/U49 -> 1.35 | Z49: =+T49/U49 -> 6 | AA49: =+V49/W49 -> 6 | AB49: =+W49/U49 -> 0.9 | AD49: =+R49/F49-1 -> 0 | AE49: =+S49/G49-1 -> 0 | AF49: =+T49/H49-1 -> 0 | AG49: =+U49/I49-1 -> 0 | AH49: =+V49/J49-1 -> 0 | AI49: =+W49/K49-1 -> 0 | AK49: 0.0017405867 | AL49: =+R49*$AK49 -> 76.133262 | AM49: =+S49*$AK49 -> 12.688877 | AN49: =+T49*$AK49 -> 56.395009 | AO49: =+U49*$AK49 -> 9.3991682 | AP49: =+V49*$AK49 -> 50.755508 | AQ49: =+W49*$AK49 -> 8.4592514 | AS49: =+VLOOKUP(B49,'Country & Code Abbreviation'!$B$3:$C$245,2,FALSE) -> TD
B50: Chile | C50: Latin America | D50: E~ | E50: =+VLOOKUP($B50,'[3]INT Web'!$B$5:$W$247,'[3]INT Web'!Q$1,FALSE) -> CLP | F50: =+VLOOKUP($B50,'[3]INT Web'!$B$5:$W$247,'[3]INT Web'!R$1,FALSE) -> 137900 | G50: =+VLOOKUP($B50,'[3]INT Web'!$B$5:$W$247,'[3]INT Web'!S$1,FALSE) -> 22900 | H50: =+VLOOKUP($B50,'[3]INT Web'!$B$5:$W$247,'[3]INT Web'!T$1,FALSE) -> 96300 | I50: =+VLOOKUP($B50,'[3]INT Web'!$B$5:$W$247,'[3]INT Web'!U$1,FALSE) -> 15900 | J50: =+VLOOKUP($B50,'[3]INT Web'!$B$5:$W$247,'[3]INT Web'!V$1,FALSE) -> 67400 | K50: =+VLOOKUP($B50,'[3]INT Web'!$B$5:$W$247,'[3]INT Web'!W$1,FALSE) -> 11200 | L50: =+F50/G50 -> 6.0218341 | M50: =+G50/I50 -> 1.4402516 | N50: =+H50/I50 -> 6.0566038 | O50: =+J50/K50 -> 6.0178571 | P50: =+K50/I50 -> 0.70440252 | Q50: =+E50 -> CLP | R50: =+VLOOKUP($B50,'Country-Level Tactics'!$B$5:$AL$248,'Country-Level Tactics'!AH$1,FALSE) -> 137900 | S50: =+VLOOKUP($B50,'Country-Level Tactics'!$B$5:$AL$248,'Country-Level Tactics'!X$1,FALSE) -> 22900 | T50: =+VLOOKUP($B50,'Country-Level Tactics'!$B$5:$AL$248,'Country-Level Tactics'!AC$1,FALSE) -> 96300 | U50: =+VLOOKUP($B50,'Country-Level Tactics'!$B$5:$AL$248,'Country-Level Tactics'!T$1,FALSE) -> 15900 | V50: =+J50 -> 67400 | W50: =+K50 -> 11200 | X50: =+R50/S50 -> 6.0218341 | Y50: =+S50/U50 -> 1.4402516 | Z50: =+T50/U50 -> 6.0566038 | AA50: =+V50/W50 -> 6.0178571 | AB50: =+W50/U50 -> 0.70440252 | AD50: =+R50/F50-1 -> 0 | AE50: =+S50/G50-1 -> 0 | AF50: =+T50/H50-1 -> 0 | AG50: =+U50/I50-1 -> 0 | AH50: =+V50/J50-1 -> 0 | AI50: =+W50/K50-1 -> 0 | AK50: 0.001079424 | AL50: =+R50*$AK50 -> 148.85257 | AM50: =+S50*$AK50 -> 24.71881 | AN50: =+T50*$AK50 -> 103.94853 | AO50: =+U50*$AK50 -> 17.162842 | AP50: =+V50*$AK50 -> 72.753178 | AQ50: =+W50*$AK50 -> 12.089549 | AS50: =+VLOOKUP(B50,'Country & Code Abbreviation'!$B$3:$C$245,2,FALSE) -> CL
B51: Christmas Island | C51: Asia | E51: =+VLOOKUP($B51,'[3]INT Web'!$B$5:$W$247,'[3]INT Web'!Q$1,FALSE) -> AUD | F51: =+VLOOKUP($B51,'[3]INT Web'!$B$5:$W$247,'[3]INT Web'!R$1,FALSE) -> 107.99 | G51: =+VLOOKUP($B51,'[3]INT Web'!$B$5:$W$247,'[3]INT Web'!S$1,FALSE) -> 17.99 | H51: =+VLOOKUP($B51,'[3]INT Web'!$B$5:$W$247,'[3]INT Web'!T$1,FALSE) -> 77.99 | I51: =+VLOOKUP($B51,'[3]INT Web'!$B$5:$W$247,'[3]INT Web'!U$1,FALSE) -> 12.99 | J51: =+VLOOKUP($B51,'[3]INT Web'!$B$5:$W$247,'[3]INT Web'!V$1,FALSE) -> 71.99 | K51: =+VLOOKUP($B51,'[3]INT Web'!$B$5:$W$247,'[3]INT Web'!W$1,FALSE) -> 11.99 | L51: =+F51/G51 -> 6.0027793 | M51: =+G51/I51 -> 1.3849115 | N51: =+H51/I51 -> 6.0038491 | O51: =+J51/K51 -> 6.0041701 | P51: =+K51/I51 -> 0.92301771 | Q51: =+E51 -> AUD | R51: =+VLOOKUP($B51,'Country-Level Tactics'!$B$5:$AL$248,'Country-Level Tactics'!AH$1,FALSE) -> 107.99 | S51: =+VLOOKUP($B51,'Country-Level Tactics'!$B$5:$AL$248,'Country-Level Tactics'!X$1,FALSE) -> 17.99 | T51: =+VLOOKUP($B51,'Country-Level Tactics'!$B$5:$AL$248,'Country-Level Tactics'!AC$1,FALSE) -> 77.99 | U51: =+VLOOKUP($B51,'Country-Level Tactics'!$B$5:$AL$248,'Country-Level Tactics'!T$1,FALSE) -> 12.99 | V51: =+J51 -> 71.99 | W51: =+K51 -> 11.99 | X51: =+R51/S51 -> 6.0027793 | Y51: =+S51/U51 -> 1.3849115 | Z51: =+T51/U51 -> 6.0038491 | AA51: =+V51/W51 -> 6.0041701 | AB51: =+W51/U51 -> 0.92301771 | AD51: =+R51/F51-1 -> 0 | AE51: =+S51/G51-1 -> 0 | AF51: =+T51/H51-1 -> 0 | AG51: =+U51/I51-1 -> 0 | AH51: =+V51/J51-1 -> 0 | AI51: =+W51/K51-1 -> 0 | AK51: 0.69375 | AL51: =+R51*$AK51 -> 74.918062 | AM51: =+S51*$AK51 -> 12.480562 | AN51: =+T51*$AK51 -> 54.105562 | AO51: =+U51*$AK51 -> 9.0118125 | AP51: =+V51*$AK51 -> 49.943062 | AQ51: =+W51*$AK51 -> 8.3180625 | AS51: =+VLOOKUP(B51,'Country & Code Abbreviation'!$B$3:$C$245,2,FALSE) -> CX
B52: Cocos (Keeling) Island | C52: Asia | E52: =+VLOOKUP($B52,'[3]INT Web'!$B$5:$W$247,'[3]INT Web'!Q$1,FALSE) -> AUD | F52: =+VLOOKUP($B52,'[3]INT Web'!$B$5:$W$247,'[3]INT Web'!R$1,FALSE) -> 161.99 | G52: =+VLOOKUP($B52,'[3]INT Web'!$B$5:$W$247,'[3]INT Web'!S$1,FALSE) -> 26.99 | H52: =+VLOOKUP($B52,'[3]INT Web'!$B$5:$W$247,'[3]INT Web'!T$1,FALSE) -> 119.99 | I52: =+VLOOKUP($B52,'[3]INT Web'!$B$5:$W$247,'[3]INT Web'!U$1,FALSE) -> 19.99 | J52: =+VLOOKUP($B52,'[3]INT Web'!$B$5:$W$247,'[3]INT Web'!V$1,FALSE) -> 107.99 | K52: =+VLOOKUP($B52,'[3]INT Web'!$B$5:$W$247,'[3]INT Web'!W$1,FALSE) -> 17.99 | L52: =+F52/G52 -> 6.0018525 | M52: =+G52/I52 -> 1.3501751 | N52: =+H52/I52 -> 6.0025013 | O52: =+J52/K52 -> 6.0027793 | P52: =+K52/I52 -> 0.89994997 | Q52: =+E52 -> AUD | R52: =+VLOOKUP($B52,'Country-Level Tactics'!$B$5:$AL$248,'Country-Level Tactics'!AH$1,FALSE) -> 161.99 | S52: =+VLOOKUP($B52,'Country-Level Tactics'!$B$5:$AL$248,'Country-Level Tactics'!X$1,FALSE) -> 26.99 | T52: =+VLOOKUP($B52,'Country-Level Tactics'!$B$5:$AL$248,'Country-Level Tactics'!AC$1,FALSE) -> 119.99 | U52: =+VLOOKUP($B52,'Country-Level Tactics'!$B$5:$AL$248,'Country-Level Tactics'!T$1,FALSE) -> 19.99 | V52: =+J52 -> 107.99 | W52: =+K52 -> 17.99 | X52: =+R52/S52 -> 6.0018525 | Y52: =+S52/U52 -> 1.3501751 | Z52: =+T52/U52 -> 6.0025013 | AA52: =+V52/W52 -> 6.0027793 | AB52: =+W52/U52 -> 0.89994997 | AD52: =+R52/F52-1 -> 0 | AE52: =+S52/G52-1 -> 0 | AF52: =+T52/H52-1 -> 0 | AG52: =+U52/I52-1 -> 0 | AH52: =+V52/J52-1 -> 0 | AI52: =+W52/K52-1 -> 0 | AK52: 0.69375 | AL52: =+R52*$AK52 -> 112.38056 | AM52: =+S52*$AK52 -> 18.724312 | AN52: =+T52*$AK52 -> 83.243062 | AO52: =+U52*$AK52 -> 13.868062 | AP52: =+V52*$AK52 -> 74.918062 | AQ52: =+W52*$AK52 -> 12.480562 | AS52: =+VLOOKUP(B52,'Country & Code Abbreviation'!$B$3:$C$245,2,FALSE) -> CC
B53: Colombia | C53: Latin America | E53: =+VLOOKUP($B53,'[3]INT Web'!$B$5:$W$247,'[3]INT Web'!Q$1,FALSE) -> COP | F53: =+VLOOKUP($B53,'[3]INT Web'!$B$5:$W$247,'[3]INT Web'!R$1,FALSE) -> 335900 | G53: =+VLOOKUP($B53,'[3]INT Web'!$B$5:$W$247,'[3]INT Web'!S$1,FALSE) -> 55900 | H53: =+VLOOKUP($B53,'[3]INT Web'!$B$5:$W$247,'[3]INT Web'!T$1,FALSE) -> 248900 | I53: =+VLOOKUP($B53,'[3]INT Web'!$B$5:$W$247,'[3]INT Web'!U$1,FALSE) -> 41400 | J53: =+VLOOKUP($B53,'[3]INT Web'!$B$5:$W$247,'[3]INT Web'!V$1,FALSE) -> 223900 | K53: =+VLOOKUP($B53,'[3]INT Web'!$B$5:$W$247,'[3]INT Web'!W$1,FALSE) -> 37400 | L53: =+F53/G53 -> 6.0089445 | M53: =+G53/I53 -> 1.3502415 | N53: =+H53/I53 -> 6.0120773 | O53: =+J53/K53 -> 5.986631 | P53: =+K53/I53 -> 0.90338164 | Q53: =+E53 -> COP | R53: =+VLOOKUP($B53,'Country-Level Tactics'!$B$5:$AL$248,'Country-Level Tactics'!AH$1,FALSE) -> 335900 | S53: =+VLOOKUP($B53,'Country-Level Tactics'!$B$5:$AL$248,'Country-Level Tactics'!X$1,FALSE) -> 55900 | T53: =+VLOOKUP($B53,'Country-Level Tactics'!$B$5:$AL$248,'Country-Level Tactics'!AC$1,FALSE) -> 248900 | U53: =+VLOOKUP($B53,'Country-Level Tactics'!$B$5:$AL$248,'Country-Level Tactics'!T$1,FALSE) -> 41400 | V53: =+J53 -> 223900 | W53: =+K53 -> 37400 | X53: =+R53/S53 -> 6.0089445 | Y53: =+S53/U53 -> 1.3502415 | Z53: =+T53/U53 -> 6.0120773 | AA53: =+V53/W53 -> 5.986631 | AB53: =+W53/U53 -> 0.90338164 | AD53: =+R53/F53-1 -> 0 | AE53: =+S53/G53-1 -> 0 | AF53: =+T53/H53-1 -> 0 | AG53: =+U53/I53-1 -> 0 | AH53: =+V53/J53-1 -> 0 | AI53: =+W53/K53-1 -> 0 | AK53: 0.00029839078 | AL53: =+R53*$AK53 -> 100.22946 | AM53: =+S53*$AK53 -> 16.680045 | AN53: =+T53*$AK53 -> 74.269465 | AO53: =+U53*$AK53 -> 12.353378 | AP53: =+V53*$AK53 -> 66.809696 | AQ53: =+W53*$AK53 -> 11.159815 | AS53: =+VLOOKUP(B53,'Country & Code Abbreviation'!$B$3:$C$245,2,FALSE) -> CO
B54: Comoros | C54: Africa | E54: =+VLOOKUP($B54,'[3]INT Web'!$B$5:$W$247,'[3]INT Web'!Q$1,FALSE) -> KMF | F54: =+VLOOKUP($B54,'[3]INT Web'!$B$5:$W$247,'[3]INT Web'!R$1,FALSE) -> 33240 | G54: =+VLOOKUP($B54,'[3]INT Web'!$B$5:$W$247,'[3]INT Web'!S$1,FALSE) -> 5540 | H54: =+VLOOKUP($B54,'[3]INT Web'!$B$5:$W$247,'[3]INT Web'!T$1,FALSE) -> 24600 | I54: =+VLOOKUP($B54,'[3]INT Web'!$B$5:$W$247,'[3]INT Web'!U$1,FALSE) -> 4100 | J54: =+VLOOKUP($B54,'[3]INT Web'!$B$5:$W$247,'[3]INT Web'!V$1,FALSE) -> 22140 | K54: =+VLOOKUP($B54,'[3]INT Web'!$B$5:$W$247,'[3]INT Web'!W$1,FALSE) -> 3690 | L54: =+F54/G54 -> 6 | M54: =+G54/I54 -> 1.3512195 | N54: =+H54/I54 -> 6 | O54: =+J54/K54 -> 6 | P54: =+K54/I54 -> 0.9 | Q54: =+E54 -> KMF | R54: =+VLOOKUP($B54,'Country-Level Tactics'!$B$5:$AL$248,'Country-Level Tactics'!AH$1,FALSE) -> 33240 | S54: =+VLOOKUP($B54,'Country-Level Tactics'!$B$5:$AL$248,'Country-Level Tactics'!X$1,FALSE) -> 5540 | T54: =+VLOOKUP($B54,'Country-Level Tactics'!$B$5:$AL$248,'Country-Level Tactics'!AC$1,FALSE) -> 24600 | U54: =+VLOOKUP($B54,'Country-Level Tactics'!$B$5:$AL$248,'Country-Level Tactics'!T$1,FALSE) -> 4100 | V54: =+J54 -> 22140 | W54: =+K54 -> 3690 | X54: =+R54/S54 -> 6 | Y54: =+S54/U54 -> 1.3512195 | Z54: =+T54/U54 -> 6 | AA54: =+V54/W54 -> 6 | AB54: =+W54/U54 -> 0.9 | AD54: =+R54/F54-1 -> 0 | AE54: =+S54/G54-1 -> 0 | AF54: =+T54/H54-1 -> 0 | AG54: =+U54/I54-1 -> 0 | AH54: =+V54/J54-1 -> 0 | AI54: =+W54/K54-1 -> 0 | AK54: 0.0023207823 | AL54: =+R54*$AK54 -> 77.142804 | AM54: =+S54*$AK54 -> 12.857134 | AN54: =+T54*$AK54 -> 57.091245 | AO54: =+U54*$AK54 -> 9.5152074 | AP54: =+V54*$AK54 -> 51.38212 | AQ54: =+W54*$AK54 -> 8.5636867 | AS54: =+VLOOKUP(B54,'Country & Code Abbreviation'!$B$3:$C$245,2,FALSE) -> KM
B55: Congo | C55: Africa | E55: =+VLOOKUP($B55,'[3]INT Web'!$B$5:$W$247,'[3]INT Web'!Q$1,FALSE) -> XAF | F55: =+VLOOKUP($B55,'[3]INT Web'!$B$5:$W$247,'[3]INT Web'!R$1,FALSE) -> 43740 | G55: =+VLOOKUP($B55,'[3]INT Web'!$B$5:$W$247,'[3]INT Web'!S$1,FALSE) -> 7290 | H55: =+VLOOKUP($B55,'[3]INT Web'!$B$5:$W$247,'[3]INT Web'!T$1,FALSE) -> 32400 | I55: =+VLOOKUP($B55,'[3]INT Web'!$B$5:$W$247,'[3]INT Web'!U$1,FALSE) -> 5400 | J55: =+VLOOKUP($B55,'[3]INT Web'!$B$5:$W$247,'[3]INT Web'!V$1,FALSE) -> 29160 | K55: =+VLOOKUP($B55,'[3]INT Web'!$B$5:$W$247,'[3]INT Web'!W$1,FALSE) -> 4860 | L55: =+F55/G55 -> 6 | M55: =+G55/I55 -> 1.35 | N55: =+H55/I55 -> 6 | O55: =+J55/K55 -> 6 | P55: =+K55/I55 -> 0.9 | Q55: =+E55 -> XAF | R55: =+VLOOKUP($B55,'Country-Level Tactics'!$B$5:$AL$248,'Country-Level Tactics'!AH$1,FALSE) -> 43740 | S55: =+VLOOKUP($B55,'Country-Level Tactics'!$B$5:$AL$248,'Country-Level Tactics'!X$1,FALSE) -> 7290 | T55: =+VLOOKUP($B55,'Country-Level Tactics'!$B$5:$AL$248,'Country-Level Tactics'!AC$1,FALSE) -> 32400 | U55: =+VLOOKUP($B55,'Country-Level Tactics'!$B$5:$AL$248,'Country-Level Tactics'!T$1,FALSE) -> 5400 | V55: =+J55 -> 29160 | W55: =+K55 -> 4860 | X55: =+R55/S55 -> 6 | Y55: =+S55/U55 -> 1.35 | Z55: =+T55/U55 -> 6 | AA55: =+V55/W55 -> 6 | AB55: =+W55/U55 -> 0.9 | AD55: =+R55/F55-1 -> 0 | AE55: =+S55/G55-1 -> 0 | AF55: =+T55/H55-1 -> 0 | AG55: =+U55/I55-1 -> 0 | AH55: =+V55/J55-1 -> 0 | AI55: =+W55/K55-1 -> 0 | AK55: 0.0017405867 | AL55: =+R55*$AK55 -> 76.133262 | AM55: =+S55*$AK55 -> 12.688877 | AN55: =+T55*$AK55 -> 56.395009 | AO55: =+U55*$AK55 -> 9.3991682 | AP55: =+V55*$AK55 -> 50.755508 | AQ55: =+W55*$AK55 -> 8.4592514 | AS55: =+VLOOKUP(B55,'Country & Code Abbreviation'!$B$3:$C$245,2,FALSE) -> CG
B56: Cook Islands | C56: Asia | E56: =+VLOOKUP($B56,'[3]INT Web'!$B$5:$W$247,'[3]INT Web'!Q$1,FALSE) -> NZD | F56: =+VLOOKUP($B56,'[3]INT Web'!$B$5:$W$247,'[3]INT Web'!R$1,FALSE) -> 203.99 | G56: =+VLOOKUP($B56,'[3]INT Web'!$B$5:$W$247,'[3]INT Web'!S$1,FALSE) -> 33.99 | H56: =+VLOOKUP($B56,'[3]INT Web'!$B$5:$W$247,'[3]INT Web'!T$1,FALSE) -> 149.99 | I56: =+VLOOKUP($B56,'[3]INT Web'!$B$5:$W$247,'[3]INT Web'!U$1,FALSE) -> 24.99 | J56: =+VLOOKUP($B56,'[3]INT Web'!$B$5:$W$247,'[3]INT Web'!V$1,FALSE) -> 144.99 | K56: =+VLOOKUP($B56,'[3]INT Web'!$B$5:$W$247,'[3]INT Web'!W$1,FALSE) -> 21.99 | L56: =+F56/G56 -> 6.001471 | M56: =+G56/I56 -> 1.3601441 | N56: =+H56/I56 -> 6.0020008 | O56: =+J56/K56 -> 6.5934516 | P56: =+K56/I56 -> 0.87995198 | Q56: =+E56 -> NZD | R56: =+VLOOKUP($B56,'Country-Level Tactics'!$B$5:$AL$248,'Country-Level Tactics'!AH$1,FALSE) -> 203.99 | S56: =+VLOOKUP($B56,'Country-Level Tactics'!$B$5:$AL$248,'Country-Level Tactics'!X$1,FALSE) -> 33.99 | T56: =+VLOOKUP($B56,'Country-Level Tactics'!$B$5:$AL$248,'Country-Level Tactics'!AC$1,FALSE) -> 149.99 | U56: =+VLOOKUP($B56,'Country-Level Tactics'!$B$5:$AL$248,'Country-Level Tactics'!T$1,FALSE) -> 24.99 | V56: =+J56 -> 144.99 | W56: =+K56 -> 21.99 | X56: =+R56/S56 -> 6.001471 | Y56: =+S56/U56 -> 1.3601441 | Z56: =+T56/U56 -> 6.0020008 | AA56: =+V56/W56 -> 6.5934516 | AB56: =+W56/U56 -> 0.87995198 | AD56: =+R56/F56-1 -> 0 | AE56: =+S56/G56-1 -> 0 | AF56: =+T56/H56-1 -> 0 | AG56: =+U56/I56-1 -> 0 | AH56: =+V56/J56-1 -> 0 | AI56: =+W56/K56-1 -> 0 | AK56: 0.56845 | AL56: =+R56*$AK56 -> 115.95812 | AM56: =+S56*$AK56 -> 19.321616 | AN56: =+T56*$AK56 -> 85.261816 | AO56: =+U56*$AK56 -> 14.205565 | AP56: =+V56*$AK56 -> 82.419566 | AQ56: =+W56*$AK56 -> 12.500215 | AS56: =+VLOOKUP(B56,'Country & Code Abbreviation'!$B$3:$C$245,2,FALSE) -> CK
B57: Costa Rica | C57: Latin America | E57: =+VLOOKUP($B57,'[3]INT Web'!$B$5:$W$247,'[3]INT Web'!Q$1,FALSE) -> CRC | F57: =+VLOOKUP($B57,'[3]INT Web'!$B$5:$W$247,'[3]INT Web'!R$1,FALSE) -> 78000 | G57: =+VLOOKUP($B57,'[3]INT Web'!$B$5:$W$247,'[3]INT Web'!S$1,FALSE) -> 13000 | H57: =+VLOOKUP($B57,'[3]INT Web'!$B$5:$W$247,'[3]INT Web'!T$1,FALSE) -> 60000 | I57: =+VLOOKUP($B57,'[3]INT Web'!$B$5:$W$247,'[3]INT Web'!U$1,FALSE) -> 10000 | J57: =+VLOOKUP($B57,'[3]INT Web'!$B$5:$W$247,'[3]INT Web'!V$1,FALSE) -> 54000 | K57: =+VLOOKUP($B57,'[3]INT Web'!$B$5:$W$247,'[3]INT Web'!W$1,FALSE) -> 9000 | L57: =+F57/G57 -> 6 | M57: =+G57/I57 -> 1.3 | N57: =+H57/I57 -> 6 | O57: =+J57/K57 -> 6 | P57: =+K57/I57 -> 0.9 | Q57: =+E57 -> CRC | R57: =+VLOOKUP($B57,'Country-Level Tactics'!$B$5:$AL$248,'Country-Level Tactics'!AH$1,FALSE) -> 78000 | S57: =+VLOOKUP($B57,'Country-Level Tactics'!$B$5:$AL$248,'Country-Level Tactics'!X$1,FALSE) -> 13000 | T57: =+VLOOKUP($B57,'Country-Level Tactics'!$B$5:$AL$248,'Country-Level Tactics'!AC$1,FALSE) -> 60000 | U57: =+VLOOKUP($B57,'Country-Level Tactics'!$B$5:$AL$248,'Country-Level Tactics'!T$1,FALSE) -> 10000 | V57: =+J57 -> 54000 | W57: =+K57 -> 9000 | X57: =+R57/S57 -> 6 | Y57: =+S57/U57 -> 1.3 | Z57: =+T57/U57 -> 6 | AA57: =+V57/W57 -> 6 | AB57: =+W57/U57 -> 0.9 | AD57: =+R57/F57-1 -> 0 | AE57: =+S57/G57-1 -> 0 | AF57: =+T57/H57-1 -> 0 | AG57: =+U57/I57-1 -> 0 | AH57: =+V57/J57-1 -> 0 | AI57: =+W57/K57-1 -> 0 | AK57: 0.0022055581 | AL57: =+R57*$AK57 -> 172.03353 | AM57: =+S57*$AK57 -> 28.672255 | AN57: =+T57*$AK57 -> 132.33349 | AO57: =+U57*$AK57 -> 22.055581 | AP57: =+V57*$AK57 -> 119.10014 | AQ57: =+W57*$AK57 -> 19.850023 | AS57: =+VLOOKUP(B57,'Country & Code Abbreviation'!$B$3:$C$245,2,FALSE) -> CR
B58: Cote D'Ivoire | C58: Africa | E58: =+VLOOKUP($B58,'[3]INT Web'!$B$5:$W$247,'[3]INT Web'!Q$1,FALSE) -> XOF | F58: =+VLOOKUP($B58,'[3]INT Web'!$B$5:$W$247,'[3]INT Web'!R$1,FALSE) -> 44580 | G58: =+VLOOKUP($B58,'[3]INT Web'!$B$5:$W$247,'[3]INT Web'!S$1,FALSE) -> 7430 | H58: =+VLOOKUP($B58,'[3]INT Web'!$B$5:$W$247,'[3]INT Web'!T$1,FALSE) -> 33000 | I58: =+VLOOKUP($B58,'[3]INT Web'!$B$5:$W$247,'[3]INT Web'!U$1,FALSE) -> 5500 | J58: =+VLOOKUP($B58,'[3]INT Web'!$B$5:$W$247,'[3]INT Web'!V$1,FALSE) -> 29700 | K58: =+VLOOKUP($B58,'[3]INT Web'!$B$5:$W$247,'[3]INT Web'!W$1,FALSE) -> 4950 | L58: =+F58/G58 -> 6 | M58: =+G58/I58 -> 1.3509091 | N58: =+H58/I58 -> 6 | O58: =+J58/K58 -> 6 | P58: =+K58/I58 -> 0.9 | Q58: =+E58 -> XOF | R58: =+VLOOKUP($B58,'Country-Level Tactics'!$B$5:$AL$248,'Country-Level Tactics'!AH$1,FALSE) -> 44580 | S58: =+VLOOKUP($B58,'Country-Level Tactics'!$B$5:$AL$248,'Country-Level Tactics'!X$1,FALSE) -> 7430 | T58: =+VLOOKUP($B58,'Country-Level Tactics'!$B$5:$AL$248,'Country-Level Tactics'!AC$1,FALSE) -> 33000 | U58: =+VLOOKUP($B58,'Country-Level Tactics'!$B$5:$AL$248,'Country-Level Tactics'!T$1,FALSE) -> 5500 | V58: =+J58 -> 29700 | W58: =+K58 -> 4950 | X58: =+R58/S58 -> 6 | Y58: =+S58/U58 -> 1.3509091 | Z58: =+T58/U58 -> 6 | AA58: =+V58/W58 -> 6 | AB58: =+W58/U58 -> 0.9 | AD58: =+R58/F58-1 -> 0 | AE58: =+S58/G58-1 -> 0 | AF58: =+T58/H58-1 -> 0 | AG58: =+U58/I58-1 -> 0 | AH58: =+V58/J58-1 -> 0 | AI58: =+W58/K58-1 -> 0 | AK58: 0.0017405867 | AL58: =+R58*$AK58 -> 77.595355 | AM58: =+S58*$AK58 -> 12.932559 | AN58: =+T58*$AK58 -> 57.439361 | AO58: =+U58*$AK58 -> 9.5732268 | AP58: =+V58*$AK58 -> 51.695425 | AQ58: =+W58*$AK58 -> 8.6159042 | AS58: =+VLOOKUP(B58,'Country & Code Abbreviation'!$B$3:$C$245,2,FALSE) -> CI
B59: Croatia | C59: Europe | E59: =+VLOOKUP($B59,'[3]INT Web'!$B$5:$W$247,'[3]INT Web'!Q$1,FALSE) -> EUR | F59: =+VLOOKUP($B59,'[3]INT Web'!$B$5:$W$247,'[3]INT Web'!R$1,FALSE) -> 107.99 | G59: =+VLOOKUP($B59,'[3]INT Web'!$B$5:$W$247,'[3]INT Web'!S$1,FALSE) -> 17.99 | H59: =+VLOOKUP($B59,'[3]INT Web'!$B$5:$W$247,'[3]INT Web'!T$1,FALSE) -> 71.99 | I59: =+VLOOKUP($B59,'[3]INT Web'!$B$5:$W$247,'[3]INT Web'!U$1,FALSE) -> 11.99 | J59: =+VLOOKUP($B59,'[3]INT Web'!$B$5:$W$247,'[3]INT Web'!V$1,FALSE) -> 66.99 | K59: =+VLOOKUP($B59,'[3]INT Web'!$B$5:$W$247,'[3]INT Web'!W$1,FALSE) -> 10.99 | L59: =+F59/G59 -> 6.0027793 | M59: =+G59/I59 -> 1.500417 | N59: =+H59/I59 -> 6.0041701 | O59: =+J59/K59 -> 6.0955414 | P59: =+K59/I59 -> 0.91659716 | Q59: =+E59 -> EUR | R59: =+VLOOKUP($B59,'Country-Level Tactics'!$B$5:$AL$248,'Country-Level Tactics'!AH$1,FALSE) -> 107.99 | S59: =+VLOOKUP($B59,'Country-Level Tactics'!$B$5:$AL$248,'Country-Level Tactics'!X$1,FALSE) -> 17.99 | T59: =+VLOOKUP($B59,'Country-Level Tactics'!$B$5:$AL$248,'Country-Level Tactics'!AC$1,FALSE) -> 71.99 | U59: =+VLOOKUP($B59,'Country-Level Tactics'!$B$5:$AL$248,'Country-Level Tactics'!T$1,FALSE) -> 11.99 | V59: =+J59 -> 66.99 | W59: =+K59 -> 10.99 | X59: =+R59/S59 -> 6.0027793 | Y59: =+S59/U59 -> 1.500417 | Z59: =+T59/U59 -> 6.0041701 | AA59: =+V59/W59 -> 6.0955414 | AB59: =+W59/U59 -> 0.91659716 | AD59: =+R59/F59-1 -> 0 | AE59: =+S59/G59-1 -> 0 | AF59: =+T59/H59-1 -> 0 | AG59: =+U59/I59-1 -> 0 | AH59: =+V59/J59-1 -> 0 | AI59: =+W59/K59-1 -> 0 | AK59: 1.14175 | AL59: =+R59*$AK59 -> 123.29758 | AM59: =+S59*$AK59 -> 20.540083 | AN59: =+T59*$AK59 -> 82.194582 | AO59: =+U59*$AK59 -> 13.689583 | AP59: =+V59*$AK59 -> 76.485833 | AQ59: =+W59*$AK59 -> 12.547833 | AS59: =+VLOOKUP(B59,'Country & Code Abbreviation'!$B$3:$C$245,2,FALSE) -> HR
B60: Curacao | C60: Latin America | E60: =+VLOOKUP($B60,'[3]INT Web'!$B$5:$W$247,'[3]INT Web'!Q$1,FALSE) -> ANG | F60: =+VLOOKUP($B60,'[3]INT Web'!$B$5:$W$247,'[3]INT Web'!R$1,FALSE) -> 167.99 | G60: =+VLOOKUP($B60,'[3]INT Web'!$B$5:$W$247,'[3]INT Web'!S$1,FALSE) -> 27.99 | H60: =+VLOOKUP($B60,'[3]INT Web'!$B$5:$W$247,'[3]INT Web'!T$1,FALSE) -> 125.99 | I60: =+VLOOKUP($B60,'[3]INT Web'!$B$5:$W$247,'[3]INT Web'!U$1,FALSE) -> 20.99 | J60: =+VLOOKUP($B60,'[3]INT Web'!$B$5:$W$247,'[3]INT Web'!V$1,FALSE) -> 113.99 | K60: =+VLOOKUP($B60,'[3]INT Web'!$B$5:$W$247,'[3]INT Web'!W$1,FALSE) -> 18.99 | L60: =+F60/G60 -> 6.0017864 | M60: =+G60/I60 -> 1.3334921 | N60: =+H60/I60 -> 6.0023821 | O60: =+J60/K60 -> 6.002633 | P60: =+K60/I60 -> 0.90471653 | Q60: =+E60 -> ANG | R60: =+VLOOKUP($B60,'Country-Level Tactics'!$B$5:$AL$248,'Country-Level Tactics'!AH$1,FALSE) -> 167.99 | S60: =+VLOOKUP($B60,'Country-Level Tactics'!$B$5:$AL$248,'Country-Level Tactics'!X$1,FALSE) -> 27.99 | T60: =+VLOOKUP($B60,'Country-Level Tactics'!$B$5:$AL$248,'Country-Level Tactics'!AC$1,FALSE) -> 125.99 | U60: =+VLOOKUP($B60,'Country-Level Tactics'!$B$5:$AL$248,'Country-Level Tactics'!T$1,FALSE) -> 20.99 | V60: =+J60 -> 113.99 | W60: =+K60 -> 18.99 | X60: =+R60/S60 -> 6.0017864 | Y60: =+S60/U60 -> 1.3334921 | Z60: =+T60/U60 -> 6.0023821 | AA60: =+V60/W60 -> 6.002633 | AB60: =+W60/U60 -> 0.90471653 | AD60: =+R60/F60-1 -> 0 | AE60: =+S60/G60-1 -> 0 | AF60: =+T60/H60-1 -> 0 | AG60: =+U60/I60-1 -> 0 | AH60: =+V60/J60-1 -> 0 | AI60: =+W60/K60-1 -> 0 | AK60: 0.55865926 | AL60: =+R60*$AK60 -> 93.849169 | AM60: =+S60*$AK60 -> 15.636873 | AN60: =+T60*$AK60 -> 70.38548 | AO60: =+U60*$AK60 -> 11.726258 | AP60: =+V60*$AK60 -> 63.681569 | AQ60: =+W60*$AK60 -> 10.608939 | AS60: =+VLOOKUP(B60,'Country & Code Abbreviation'!$B$3:$C$245,2,FALSE) -> CW
B61: Cyprus | C61: Europe | E61: =+VLOOKUP($B61,'[3]INT Web'!$B$5:$W$247,'[3]INT Web'!Q$1,FALSE) -> EUR | F61: =+VLOOKUP($B61,'[3]INT Web'!$B$5:$W$247,'[3]INT Web'!R$1,FALSE) -> 89.99 | G61: =+VLOOKUP($B61,'[3]INT Web'!$B$5:$W$247,'[3]INT Web'!S$1,FALSE) -> 12.99 | H61: =+VLOOKUP($B61,'[3]INT Web'!$B$5:$W$247,'[3]INT Web'!T$1,FALSE) -> 69.99 | I61: =+VLOOKUP($B61,'[3]INT Web'!$B$5:$W$247,'[3]INT Web'!U$1,FALSE) -> 9.99 | J61: =+VLOOKUP($B61,'[3]INT Web'!$B$5:$W$247,'[3]INT Web'!V$1,FALSE) -> 59.99 | K61: =+VLOOKUP($B61,'[3]INT Web'!$B$5:$W$247,'[3]INT Web'!W$1,FALSE) -> 8.99 | L61: =+F61/G61 -> 6.9276366 | M61: =+G61/I61 -> 1.3003003 | N61: =+H61/I61 -> 7.006006 | O61: =+J61/K61 -> 6.67297 | P61: =+K61/I61 -> 0.8998999 | Q61: =+E61 -> EUR | R61: =+VLOOKUP($B61,'Country-Level Tactics'!$B$5:$AL$248,'Country-Level Tactics'!AH$1,FALSE) -> 89.99 | S61: =+VLOOKUP($B61,'Country-Level Tactics'!$B$5:$AL$248,'Country-Level Tactics'!X$1,FALSE) -> 12.99 | T61: =+VLOOKUP($B61,'Country-Level Tactics'!$B$5:$AL$248,'Country-Level Tactics'!AC$1,FALSE) -> 69.99 | U61: =+VLOOKUP($B61,'Country-Level Tactics'!$B$5:$AL$248,'Country-Level Tactics'!T$1,FALSE) -> 9.99 | V61: =+J61 -> 59.99 | W61: =+K61 -> 8.99 | X61: =+R61/S61 -> 6.9276366 | Y61: =+S61/U61 -> 1.3003003 | Z61: =+T61/U61 -> 7.006006 | AA61: =+V61/W61 -> 6.67297 | AB61: =+W61/U61 -> 0.8998999 | AD61: =+R61/F61-1 -> 0 | AE61: =+S61/G61-1 -> 0 | AF61: =+T61/H61-1 -> 0 | AG61: =+U61/I61-1 -> 0 | AH61: =+V61/J61-1 -> 0 | AI61: =+W61/K61-1 -> 0 | AK61: 1.14175 | AL61: =+R61*$AK61 -> 102.74608 | AM61: =+S61*$AK61 -> 14.831333 | AN61: =+T61*$AK61 -> 79.911082 | AO61: =+U61*$AK61 -> 11.406083 | AP61: =+V61*$AK61 -> 68.493583 | AQ61: =+W61*$AK61 -> 10.264333 | AS61: =+VLOOKUP(B61,'Country & Code Abbreviation'!$B$3:$C$245,2,FALSE) -> CY
B62: Czech Republic | C62: Europe | E62: =+VLOOKUP($B62,'[3]INT Web'!$B$5:$W$247,'[3]INT Web'!Q$1,FALSE) -> CZK | F62: =+VLOOKUP($B62,'[3]INT Web'!$B$5:$W$247,'[3]INT Web'!R$1,FALSE) -> 3599.99 | G62: =+VLOOKUP($B62,'[3]INT Web'!$B$5:$W$247,'[3]INT Web'!S$1,FALSE) -> 549.99 | H62: =+VLOOKUP($B62,'[3]INT Web'!$B$5:$W$247,'[3]INT Web'!T$1,FALSE) -> 2399.99 | I62: =+VLOOKUP($B62,'[3]INT Web'!$B$5:$W$247,'[3]INT Web'!U$1,FALSE) -> 399.99 | J62: =+VLOOKUP($B62,'[3]INT Web'!$B$5:$W$247,'[3]INT Web'!V$1,FALSE) -> 2159.99 | K62: =+VLOOKUP($B62,'[3]INT Web'!$B$5:$W$247,'[3]INT Web'!W$1,FALSE) -> 359.99 | L62: =+F62/G62 -> 6.5455554 | M62: =+G62/I62 -> 1.3750094 | N62: =+H62/I62 -> 6.000125 | O62: =+J62/K62 -> 6.0001389 | P62: =+K62/I62 -> 0.8999975 | Q62: =+E62 -> CZK | R62: =+VLOOKUP($B62,'Country-Level Tactics'!$B$5:$AL$248,'Country-Level Tactics'!AH$1,FALSE) -> 3599.99 | S62: =+VLOOKUP($B62,'Country-Level Tactics'!$B$5:$AL$248,'Country-Level Tactics'!X$1,FALSE) -> 549.99 | T62: =+VLOOKUP($B62,'Country-Level Tactics'!$B$5:$AL$248,'Country-Level Tactics'!AC$1,FALSE) -> 2399.99 | U62: =+VLOOKUP($B62,'Country-Level Tactics'!$B$5:$AL$248,'Country-Level Tactics'!T$1,FALSE) -> 399.99 | V62: =+J62 -> 2159.99 | W62: =+K62 -> 359.99 | X62: =+R62/S62 -> 6.5455554 | Y62: =+S62/U62 -> 1.3750094 | Z62: =+T62/U62 -> 6.000125 | AA62: =+V62/W62 -> 6.0001389 | AB62: =+W62/U62 -> 0.8999975 | AD62: =+R62/F62-1 -> 0 | AE62: =+S62/G62-1 -> 0 | AF62: =+T62/H62-1 -> 0 | AG62: =+U62/I62-1 -> 0 | AH62: =+V62/J62-1 -> 0 | AI62: =+W62/K62-1 -> 0 | AK62: 0.047255963 | AL62: =+R62*$AK62 -> 170.12099 | AM62: =+S62*$AK62 -> 25.990307 | AN62: =+T62*$AK62 -> 113.41384 | AO62: =+U62*$AK62 -> 18.901913 | AP62: =+V62*$AK62 -> 102.07241 | AQ62: =+W62*$AK62 -> 17.011674 | AS62: =+VLOOKUP(B62,'Country & Code Abbreviation'!$B$3:$C$245,2,FALSE) -> CZ
... B66: Dominica | C66: Latin America | E66: =+VLOOKUP($B66,'[3]INT Web'!$B$5:$W$247,'[3]INT Web'!Q$1,FALSE) -> XCD | F66: =+VLOOKUP($B66,'[3]INT Web'!$B$5:$W$247,'[3]INT Web'!R$1,FALSE) -> 305.99 | G66: =+VLOOKUP($B66,'[3]INT Web'!$B$5:$W$247,'[3]INT Web'!S$1,FALSE) -> 50.99 | H66: =+VLOOKUP($B66,'[3]INT Web'!$B$5:$W$247,'[3]INT Web'!T$1,FALSE) -> 227.99 | I66: =+VLOOKUP($B66,'[3]INT Web'!$B$5:$W$247,'[3]INT Web'!U$1,FALSE) -> 37.99 | J66: =+VLOOKUP($B66,'[3]INT Web'!$B$5:$W$247,'[3]INT Web'!V$1,FALSE) -> 203.99 | K66: =+VLOOKUP($B66,'[3]INT Web'!$B$5:$W$247,'[3]INT Web'!W$1,FALSE) -> 33.99 | L66: =+F66/G66 -> 6.0009806 | M66: =+G66/I66 -> 1.3421953 | N66: =+H66/I66 -> 6.0013161 | O66: =+J66/K66 -> 6.001471 | P66: =+K66/I66 -> 0.89470913 | Q66: =+E66 -> XCD | R66: =+VLOOKUP($B66,'Country-Level Tactics'!$B$5:$AL$248,'Country-Level Tactics'!AH$1,FALSE) -> 305.99 | S66: =+VLOOKUP($B66,'Country-Level Tactics'!$B$5:$AL$248,'Country-Level Tactics'!X$1,FALSE) -> 50.99 | T66: =+VLOOKUP($B66,'Country-Level Tactics'!$B$5:$AL$248,'Country-Level Tactics'!AC$1,FALSE) -> 227.99 | U66: =+VLOOKUP($B66,'Country-Level Tactics'!$B$5:$AL$248,'Country-Level Tactics'!T$1,FALSE) -> 37.99 | V66: =+J66 -> 203.99 | W66: =+K66 -> 33.99 | X66: =+R66/S66 -> 6.0009806 | Y66: =+S66/U66 -> 1.3421953 | Z66: =+T66/U66 -> 6.0013161 | AA66: =+V66/W66 -> 6.001471 | AB66: =+W66/U66 -> 0.89470913 | AD66: =+R66/F66-1 -> 0 | AE66: =+S66/G66-1 -> 0 | AF66: =+T66/H66-1 -> 0 | AG66: =+U66/I66-1 -> 0 | AH66: =+V66/J66-1 -> 0 | AI66: =+W66/K66-1 -> 0 | AK66: 0.37037036 | AL66: =+R66*$AK66 -> 113.32963 | AM66: =+S66*$AK66 -> 18.885185 | AN66: =+T66*$AK66 -> 84.440738 | AO66: =+U66*$AK66 -> 14.07037 | AP66: =+V66*$AK66 -> 75.55185 | AQ66: =+W66*$AK66 -> 12.588889 | AS66: =+VLOOKUP(B66,'Country & Code Abbreviation'!$B$3:$C$245,2,FALSE) -> DM
B67: Dominican Republic | C67: Latin America | D67: D | E67: =+VLOOKUP($B67,'[3]INT Web'!$B$5:$W$247,'[3]INT Web'!Q$1,FALSE) -> DOP | F67: =+VLOOKUP($B67,'[3]INT Web'!$B$5:$W$247,'[3]INT Web'!R$1,FALSE) -> 7499.99 | G67: =+VLOOKUP($B67,'[3]INT Web'!$B$5:$W$247,'[3]INT Web'!S$1,FALSE) -> 1249.99 | H67: =+VLOOKUP($B67,'[3]INT Web'!$B$5:$W$247,'[3]INT Web'!T$1,FALSE) -> 5219.99 | I67: =+VLOOKUP($B67,'[3]INT Web'!$B$5:$W$247,'[3]INT Web'!U$1,FALSE) -> 869.99 | J67: =+VLOOKUP($B67,'[3]INT Web'!$B$5:$W$247,'[3]INT Web'!V$1,FALSE) -> 4697.99 | K67: =+VLOOKUP($B67,'[3]INT Web'!$B$5:$W$247,'[3]INT Web'!W$1,FALSE) -> 782.99 | L67: =+F67/G67 -> 6.00004 | M67: =+G67/I67 -> 1.4367866 | N67: =+H67/I67 -> 6.0000575 | O67: =+J67/K67 -> 6.0000639 | P67: =+K67/I67 -> 0.89999885 | Q67: =+E67 -> DOP | R67: =+VLOOKUP($B67,'Country-Level Tactics'!$B$5:$AL$248,'Country-Level Tactics'!AH$1,FALSE) -> 7499.99 | S67: =+VLOOKUP($B67,'Country-Level Tactics'!$B$5:$AL$248,'Country-Level Tactics'!X$1,FALSE) -> 1249.99 | T67: =+VLOOKUP($B67,'Country-Level Tactics'!$B$5:$AL$248,'Country-Level Tactics'!AC$1,FALSE) -> 5219.99 | U67: =+VLOOKUP($B67,'Country-Level Tactics'!$B$5:$AL$248,'Country-Level Tactics'!T$1,FALSE) -> 869.99 | V67: =+J67 -> 4697.99 | W67: =+K67 -> 782.99 | X67: =+R67/S67 -> 6.00004 | Y67: =+S67/U67 -> 1.4367866 | Z67: =+T67/U67 -> 6.0000575 | AA67: =+V67/W67 -> 6.0000639 | AB67: =+W67/U67 -> 0.89999885 | AD67: =+R67/F67-1 -> 0 | AE67: =+S67/G67-1 -> 0 | AF67: =+T67/H67-1 -> 0 | AG67: =+U67/I67-1 -> 0 | AH67: =+V67/J67-1 -> 0 | AI67: =+W67/K67-1 -> 0 | AK67: 0.016894747 | AL67: =+R67*$AK67 -> 126.71043 | AM67: =+S67*$AK67 -> 21.118265 | AN67: =+T67*$AK67 -> 88.19041 | AO67: =+U67*$AK67 -> 14.698261 | AP67: =+V67*$AK67 -> 79.371352 | AQ67: =+W67*$AK67 -> 13.228418 | AS67: =+VLOOKUP(B67,'Country & Code Abbreviation'!$B$3:$C$245,2,FALSE) -> DO
B68: Ecuador | C68: Latin America | E68: =+VLOOKUP($B68,'[3]INT Web'!$B$5:$W$247,'[3]INT Web'!Q$1,FALSE) -> USD | F68: =+VLOOKUP($B68,'[3]INT Web'!$B$5:$W$247,'[3]INT Web'!R$1,FALSE) -> 102.99 | G68: =+VLOOKUP($B68,'[3]INT Web'!$B$5:$W$247,'[3]INT Web'!S$1,FALSE) -> 16.99 | H68: =+VLOOKUP($B68,'[3]INT Web'!$B$5:$W$247,'[3]INT Web'!T$1,FALSE) -> 71.99 | I68: =+VLOOKUP($B68,'[3]INT Web'!$B$5:$W$247,'[3]INT Web'!U$1,FALSE) -> 11.99 | J68: =+VLOOKUP($B68,'[3]INT Web'!$B$5:$W$247,'[3]INT Web'!V$1,FALSE) -> 65.99 | K68: =+VLOOKUP($B68,'[3]INT Web'!$B$5:$W$247,'[3]INT Web'!W$1,FALSE) -> 10.99 | L68: =+F68/G68 -> 6.0618011 | M68: =+G68/I68 -> 1.4170142 | N68: =+H68/I68 -> 6.0041701 | O68: =+J68/K68 -> 6.0045496 | P68: =+K68/I68 -> 0.91659716 | Q68: =+E68 -> USD | R68: =+VLOOKUP($B68,'Country-Level Tactics'!$B$5:$AL$248,'Country-Level Tactics'!AH$1,FALSE) -> 102.99 | S68: =+VLOOKUP($B68,'Country-Level Tactics'!$B$5:$AL$248,'Country-Level Tactics'!X$1,FALSE) -> 16.99 | T68: =+VLOOKUP($B68,'Country-Level Tactics'!$B$5:$AL$248,'Country-Level Tactics'!AC$1,FALSE) -> 71.99 | U68: =+VLOOKUP($B68,'Country-Level Tactics'!$B$5:$AL$248,'Country-Level Tactics'!T$1,FALSE) -> 11.99 | V68: =+J68 -> 65.99 | W68: =+K68 -> 10.99 | X68: =+R68/S68 -> 6.0618011 | Y68: =+S68/U68 -> 1.4170142 | Z68: =+T68/U68 -> 6.0041701 | AA68: =+V68/W68 -> 6.0045496 | AB68: =+W68/U68 -> 0.91659716 | AD68: =+R68/F68-1 -> 0 | AE68: =+S68/G68-1 -> 0 | AF68: =+T68/H68-1 -> 0 | AG68: =+U68/I68-1 -> 0 | AH68: =+V68/J68-1 -> 0 | AI68: =+W68/K68-1 -> 0 | AK68: 1 | AL68: =+R68*$AK68 -> 102.99 | AM68: =+S68*$AK68 -> 16.99 | AN68: =+T68*$AK68 -> 71.99 | AO68: =+U68*$AK68 -> 11.99 | AP68: =+V68*$AK68 -> 65.99 | AQ68: =+W68*$AK68 -> 10.99 | AS68: =+VLOOKUP(B68,'Country & Code Abbreviation'!$B$3:$C$245,2,FALSE) -> EC
B69: Egypt | C69: Africa | E69: =+VLOOKUP($B69,'[3]INT Web'!$B$5:$W$247,'[3]INT Web'!Q$1,FALSE) -> EGP | F69: =+VLOOKUP($B69,'[3]INT Web'!$B$5:$W$247,'[3]INT Web'!R$1,FALSE) -> 2359 | G69: =+VLOOKUP($B69,'[3]INT Web'!$B$5:$W$247,'[3]INT Web'!S$1,FALSE) -> 399 | H69: =+VLOOKUP($B69,'[3]INT Web'!$B$5:$W$247,'[3]INT Web'!T$1,FALSE) -> 1569 | I69: =+VLOOKUP($B69,'[3]INT Web'!$B$5:$W$247,'[3]INT Web'!U$1,FALSE) -> 259 | J69: =+VLOOKUP($B69,'[3]INT Web'!$B$5:$W$247,'[3]INT Web'!V$1,FALSE) -> 1419 | K69: =+VLOOKUP($B69,'[3]INT Web'!$B$5:$W$247,'[3]INT Web'!W$1,FALSE) -> 239 | L69: =+F69/G69 -> 5.9122807 | M69: =+G69/I69 -> 1.5405405 | N69: =+H69/I69 -> 6.0579151 | O69: =+J69/K69 -> 5.9372385 | P69: =+K69/I69 -> 0.92277992 | Q69: =+E69 -> EGP | R69: =+VLOOKUP($B69,'Country-Level Tactics'!$B$5:$AL$248,'Country-Level Tactics'!AH$1,FALSE) -> 2359 | S69: =+VLOOKUP($B69,'Country-Level Tactics'!$B$5:$AL$248,'Country-Level Tactics'!X$1,FALSE) -> 399 | T69: =+VLOOKUP($B69,'Country-Level Tactics'!$B$5:$AL$248,'Country-Level Tactics'!AC$1,FALSE) -> 1569 | U69: =+VLOOKUP($B69,'Country-Level Tactics'!$B$5:$AL$248,'Country-Level Tactics'!T$1,FALSE) -> 259 | V69: =+J69 -> 1419 | W69: =+K69 -> 239 | X69: =+R69/S69 -> 5.9122807 | Y69: =+S69/U69 -> 1.5405405 | Z69: =+T69/U69 -> 6.0579151 | AA69: =+V69/W69 -> 5.9372385 | AB69: =+W69/U69 -> 0.92277992 | AD69: =+R69/F69-1 -> 0 | AE69: =+S69/G69-1 -> 0 | AF69: =+T69/H69-1 -> 0 | AG69: =+U69/I69-1 -> 0 | AH69: =+V69/J69-1 -> 0 | AI69: =+W69/K69-1 -> 0 | AK69: 0.020491803 | AL69: =+R69*$AK69 -> 48.340163 | AM69: =+S69*$AK69 -> 8.1762294 | AN69: =+T69*$AK69 -> 32.151639 | AO69: =+U69*$AK69 -> 5.307377 | AP69: =+V69*$AK69 -> 29.077868 | AQ69: =+W69*$AK69 -> 4.8975409 | AS69: =+VLOOKUP(B69,'Country & Code Abbreviation'!$B$3:$C$245,2,FALSE) -> EG
B70: El Salvador | C70: Latin America | E70: =+VLOOKUP($B70,'[3]INT Web'!$B$5:$W$247,'[3]INT Web'!Q$1,FALSE) -> USD | F70: =+VLOOKUP($B70,'[3]INT Web'!$B$5:$W$247,'[3]INT Web'!R$1,FALSE) -> 96.99 | G70: =+VLOOKUP($B70,'[3]INT Web'!$B$5:$W$247,'[3]INT Web'!S$1,FALSE) -> 15.99 | H70: =+VLOOKUP($B70,'[3]INT Web'!$B$5:$W$247,'[3]INT Web'!T$1,FALSE) -> 65.99 | I70: =+VLOOKUP($B70,'[3]INT Web'!$B$5:$W$247,'[3]INT Web'!U$1,FALSE) -> 10.99 | J70: =+VLOOKUP($B70,'[3]INT Web'!$B$5:$W$247,'[3]INT Web'!V$1,FALSE) -> 59.99 | K70: =+VLOOKUP($B70,'[3]INT Web'!$B$5:$W$247,'[3]INT Web'!W$1,FALSE) -> 9.99 | L70: =+F70/G70 -> 6.065666 | M70: =+G70/I70 -> 1.4549591 | N70: =+H70/I70 -> 6.0045496 | O70: =+J70/K70 -> 6.005005 | P70: =+K70/I70 -> 0.90900819 | Q70: =+E70 -> USD | R70: =+VLOOKUP($B70,'Country-Level Tactics'!$B$5:$AL$248,'Country-Level Tactics'!AH$1,FALSE) -> 96.99 | S70: =+VLOOKUP($B70,'Country-Level Tactics'!$B$5:$AL$248,'Country-Level Tactics'!X$1,FALSE) -> 15.99 | T70: =+VLOOKUP($B70,'Country-Level Tactics'!$B$5:$AL$248,'Country-Level Tactics'!AC$1,FALSE) -> 65.99 | U70: =+VLOOKUP($B70,'Country-Level Tactics'!$B$5:$AL$248,'Country-Level Tactics'!T$1,FALSE) -> 10.99 | V70: =+J70 -> 59.99 | W70: =+K70 -> 9.99 | X70: =+R70/S70 -> 6.065666 | Y70: =+S70/U70 -> 1.4549591 | Z70: =+T70/U70 -> 6.0045496 | AA70: =+V70/W70 -> 6.005005 | AB70: =+W70/U70 -> 0.90900819 | AD70: =+R70/F70-1 -> 0 | AE70: =+S70/G70-1 -> 0 | AF70: =+T70/H70-1 -> 0 | AG70: =+U70/I70-1 -> 0 | AH70: =+V70/J70-1 -> 0 | AI70: =+W70/K70-1 -> 0 | AK70: 1 | AL70: =+R70*$AK70 -> 96.99 | AM70: =+S70*$AK70 -> 15.99 | AN70: =+T70*$AK70 -> 65.99 | AO70: =+U70*$AK70 -> 10.99 | AP70: =+V70*$AK70 -> 59.99 | AQ70: =+W70*$AK70 -> 9.99 | AS70: =+VLOOKUP(B70,'Country & Code Abbreviation'!$B$3:$C$245,2,FALSE) -> SV
B71: Equatorial Guinea | C71: Africa | E71: =+VLOOKUP($B71,'[3]INT Web'!$B$5:$W$247,'[3]INT Web'!Q$1,FALSE) -> XAF | F71: =+VLOOKUP($B71,'[3]INT Web'!$B$5:$W$247,'[3]INT Web'!R$1,FALSE) -> 34020 | G71: =+VLOOKUP($B71,'[3]INT Web'!$B$5:$W$247,'[3]INT Web'!S$1,FALSE) -> 5670 | H71: =+VLOOKUP($B71,'[3]INT Web'!$B$5:$W$247,'[3]INT Web'!T$1,FALSE) -> 25200 | I71: =+VLOOKUP($B71,'[3]INT Web'!$B$5:$W$247,'[3]INT Web'!U$1,FALSE) -> 4200 | J71: =+VLOOKUP($B71,'[3]INT Web'!$B$5:$W$247,'[3]INT Web'!V$1,FALSE) -> 22680 | K71: =+VLOOKUP($B71,'[3]INT Web'!$B$5:$W$247,'[3]INT Web'!W$1,FALSE) -> 3780 | L71: =+F71/G71 -> 6 | M71: =+G71/I71 -> 1.35 | N71: =+H71/I71 -> 6 | O71: =+J71/K71 -> 6 | P71: =+K71/I71 -> 0.9 | Q71: =+E71 -> XAF | R71: =+VLOOKUP($B71,'Country-Level Tactics'!$B$5:$AL$248,'Country-Level Tactics'!AH$1,FALSE) -> 34020 | S71: =+VLOOKUP($B71,'Country-Level Tactics'!$B$5:$AL$248,'Country-Level Tactics'!X$1,FALSE) -> 5670 | T71: =+VLOOKUP($B71,'Country-Level Tactics'!$B$5:$AL$248,'Country-Level Tactics'!AC$1,FALSE) -> 25200 | U71: =+VLOOKUP($B71,'Country-Level Tactics'!$B$5:$AL$248,'Country-Level Tactics'!T$1,FALSE) -> 4200 | V71: =+J71 -> 22680 | W71: =+K71 -> 3780 | X71: =+R71/S71 -> 6 | Y71: =+S71/U71 -> 1.35 | Z71: =+T71/U71 -> 6 | AA71: =+V71/W71 -> 6 | AB71: =+W71/U71 -> 0.9 | AD71: =+R71/F71-1 -> 0 | AE71: =+S71/G71-1 -> 0 | AF71: =+T71/H71-1 -> 0 | AG71: =+U71/I71-1 -> 0 | AH71: =+V71/J71-1 -> 0 | AI71: =+W71/K71-1 -> 0 | AK71: 0.0017405867 | AL71: =+R71*$AK71 -> 59.21476 | AM71: =+S71*$AK71 -> 9.8691266 | AN71: =+T71*$AK71 -> 43.862785 | AO71: =+U71*$AK71 -> 7.3104641 | AP71: =+V71*$AK71 -> 39.476506 | AQ71: =+W71*$AK71 -> 6.5794177 | AS71: =+VLOOKUP(B71,'Country & Code Abbreviation'!$B$3:$C$245,2,FALSE) -> GQ
B72: Eritrea | C72: Africa | E72: =+VLOOKUP($B72,'[3]INT Web'!$B$5:$W$247,'[3]INT Web'!Q$1,FALSE) -> USD | F72: =+VLOOKUP($B72,'[3]INT Web'!$B$5:$W$247,'[3]INT Web'!R$1,FALSE) -> 71.99 | G72: =+VLOOKUP($B72,'[3]INT Web'!$B$5:$W$247,'[3]INT Web'!S$1,FALSE) -> 11.99 | H72: =+VLOOKUP($B72,'[3]INT Web'!$B$5:$W$247,'[3]INT Web'!T$1,FALSE) -> 53.99 | I72: =+VLOOKUP($B72,'[3]INT Web'!$B$5:$W$247,'[3]INT Web'!U$1,FALSE) -> 8.99 | J72: =+VLOOKUP($B72,'[3]INT Web'!$B$5:$W$247,'[3]INT Web'!V$1,FALSE) -> 47.99 | K72: =+VLOOKUP($B72,'[3]INT Web'!$B$5:$W$247,'[3]INT Web'!W$1,FALSE) -> 7.99 | L72: =+F72/G72 -> 6.0041701 | M72: =+G72/I72 -> 1.3337041 | N72: =+H72/I72 -> 6.0055617 | O72: =+J72/K72 -> 6.0062578 | P72: =+K72/I72 -> 0.88876529 | Q72: =+E72 -> USD | R72: =+VLOOKUP($B72,'Country-Level Tactics'!$B$5:$AL$248,'Country-Level Tactics'!AH$1,FALSE) -> 71.99 | S72: =+VLOOKUP($B72,'Country-Level Tactics'!$B$5:$AL$248,'Country-Level Tactics'!X$1,FALSE) -> 11.99 | T72: =+VLOOKUP($B72,'Country-Level Tactics'!$B$5:$AL$248,'Country-Level Tactics'!AC$1,FALSE) -> 53.99 | U72: =+VLOOKUP($B72,'Country-Level Tactics'!$B$5:$AL$248,'Country-Level Tactics'!T$1,FALSE) -> 8.99 | V72: =+J72 -> 47.99 | W72: =+K72 -> 7.99 | X72: =+R72/S72 -> 6.0041701 | Y72: =+S72/U72 -> 1.3337041 | Z72: =+T72/U72 -> 6.0055617 | AA72: =+V72/W72 -> 6.0062578 | AB72: =+W72/U72 -> 0.88876529 | AD72: =+R72/F72-1 -> 0 | AE72: =+S72/G72-1 -> 0 | AF72: =+T72/H72-1 -> 0 | AG72: =+U72/I72-1 -> 0 | AH72: =+V72/J72-1 -> 0 | AI72: =+W72/K72-1 -> 0 | AK72: 1 | AL72: =+R72*$AK72 -> 71.99 | AM72: =+S72*$AK72 -> 11.99 | AN72: =+T72*$AK72 -> 53.99 | AO72: =+U72*$AK72 -> 8.99 | AP72: =+V72*$AK72 -> 47.99 | AQ72: =+W72*$AK72 -> 7.99 | AS72: =+VLOOKUP(B72,'Country & Code Abbreviation'!$B$3:$C$245,2,FALSE) -> ER
B73: Estonia | C73: Europe | E73: =+VLOOKUP($B73,'[3]INT Web'!$B$5:$W$247,'[3]INT Web'!Q$1,FALSE) -> EUR | F73: =+VLOOKUP($B73,'[3]INT Web'!$B$5:$W$247,'[3]INT Web'!R$1,FALSE) -> 99.99 | G73: =+VLOOKUP($B73,'[3]INT Web'!$B$5:$W$247,'[3]INT Web'!S$1,FALSE) -> 15.99 | H73: =+VLOOKUP($B73,'[3]INT Web'!$B$5:$W$247,'[3]INT Web'!T$1,FALSE) -> 74.99 | I73: =+VLOOKUP($B73,'[3]INT Web'!$B$5:$W$247,'[3]INT Web'!U$1,FALSE) -> 11.99 | J73: =+VLOOKUP($B73,'[3]INT Web'!$B$5:$W$247,'[3]INT Web'!V$1,FALSE) -> 64.99 | K73: =+VLOOKUP($B73,'[3]INT Web'!$B$5:$W$247,'[3]INT Web'!W$1,FALSE) -> 10.99 | L73: =+F73/G73 -> 6.2532833 | M73: =+G73/I73 -> 1.3336113 | N73: =+H73/I73 -> 6.2543786 | O73: =+J73/K73 -> 5.9135578 | P73: =+K73/I73 -> 0.91659716 | Q73: =+E73 -> EUR | R73: =+VLOOKUP($B73,'Country-Level Tactics'!$B$5:$AL$248,'Country-Level Tactics'!AH$1,FALSE) -> 99.99 | S73: =+VLOOKUP($B73,'Country-Level Tactics'!$B$5:$AL$248,'Country-Level Tactics'!X$1,FALSE) -> 15.99 | T73: =+VLOOKUP($B73,'Country-Level Tactics'!$B$5:$AL$248,'Country-Level Tactics'!AC$1,FALSE) -> 74.99 | U73: =+VLOOKUP($B73,'Country-Level Tactics'!$B$5:$AL$248,'Country-Level Tactics'!T$1,FALSE) -> 11.99 | V73: =+J73 -> 64.99 | W73: =+K73 -> 10.99 | X73: =+R73/S73 -> 6.2532833 | Y73: =+S73/U73 -> 1.3336113 | Z73: =+T73/U73 -> 6.2543786 | AA73: =+V73/W73 -> 5.9135578 | AB73: =+W73/U73 -> 0.91659716 | AD73: =+R73/F73-1 -> 0 | AE73: =+S73/G73-1 -> 0 | AF73: =+T73/H73-1 -> 0 | AG73: =+U73/I73-1 -> 0 | AH73: =+V73/J73-1 -> 0 | AI73: =+W73/K73-1 -> 0 | AK73: 1.14175 | AL73: =+R73*$AK73 -> 114.16358 | AM73: =+S73*$AK73 -> 18.256583 | AN73: =+T73*$AK73 -> 85.619833 | AO73: =+U73*$AK73 -> 13.689583 | AP73: =+V73*$AK73 -> 74.202332 | AQ73: =+W73*$AK73 -> 12.547833 | AS73: =+VLOOKUP(B73,'Country & Code Abbreviation'!$B$3:$C$245,2,FALSE) -> EE
B74: eSwatini | C74: Africa | E74: =+VLOOKUP($B74,'[3]INT Web'!$B$5:$W$247,'[3]INT Web'!Q$1,FALSE) -> SZL | F74: =+VLOOKUP($B74,'[3]INT Web'!$B$5:$W$247,'[3]INT Web'!R$1,FALSE) -> 1295.99 | G74: =+VLOOKUP($B74,'[3]INT Web'!$B$5:$W$247,'[3]INT Web'!S$1,FALSE) -> 215.99 | H74: =+VLOOKUP($B74,'[3]INT Web'!$B$5:$W$247,'[3]INT Web'!T$1,FALSE) -> 959.99 | I74: =+VLOOKUP($B74,'[3]INT Web'!$B$5:$W$247,'[3]INT Web'!U$1,FALSE) -> 159.99 | J74: =+VLOOKUP($B74,'[3]INT Web'!$B$5:$W$247,'[3]INT Web'!V$1,FALSE) -> 863.99 | K74: =+VLOOKUP($B74,'[3]INT Web'!$B$5:$W$247,'[3]INT Web'!W$1,FALSE) -> 143.99 | L74: =+F74/G74 -> 6.0002315 | M74: =+G74/I74 -> 1.3500219 | N74: =+H74/I74 -> 6.0003125 | O74: =+J74/K74 -> 6.0003472 | P74: =+K74/I74 -> 0.89999375 | Q74: =+E74 -> SZL | R74: =+VLOOKUP($B74,'Country-Level Tactics'!$B$5:$AL$248,'Country-Level Tactics'!AH$1,FALSE) -> 1295.99 | S74: =+VLOOKUP($B74,'Country-Level Tactics'!$B$5:$AL$248,'Country-Level Tactics'!X$1,FALSE) -> 215.99 | T74: =+VLOOKUP($B74,'Country-Level Tactics'!$B$5:$AL$248,'Country-Level Tactics'!AC$1,FALSE) -> 959.99 | U74: =+VLOOKUP($B74,'Country-Level Tactics'!$B$5:$AL$248,'Country-Level Tactics'!T$1,FALSE) -> 159.99 | V74: =+J74 -> 863.99 | W74: =+K74 -> 143.99 | X74: =+R74/S74 -> 6.0002315 | Y74: =+S74/U74 -> 1.3500219 | Z74: =+T74/U74 -> 6.0003125 | AA74: =+V74/W74 -> 6.0003472 | AB74: =+W74/U74 -> 0.89999375 | AD74: =+R74/F74-1 -> 0 | AE74: =+S74/G74-1 -> 0 | AF74: =+T74/H74-1 -> 0 | AG74: =+U74/I74-1 -> 0 | AH74: =+V74/J74-1 -> 0 | AI74: =+W74/K74-1 -> 0 | AK74: 0.061533917 | AL74: =+R74*$AK74 -> 79.747341 | AM74: =+S74*$AK74 -> 13.290711 | AN74: =+T74*$AK74 -> 59.071945 | AO74: =+U74*$AK74 -> 9.8448114 | AP74: =+V74*$AK74 -> 53.164689 | AQ74: =+W74*$AK74 -> 8.8602687 | AS74: =+VLOOKUP(B74,'Country & Code Abbreviation'!$B$3:$C$245,2,FALSE) -> SZ
B75: Ethiopia | C75: Africa | E75: =+VLOOKUP($B75,'[3]INT Web'!$B$5:$W$247,'[3]INT Web'!Q$1,FALSE) -> ETB | F75: =+VLOOKUP($B75,'[3]INT Web'!$B$5:$W$247,'[3]INT Web'!R$1,FALSE) -> 2591.99 | G75: =+VLOOKUP($B75,'[3]INT Web'!$B$5:$W$247,'[3]INT Web'!S$1,FALSE) -> 431.99 | H75: =+VLOOKUP($B75,'[3]INT Web'!$B$5:$W$247,'[3]INT Web'!T$1,FALSE) -> 1919.99 | I75: =+VLOOKUP($B75,'[3]INT Web'!$B$5:$W$247,'[3]INT Web'!U$1,FALSE) -> 319.99 | J75: =+VLOOKUP($B75,'[3]INT Web'!$B$5:$W$247,'[3]INT Web'!V$1,FALSE) -> 1727.99 | K75: =+VLOOKUP($B75,'[3]INT Web'!$B$5:$W$247,'[3]INT Web'!W$1,FALSE) -> 287.99 | L75: =+F75/G75 -> 6.0001157 | M75: =+G75/I75 -> 1.3500109 | N75: =+H75/I75 -> 6.0001563 | O75: =+J75/K75 -> 6.0001736 | P75: =+K75/I75 -> 0.89999687 | Q75: =+E75 -> ETB | R75: =+VLOOKUP($B75,'Country-Level Tactics'!$B$5:$AL$248,'Country-Level Tactics'!AH$1,FALSE) -> 2591.99 | S75: =+VLOOKUP($B75,'Country-Level Tactics'!$B$5:$AL$248,'Country-Level Tactics'!X$1,FALSE) -> 431.99 | T75: =+VLOOKUP($B75,'Country-Level Tactics'!$B$5:$AL$248,'Country-Level Tactics'!AC$1,FALSE) -> 1919.99 | U75: =+VLOOKUP($B75,'Country-Level Tactics'!$B$5:$AL$248,'Country-Level Tactics'!T$1,FALSE) -> 319.99 | V75: =+J75 -> 1727.99 | W75: =+K75 -> 287.99 | X75: =+R75/S75 -> 6.0001157 | Y75: =+S75/U75 -> 1.3500109 | Z75: =+T75/U75 -> 6.0001563 | AA75: =+V75/W75 -> 6.0001736 | AB75: =+W75/U75 -> 0.89999687 | AD75: =+R75/F75-1 -> 0 | AE75: =+S75/G75-1 -> 0 | AF75: =+T75/H75-1 -> 0 | AG75: =+U75/I75-1 -> 0 | AH75: =+V75/J75-1 -> 0 | AI75: =+W75/K75-1 -> 0 | AK75: 0.0061946358 | AL75: =+R75*$AK75 -> 16.056434 | AM75: =+S75*$AK75 -> 2.6760207 | AN75: =+T75*$AK75 -> 11.893639 | AO75: =+U75*$AK75 -> 1.9822215 | AP75: =+V75*$AK75 -> 10.704269 | AQ75: =+W75*$AK75 -> 1.7839932 | AS75: =+VLOOKUP(B75,'Country & Code Abbreviation'!$B$3:$C$245,2,FALSE) -> ET
B76: Falkland Islands | C76: Latin America | E76: =+VLOOKUP($B76,'[3]INT Web'!$B$5:$W$247,'[3]INT Web'!Q$1,FALSE) -> FKP | F76: =+VLOOKUP($B76,'[3]INT Web'!$B$5:$W$247,'[3]INT Web'!R$1,FALSE) -> 60 | G76: =+VLOOKUP($B76,'[3]INT Web'!$B$5:$W$247,'[3]INT Web'!S$1,FALSE) -> 10 | H76: =+VLOOKUP($B76,'[3]INT Web'!$B$5:$W$247,'[3]INT Web'!T$1,FALSE) -> 50 | I76: =+VLOOKUP($B76,'[3]INT Web'!$B$5:$W$247,'[3]INT Web'!U$1,FALSE) -> 7 | J76: =+VLOOKUP($B76,'[3]INT Web'!$B$5:$W$247,'[3]INT Web'!V$1,FALSE) -> 40 | K76: =+VLOOKUP($B76,'[3]INT Web'!$B$5:$W$247,'[3]INT Web'!W$1,FALSE) -> 6 | L76: =+F76/G76 -> 6 | M76: =+G76/I76 -> 1.4285714 | N76: =+H76/I76 -> 7.1428571 | O76: =+J76/K76 -> 6.6666667 | P76: =+K76/I76 -> 0.85714286 | Q76: =+E76 -> FKP | R76: =+VLOOKUP($B76,'Country-Level Tactics'!$B$5:$AL$248,'Country-Level Tactics'!AH$1,FALSE) -> 60 | S76: =+VLOOKUP($B76,'Country-Level Tactics'!$B$5:$AL$248,'Country-Level Tactics'!X$1,FALSE) -> 10 | T76: =+VLOOKUP($B76,'Country-Level Tactics'!$B$5:$AL$248,'Country-Level Tactics'!AC$1,FALSE) -> 50 | U76: =+VLOOKUP($B76,'Country-Level Tactics'!$B$5:$AL$248,'Country-Level Tactics'!T$1,FALSE) -> 7 | V76: =+J76 -> 40 | W76: =+K76 -> 6 | X76: =+R76/S76 -> 6 | Y76: =+S76/U76 -> 1.4285714 | Z76: =+T76/U76 -> 7.1428571 | AA76: =+V76/W76 -> 6.6666667 | AB76: =+W76/U76 -> 0.85714286 | AD76: =+R76/F76-1 -> 0 | AE76: =+S76/G76-1 -> 0 | AF76: =+T76/H76-1 -> 0 | AG76: =+U76/I76-1 -> 0 | AH76: =+V76/J76-1 -> 0 | AI76: =+W76/K76-1 -> 0 | AK76: 1.3335 | AL76: =+R76*$AK76 -> 80.01 | AM76: =+S76*$AK76 -> 13.335 | AN76: =+T76*$AK76 -> 66.675 | AO76: =+U76*$AK76 -> 9.3345 | AP76: =+V76*$AK76 -> 53.34 | AQ76: =+W76*$AK76 -> 8.001 | AS76: =+VLOOKUP(B76,'Country & Code Abbreviation'!$B$3:$C$245,2,FALSE) -> FK
B77: Faroe Islands | C77: Europe | E77: =+VLOOKUP($B77,'[3]INT Web'!$B$5:$W$247,'[3]INT Web'!Q$1,FALSE) -> DKK | F77: =+VLOOKUP($B77,'[3]INT Web'!$B$5:$W$247,'[3]INT Web'!R$1,FALSE) -> 1139.99 | G77: =+VLOOKUP($B77,'[3]INT Web'!$B$5:$W$247,'[3]INT Web'!S$1,FALSE) -> 189.99 | H77: =+VLOOKUP($B77,'[3]INT Web'!$B$5:$W$247,'[3]INT Web'!T$1,FALSE) -> 829.99 | I77: =+VLOOKUP($B77,'[3]INT Web'!$B$5:$W$247,'[3]INT Web'!U$1,FALSE) -> 139.99 | J77: =+VLOOKUP($B77,'[3]INT Web'!$B$5:$W$247,'[3]INT Web'!V$1,FALSE) -> 779.99 | K77: =+VLOOKUP($B77,'[3]INT Web'!$B$5:$W$247,'[3]INT Web'!W$1,FALSE) -> 129.99 | L77: =+F77/G77 -> 6.0002632 | M77: =+G77/I77 -> 1.3571684 | N77: =+H77/I77 -> 5.9289235 | O77: =+J77/K77 -> 6.0003846 | P77: =+K77/I77 -> 0.92856633 | Q77: =+E77 -> DKK | R77: =+VLOOKUP($B77,'Country-Level Tactics'!$B$5:$AL$248,'Country-Level Tactics'!AH$1,FALSE) -> 1139.99 | S77: =+VLOOKUP($B77,'Country-Level Tactics'!$B$5:$AL$248,'Country-Level Tactics'!X$1,FALSE) -> 189.99 | T77: =+VLOOKUP($B77,'Country-Level Tactics'!$B$5:$AL$248,'Country-Level Tactics'!AC$1,FALSE) -> 829.99 | U77: =+VLOOKUP($B77,'Country-Level Tactics'!$B$5:$AL$248,'Country-Level Tactics'!T$1,FALSE) -> 139.99 | V77: =+J77 -> 779.99 | W77: =+K77 -> 129.99 | X77: =+R77/S77 -> 6.0002632 | Y77: =+S77/U77 -> 1.3571684 | Z77: =+T77/U77 -> 5.9289235 | AA77: =+V77/W77 -> 6.0003846 | AB77: =+W77/U77 -> 0.92856633 | AD77: =+R77/F77-1 -> 0 | AE77: =+S77/G77-1 -> 0 | AF77: =+T77/H77-1 -> 0 | AG77: =+U77/I77-1 -> 0 | AH77: =+V77/J77-1 -> 0 | AI77: =+W77/K77-1 -> 0 | AK77: 0.15274872 | AL77: =+R77*$AK77 -> 174.13201 | AM77: =+S77*$AK77 -> 29.020729 | AN77: =+T77*$AK77 -> 126.77991 | AO77: =+U77*$AK77 -> 21.383293 | AP77: =+V77*$AK77 -> 119.14247 | AQ77: =+W77*$AK77 -> 19.855806 | AS77: =+VLOOKUP(B77,'Country & Code Abbreviation'!$B$3:$C$245,2,FALSE) -> FO
B78: Fiji | C78: Asia | E78: =+VLOOKUP($B78,'[3]INT Web'!$B$5:$W$247,'[3]INT Web'!Q$1,FALSE) -> FJD | F78: =+VLOOKUP($B78,'[3]INT Web'!$B$5:$W$247,'[3]INT Web'!R$1,FALSE) -> 179.99 | G78: =+VLOOKUP($B78,'[3]INT Web'!$B$5:$W$247,'[3]INT Web'!S$1,FALSE) -> 29.99 | H78: =+VLOOKUP($B78,'[3]INT Web'!$B$5:$W$247,'[3]INT Web'!T$1,FALSE) -> 131.99 | I78: =+VLOOKUP($B78,'[3]INT Web'!$B$5:$W$247,'[3]INT Web'!U$1,FALSE) -> 21.99 | J78: =+VLOOKUP($B78,'[3]INT Web'!$B$5:$W$247,'[3]INT Web'!V$1,FALSE) -> 119.99 | K78: =+VLOOKUP($B78,'[3]INT Web'!$B$5:$W$247,'[3]INT Web'!W$1,FALSE) -> 19.99 | L78: =+F78/G78 -> 6.0016672 | M78: =+G78/I78 -> 1.3638017 | N78: =+H78/I78 -> 6.0022738 | O78: =+J78/K78 -> 6.0025013 | P78: =+K78/I78 -> 0.90904957 | Q78: =+E78 -> FJD | R78: =+VLOOKUP($B78,'Country-Level Tactics'!$B$5:$AL$248,'Country-Level Tactics'!AH$1,FALSE) -> 179.99 | S78: =+VLOOKUP($B78,'Country-Level Tactics'!$B$5:$AL$248,'Country-Level Tactics'!X$1,FALSE) -> 29.99 | T78: =+VLOOKUP($B78,'Country-Level Tactics'!$B$5:$AL$248,'Country-Level Tactics'!AC$1,FALSE) -> 131.99 | U78: =+VLOOKUP($B78,'Country-Level Tactics'!$B$5:$AL$248,'Country-Level Tactics'!T$1,FALSE) -> 21.99 | V78: =+J78 -> 119.99 | W78: =+K78 -> 19.99 | X78: =+R78/S78 -> 6.0016672 | Y78: =+S78/U78 -> 1.3638017 | Z78: =+T78/U78 -> 6.0022738 | AA78: =+V78/W78 -> 6.0025013 | AB78: =+W78/U78 -> 0.90904957 | AD78: =+R78/F78-1 -> 0 | AE78: =+S78/G78-1 -> 0 | AF78: =+T78/H78-1 -> 0 | AG78: =+U78/I78-1 -> 0 | AH78: =+V78/J78-1 -> 0 | AI78: =+W78/K78-1 -> 0 | AK78: 0.44274235 | AL78: =+R78*$AK78 -> 79.689196 | AM78: =+S78*$AK78 -> 13.277843 | AN78: =+T78*$AK78 -> 58.437563 | AO78: =+U78*$AK78 -> 9.7359043 | AP78: =+V78*$AK78 -> 53.124655 | AQ78: =+W78*$AK78 -> 8.8504196 | AS78: =+VLOOKUP(B78,'Country & Code Abbreviation'!$B$3:$C$245,2,FALSE) -> FJ
B79: Finland | C79: Europe | E79: =+VLOOKUP($B79,'[3]INT Web'!$B$5:$W$247,'[3]INT Web'!Q$1,FALSE) -> EUR | F79: =+VLOOKUP($B79,'[3]INT Web'!$B$5:$W$247,'[3]INT Web'!R$1,FALSE) -> 129.99 | G79: =+VLOOKUP($B79,'[3]INT Web'!$B$5:$W$247,'[3]INT Web'!S$1,FALSE) -> 19.99 | H79: =+VLOOKUP($B79,'[3]INT Web'!$B$5:$W$247,'[3]INT Web'!T$1,FALSE) -> 99.99 | I79: =+VLOOKUP($B79,'[3]INT Web'!$B$5:$W$247,'[3]INT Web'!U$1,FALSE) -> 14.99 | J79: =+VLOOKUP($B79,'[3]INT Web'!$B$5:$W$247,'[3]INT Web'!V$1,FALSE) -> 89.99 | K79: =+VLOOKUP($B79,'[3]INT Web'!$B$5:$W$247,'[3]INT Web'!W$1,FALSE) -> 13.99 | L79: =+F79/G79 -> 6.5027514 | M79: =+G79/I79 -> 1.3335557 | N79: =+H79/I79 -> 6.670447 | O79: =+J79/K79 -> 6.4324518 | P79: =+K79/I79 -> 0.93328886 | Q79: =+E79 -> EUR | R79: =+VLOOKUP($B79,'Country-Level Tactics'!$B$5:$AL$248,'Country-Level Tactics'!AH$1,FALSE) -> 129.99 | S79: =+VLOOKUP($B79,'Country-Level Tactics'!$B$5:$AL$248,'Country-Level Tactics'!X$1,FALSE) -> 19.99 | T79: =+VLOOKUP($B79,'Country-Level Tactics'!$B$5:$AL$248,'Country-Level Tactics'!AC$1,FALSE) -> 99.99 | U79: =+VLOOKUP($B79,'Country-Level Tactics'!$B$5:$AL$248,'Country-Level Tactics'!T$1,FALSE) -> 14.99 | V79: =+J79 -> 89.99 | W79: =+K79 -> 13.99 | X79: =+R79/S79 -> 6.5027514 | Y79: =+S79/U79 -> 1.3335557 | Z79: =+T79/U79 -> 6.670447 | AA79: =+V79/W79 -> 6.4324518 | AB79: =+W79/U79 -> 0.93328886 | AD79: =+R79/F79-1 -> 0 | AE79: =+S79/G79-1 -> 0 | AF79: =+T79/H79-1 -> 0 | AG79: =+U79/I79-1 -> 0 | AH79: =+V79/J79-1 -> 0 | AI79: =+W79/K79-1 -> 0 | AK79: 1.14175 | AL79: =+R79*$AK79 -> 148.41608 | AM79: =+S79*$AK79 -> 22.823583 | AN79: =+T79*$AK79 -> 114.16358 | AO79: =+U79*$AK79 -> 17.114833 | AP79: =+V79*$AK79 -> 102.74608 | AQ79: =+W79*$AK79 -> 15.973083 | AS79: =+VLOOKUP(B79,'Country & Code Abbreviation'!$B$3:$C$245,2,FALSE) -> FI
B80: France | C80: Europe | D80: B | E80: =+VLOOKUP($B80,'[3]INT Web'!$B$5:$W$247,'[3]INT Web'!Q$1,FALSE) -> EUR | F80: =+VLOOKUP($B80,'[3]INT Web'!$B$5:$W$247,'[3]INT Web'!R$1,FALSE) -> 199.99 | G80: =+VLOOKUP($B80,'[3]INT Web'!$B$5:$W$247,'[3]INT Web'!S$1,FALSE) -> 28.99 | H80: =+VLOOKUP($B80,'[3]INT Web'!$B$5:$W$247,'[3]INT Web'!T$1,FALSE) -> 146.99 | I80: =+VLOOKUP($B80,'[3]INT Web'!$B$5:$W$247,'[3]INT Web'!U$1,FALSE) -> 21.99 | J80: =+VLOOKUP($B80,'[3]INT Web'!$B$5:$W$247,'[3]INT Web'!V$1,FALSE) -> 134.99 | K80: =+VLOOKUP($B80,'[3]INT Web'!$B$5:$W$247,'[3]INT Web'!W$1,FALSE) -> 19.99 | L80: =+F80/G80 -> 6.8985857 | M80: =+G80/I80 -> 1.3183265 | N80: =+H80/I80 -> 6.684402 | O80: =+J80/K80 -> 6.7528764 | P80: =+K80/I80 -> 0.90904957 | Q80: =+E80 -> EUR | R80: =+VLOOKUP($B80,'Country-Level Tactics'!$B$5:$AL$248,'Country-Level Tactics'!AH$1,FALSE) -> 199.99 | S80: =+VLOOKUP($B80,'Country-Level Tactics'!$B$5:$AL$248,'Country-Level Tactics'!X$1,FALSE) -> 28.99 | T80: =+VLOOKUP($B80,'Country-Level Tactics'!$B$5:$AL$248,'Country-Level Tactics'!AC$1,FALSE) -> 146.99 | U80: =+VLOOKUP($B80,'Country-Level Tactics'!$B$5:$AL$248,'Country-Level Tactics'!T$1,FALSE) -> 21.99 | V80: =+J80 -> 134.99 | W80: =+K80 -> 19.99 | X80: =+R80/S80 -> 6.8985857 | Y80: =+S80/U80 -> 1.3183265 | Z80: =+T80/U80 -> 6.684402 | AA80: =+V80/W80 -> 6.7528764 | AB80: =+W80/U80 -> 0.90904957 | AD80: =+R80/F80-1 -> 0 | AE80: =+S80/G80-1 -> 0 | AF80: =+T80/H80-1 -> 0 | AG80: =+U80/I80-1 -> 0 | AH80: =+V80/J80-1 -> 0 | AI80: =+W80/K80-1 -> 0 | AK80: 1.14175 | AL80: =+R80*$AK80 -> 228.33858 | AM80: =+S80*$AK80 -> 33.099333 | AN80: =+T80*$AK80 -> 167.82583 | AO80: =+U80*$AK80 -> 25.107083 | AP80: =+V80*$AK80 -> 154.12483 | AQ80: =+W80*$AK80 -> 22.823583 | AS80: =+VLOOKUP(B80,'Country & Code Abbreviation'!$B$3:$C$245,2,FALSE) -> FR
B81: French Guiana | C81: Europe | E81: =+VLOOKUP($B81,'[3]INT Web'!$B$5:$W$247,'[3]INT Web'!Q$1,FALSE) -> EUR | F81: =+VLOOKUP($B81,'[3]INT Web'!$B$5:$W$247,'[3]INT Web'!R$1,FALSE) -> 77.99 | G81: =+VLOOKUP($B81,'[3]INT Web'!$B$5:$W$247,'[3]INT Web'!S$1,FALSE) -> 12.99 | H81: =+VLOOKUP($B81,'[3]INT Web'!$B$5:$W$247,'[3]INT Web'!T$1,FALSE) -> 59.99 | I81: =+VLOOKUP($B81,'[3]INT Web'!$B$5:$W$247,'[3]INT Web'!U$1,FALSE) -> 9.99 | J81: =+VLOOKUP($B81,'[3]INT Web'!$B$5:$W$247,'[3]INT Web'!V$1,FALSE) -> 53.99 | K81: =+VLOOKUP($B81,'[3]INT Web'!$B$5:$W$247,'[3]INT Web'!W$1,FALSE) -> 8.99 | L81: =+F81/G81 -> 6.0038491 | M81: =+G81/I81 -> 1.3003003 | N81: =+H81/I81 -> 6.005005 | O81: =+J81/K81 -> 6.0055617 | P81: =+K81/I81 -> 0.8998999 | Q81: =+E81 -> EUR | R81: =+VLOOKUP($B81,'Country-Level Tactics'!$B$5:$AL$248,'Country-Level Tactics'!AH$1,FALSE) -> 77.99 | S81: =+VLOOKUP($B81,'Country-Level Tactics'!$B$5:$AL$248,'Country-Level Tactics'!X$1,FALSE) -> 12.99 | T81: =+VLOOKUP($B81,'Country-Level Tactics'!$B$5:$AL$248,'Country-Level Tactics'!AC$1,FALSE) -> 59.99 | U81: =+VLOOKUP($B81,'Country-Level Tactics'!$B$5:$AL$248,'Country-Level Tactics'!T$1,FALSE) -> 9.99 | V81: =+J81 -> 53.99 | W81: =+K81 -> 8.99 | X81: =+R81/S81 -> 6.0038491 | Y81: =+S81/U81 -> 1.3003003 | Z81: =+T81/U81 -> 6.005005 | AA81: =+V81/W81 -> 6.0055617 | AB81: =+W81/U81 -> 0.8998999 | AD81: =+R81/F81-1 -> 0 | AE81: =+S81/G81-1 -> 0 | AF81: =+T81/H81-1 -> 0 | AG81: =+U81/I81-1 -> 0 | AH81: =+V81/J81-1 -> 0 | AI81: =+W81/K81-1 -> 0 | AK81: 1.14175 | AL81: =+R81*$AK81 -> 89.045082 | AM81: =+S81*$AK81 -> 14.831333 | AN81: =+T81*$AK81 -> 68.493583 | AO81: =+U81*$AK81 -> 11.406083 | AP81: =+V81*$AK81 -> 61.643083 | AQ81: =+W81*$AK81 -> 10.264333 | AS81: =+VLOOKUP(B81,'Country & Code Abbreviation'!$B$3:$C$245,2,FALSE) -> GF
B82: French Polynesia | C82: Asia | E82: =+VLOOKUP($B82,'[3]INT Web'!$B$5:$W$247,'[3]INT Web'!Q$1,FALSE) -> XPF | F82: =+VLOOKUP($B82,'[3]INT Web'!$B$5:$W$247,'[3]INT Web'!R$1,FALSE) -> 8100 | G82: =+VLOOKUP($B82,'[3]INT Web'!$B$5:$W$247,'[3]INT Web'!S$1,FALSE) -> 1350 | H82: =+VLOOKUP($B82,'[3]INT Web'!$B$5:$W$247,'[3]INT Web'!T$1,FALSE) -> 6000 | I82: =+VLOOKUP($B82,'[3]INT Web'!$B$5:$W$247,'[3]INT Web'!U$1,FALSE) -> 1000 | J82: =+VLOOKUP($B82,'[3]INT Web'!$B$5:$W$247,'[3]INT Web'!V$1,FALSE) -> 5400 | K82: =+VLOOKUP($B82,'[3]INT Web'!$B$5:$W$247,'[3]INT Web'!W$1,FALSE) -> 900 | L82: =+F82/G82 -> 6 | M82: =+G82/I82 -> 1.35 | N82: =+H82/I82 -> 6 | O82: =+J82/K82 -> 6 | P82: =+K82/I82 -> 0.9 | Q82: =+E82 -> XPF | R82: =+VLOOKUP($B82,'Country-Level Tactics'!$B$5:$AL$248,'Country-Level Tactics'!AH$1,FALSE) -> 8100 | S82: =+VLOOKUP($B82,'Country-Level Tactics'!$B$5:$AL$248,'Country-Level Tactics'!X$1,FALSE) -> 1350 | T82: =+VLOOKUP($B82,'Country-Level Tactics'!$B$5:$AL$248,'Country-Level Tactics'!AC$1,FALSE) -> 6000 | U82: =+VLOOKUP($B82,'Country-Level Tactics'!$B$5:$AL$248,'Country-Level Tactics'!T$1,FALSE) -> 1000 | V82: =+J82 -> 5400 | W82: =+K82 -> 900 | X82: =+R82/S82 -> 6 | Y82: =+S82/U82 -> 1.35 | Z82: =+T82/U82 -> 6 | AA82: =+V82/W82 -> 6 | AB82: =+W82/U82 -> 0.9 | AD82: =+R82/F82-1 -> 0 | AE82: =+S82/G82-1 -> 0 | AF82: =+T82/H82-1 -> 0 | AG82: =+U82/I82-1 -> 0 | AH82: =+V82/J82-1 -> 0 | AI82: =+W82/K82-1 -> 0 | AK82: 0.009567867 | AL82: =+R82*$AK82 -> 77.499723 | AM82: =+S82*$AK82 -> 12.91662 | AN82: =+T82*$AK82 -> 57.407202 | AO82: =+U82*$AK82 -> 9.567867 | AP82: =+V82*$AK82 -> 51.666482 | AQ82: =+W82*$AK82 -> 8.6110803 | AS82: =+VLOOKUP(B82,'Country & Code Abbreviation'!$B$3:$C$245,2,FALSE) -> PF
B83: French Southern Territories | C83: Europe | E83: =+VLOOKUP($B83,'[3]INT Web'!$B$5:$W$247,'[3]INT Web'!Q$1,FALSE) -> EUR | F83: =+VLOOKUP($B83,'[3]INT Web'!$B$5:$W$247,'[3]INT Web'!R$1,FALSE) -> 119.99 | G83: =+VLOOKUP($B83,'[3]INT Web'!$B$5:$W$247,'[3]INT Web'!S$1,FALSE) -> 19.99 | H83: =+VLOOKUP($B83,'[3]INT Web'!$B$5:$W$247,'[3]INT Web'!T$1,FALSE) -> 89.99 | I83: =+VLOOKUP($B83,'[3]INT Web'!$B$5:$W$247,'[3]INT Web'!U$1,FALSE) -> 14.99 | J83: =+VLOOKUP($B83,'[3]INT Web'!$B$5:$W$247,'[3]INT Web'!V$1,FALSE) -> 79.99 | K83: =+VLOOKUP($B83,'[3]INT Web'!$B$5:$W$247,'[3]INT Web'!W$1,FALSE) -> 12.99 | L83: =+F83/G83 -> 6.0025013 | M83: =+G83/I83 -> 1.3335557 | N83: =+H83/I83 -> 6.0033356 | O83: =+J83/K83 -> 6.1578137 | P83: =+K83/I83 -> 0.86657772 | Q83: =+E83 -> EUR | R83: =+VLOOKUP($B83,'Country-Level Tactics'!$B$5:$AL$248,'Country-Level Tactics'!AH$1,FALSE) -> 119.99 | S83: =+VLOOKUP($B83,'Country-Level Tactics'!$B$5:$AL$248,'Country-Level Tactics'!X$1,FALSE) -> 19.99 | T83: =+VLOOKUP($B83,'Country-Level Tactics'!$B$5:$AL$248,'Country-Level Tactics'!AC$1,FALSE) -> 89.99 | U83: =+VLOOKUP($B83,'Country-Level Tactics'!$B$5:$AL$248,'Country-Level Tactics'!T$1,FALSE) -> 14.99 | V83: =+J83 -> 79.99 | W83: =+K83 -> 12.99 | X83: =+R83/S83 -> 6.0025013 | Y83: =+S83/U83 -> 1.3335557 | Z83: =+T83/U83 -> 6.0033356 | AA83: =+V83/W83 -> 6.1578137 | AB83: =+W83/U83 -> 0.86657772 | AD83: =+R83/F83-1 -> 0 | AE83: =+S83/G83-1 -> 0 | AF83: =+T83/H83-1 -> 0 | AG83: =+U83/I83-1 -> 0 | AH83: =+V83/J83-1 -> 0 | AI83: =+W83/K83-1 -> 0 | AK83: 1.14175 | AL83: =+R83*$AK83 -> 136.99858 | AM83: =+S83*$AK83 -> 22.823583 | AN83: =+T83*$AK83 -> 102.74608 | AO83: =+U83*$AK83 -> 17.114833 | AP83: =+V83*$AK83 -> 91.328582 | AQ83: =+W83*$AK83 -> 14.831333 | AS83: =+VLOOKUP(B83,'Country & Code Abbreviation'!$B$3:$C$245,2,FALSE) -> TF
B84: Gabon | C84: Africa | E84: =+VLOOKUP($B84,'[3]INT Web'!$B$5:$W$247,'[3]INT Web'!Q$1,FALSE) -> XAF | F84: =+VLOOKUP($B84,'[3]INT Web'!$B$5:$W$247,'[3]INT Web'!R$1,FALSE) -> 34020 | G84: =+VLOOKUP($B84,'[3]INT Web'!$B$5:$W$247,'[3]INT Web'!S$1,FALSE) -> 5670 | H84: =+VLOOKUP($B84,'[3]INT Web'!$B$5:$W$247,'[3]INT Web'!T$1,FALSE) -> 25200 | I84: =+VLOOKUP($B84,'[3]INT Web'!$B$5:$W$247,'[3]INT Web'!U$1,FALSE) -> 4200 | J84: =+VLOOKUP($B84,'[3]INT Web'!$B$5:$W$247,'[3]INT Web'!V$1,FALSE) -> 22680 | K84: =+VLOOKUP($B84,'[3]INT Web'!$B$5:$W$247,'[3]INT Web'!W$1,FALSE) -> 3780 | L84: =+F84/G84 -> 6 | M84: =+G84/I84 -> 1.35 | N84: =+H84/I84 -> 6 | O84: =+J84/K84 -> 6 | P84: =+K84/I84 -> 0.9 | Q84: =+E84 -> XAF | R84: =+VLOOKUP($B84,'Country-Level Tactics'!$B$5:$AL$248,'Country-Level Tactics'!AH$1,FALSE) -> 34020 | S84: =+VLOOKUP($B84,'Country-Level Tactics'!$B$5:$AL$248,'Country-Level Tactics'!X$1,FALSE) -> 5670 | T84: =+VLOOKUP($B84,'Country-Level Tactics'!$B$5:$AL$248,'Country-Level Tactics'!AC$1,FALSE) -> 25200 | U84: =+VLOOKUP($B84,'Country-Level Tactics'!$B$5:$AL$248,'Country-Level Tactics'!T$1,FALSE) -> 4200 | V84: =+J84 -> 22680 | W84: =+K84 -> 3780 | X84: =+R84/S84 -> 6 | Y84: =+S84/U84 -> 1.35 | Z84: =+T84/U84 -> 6 | AA84: =+V84/W84 -> 6 | AB84: =+W84/U84 -> 0.9 | AD84: =+R84/F84-1 -> 0 | AE84: =+S84/G84-1 -> 0 | AF84: =+T84/H84-1 -> 0 | AG84: =+U84/I84-1 -> 0 | AH84: =+V84/J84-1 -> 0 | AI84: =+W84/K84-1 -> 0 | AK84: 0.0017405867 | AL84: =+R84*$AK84 -> 59.21476 | AM84: =+S84*$AK84 -> 9.8691266 | AN84: =+T84*$AK84 -> 43.862785 | AO84: =+U84*$AK84 -> 7.3104641 | AP84: =+V84*$AK84 -> 39.476506 | AQ84: =+W84*$AK84 -> 6.5794177 | AS84: =+VLOOKUP(B84,'Country & Code Abbreviation'!$B$3:$C$245,2,FALSE) -> GA
B85: Gambia | C85: Africa | E85: =+VLOOKUP($B85,'[3]INT Web'!$B$5:$W$247,'[3]INT Web'!Q$1,FALSE) -> GMD | F85: =+VLOOKUP($B85,'[3]INT Web'!$B$5:$W$247,'[3]INT Web'!R$1,FALSE) -> 4451.99 | G85: =+VLOOKUP($B85,'[3]INT Web'!$B$5:$W$247,'[3]INT Web'!S$1,FALSE) -> 741.99 | H85: =+VLOOKUP($B85,'[3]INT Web'!$B$5:$W$247,'[3]INT Web'!T$1,FALSE) -> 3299.99 | I85: =+VLOOKUP($B85,'[3]INT Web'!$B$5:$W$247,'[3]INT Web'!U$1,FALSE) -> 549.99 | J85: =+VLOOKUP($B85,'[3]INT Web'!$B$5:$W$247,'[3]INT Web'!V$1,FALSE) -> 2969.99 | K85: =+VLOOKUP($B85,'[3]INT Web'!$B$5:$W$247,'[3]INT Web'!W$1,FALSE) -> 494.99 | L85: =+F85/G85 -> 6.0000674 | M85: =+G85/I85 -> 1.3490973 | N85: =+H85/I85 -> 6.0000909 | O85: =+J85/K85 -> 6.000101 | P85: =+K85/I85 -> 0.89999818 | Q85: =+E85 -> GMD | R85: =+VLOOKUP($B85,'Country-Level Tactics'!$B$5:$AL$248,'Country-Level Tactics'!AH$1,FALSE) -> 4451.99 | S85: =+VLOOKUP($B85,'Country-Level Tactics'!$B$5:$AL$248,'Country-Level Tactics'!X$1,FALSE) -> 741.99 | T85: =+VLOOKUP($B85,'Country-Level Tactics'!$B$5:$AL$248,'Country-Level Tactics'!AC$1,FALSE) -> 3299.99 | U85: =+VLOOKUP($B85,'Country-Level Tactics'!$B$5:$AL$248,'Country-Level Tactics'!T$1,FALSE) -> 549.99 | V85: =+J85 -> 2969.99 | W85: =+K85 -> 494.99 | X85: =+R85/S85 -> 6.0000674 | Y85: =+S85/U85 -> 1.3490973 | Z85: =+T85/U85 -> 6.0000909 | AA85: =+V85/W85 -> 6.000101 | AB85: =+W85/U85 -> 0.89999818 | AD85: =+R85/F85-1 -> 0 | AE85: =+S85/G85-1 -> 0 | AF85: =+T85/H85-1 -> 0 | AG85: =+U85/I85-1 -> 0 | AH85: =+V85/J85-1 -> 0 | AI85: =+W85/K85-1 -> 0 | AK85: 0.013605442 | AL85: =+R85*$AK85 -> 60.571292 | AM85: =+S85*$AK85 -> 10.095102 | AN85: =+T85*$AK85 -> 44.897823 | AO85: =+U85*$AK85 -> 7.482857 | AP85: =+V85*$AK85 -> 40.408027 | AQ85: =+W85*$AK85 -> 6.7345577 | AS85: =+VLOOKUP(B85,'Country & Code Abbreviation'!$B$3:$C$245,2,FALSE) -> GM
B86: Georgia | C86: Middle East | E86: =+VLOOKUP($B86,'[3]INT Web'!$B$5:$W$247,'[3]INT Web'!Q$1,FALSE) -> GEL | F86: =+VLOOKUP($B86,'[3]INT Web'!$B$5:$W$247,'[3]INT Web'!R$1,FALSE) -> 299.99 | G86: =+VLOOKUP($B86,'[3]INT Web'!$B$5:$W$247,'[3]INT Web'!S$1,FALSE) -> 50.99 | H86: =+VLOOKUP($B86,'[3]INT Web'!$B$5:$W$247,'[3]INT Web'!T$1,FALSE) -> 229.99 | I86: =+VLOOKUP($B86,'[3]INT Web'!$B$5:$W$247,'[3]INT Web'!U$1,FALSE) -> 37.99 | J86: =+VLOOKUP($B86,'[3]INT Web'!$B$5:$W$247,'[3]INT Web'!V$1,FALSE) -> 199.99 | K86: =+VLOOKUP($B86,'[3]INT Web'!$B$5:$W$247,'[3]INT Web'!W$1,FALSE) -> 33.99 | L86: =+F86/G86 -> 5.8833105 | M86: =+G86/I86 -> 1.3421953 | N86: =+H86/I86 -> 6.0539616 | O86: =+J86/K86 -> 5.8837893 | P86: =+K86/I86 -> 0.89470913 | Q86: =+E86 -> GEL | R86: =+VLOOKUP($B86,'Country-Level Tactics'!$B$5:$AL$248,'Country-Level Tactics'!AH$1,FALSE) -> 299.99 | S86: =+VLOOKUP($B86,'Country-Level Tactics'!$B$5:$AL$248,'Country-Level Tactics'!X$1,FALSE) -> 50.99 | T86: =+VLOOKUP($B86,'Country-Level Tactics'!$B$5:$AL$248,'Country-Level Tactics'!AC$1,FALSE) -> 229.99 | U86: =+VLOOKUP($B86,'Country-Level Tactics'!$B$5:$AL$248,'Country-Level Tactics'!T$1,FALSE) -> 37.99 | V86: =+J86 -> 199.99 | W86: =+K86 -> 33.99 | X86: =+R86/S86 -> 5.8833105 | Y86: =+S86/U86 -> 1.3421953 | Z86: =+T86/U86 -> 6.0539616 | AA86: =+V86/W86 -> 5.8837893 | AB86: =+W86/U86 -> 0.89470913 | AD86: =+R86/F86-1 -> 0 | AE86: =+S86/G86-1 -> 0 | AF86: =+T86/H86-1 -> 0 | AG86: =+U86/I86-1 -> 0 | AH86: =+V86/J86-1 -> 0 | AI86: =+W86/K86-1 -> 0 | AK86: 0.37979493 | AL86: =+R86*$AK86 -> 113.93468 | AM86: =+S86*$AK86 -> 19.365743 | AN86: =+T86*$AK86 -> 87.349036 | AO86: =+U86*$AK86 -> 14.428409 | AP86: =+V86*$AK86 -> 75.955188 | AQ86: =+W86*$AK86 -> 12.90923 | AS86: =+VLOOKUP(B86,'Country & Code Abbreviation'!$B$3:$C$245,2,FALSE) -> GE
B87: Germany | C87: Europe | D87: B | E87: =+VLOOKUP($B87,'[3]INT Web'!$B$5:$W$247,'[3]INT Web'!Q$1,FALSE) -> EUR | F87: =+VLOOKUP($B87,'[3]INT Web'!$B$5:$W$247,'[3]INT Web'!R$1,FALSE) -> 189.99 | G87: =+VLOOKUP($B87,'[3]INT Web'!$B$5:$W$247,'[3]INT Web'!S$1,FALSE) -> 27.99 | H87: =+VLOOKUP($B87,'[3]INT Web'!$B$5:$W$247,'[3]INT Web'!T$1,FALSE) -> 139.99 | I87: =+VLOOKUP($B87,'[3]INT Web'!$B$5:$W$247,'[3]INT Web'!U$1,FALSE) -> 19.99 | J87: =+VLOOKUP($B87,'[3]INT Web'!$B$5:$W$247,'[3]INT Web'!V$1,FALSE) -> 124.99 | K87: =+VLOOKUP($B87,'[3]INT Web'!$B$5:$W$247,'[3]INT Web'!W$1,FALSE) -> 17.99 | L87: =+F87/G87 -> 6.7877814 | M87: =+G87/I87 -> 1.4002001 | N87: =+H87/I87 -> 7.0030015 | O87: =+J87/K87 -> 6.9477487 | P87: =+K87/I87 -> 0.89994997 | Q87: =+E87 -> EUR | R87: =+VLOOKUP($B87,'Country-Level Tactics'!$B$5:$AL$248,'Country-Level Tactics'!AH$1,FALSE) -> 189.99 | S87: =+VLOOKUP($B87,'Country-Level Tactics'!$B$5:$AL$248,'Country-Level Tactics'!X$1,FALSE) -> 27.99 | T87: =+VLOOKUP($B87,'Country-Level Tactics'!$B$5:$AL$248,'Country-Level Tactics'!AC$1,FALSE) -> 139.99 | U87: =+VLOOKUP($B87,'Country-Level Tactics'!$B$5:$AL$248,'Country-Level Tactics'!T$1,FALSE) -> 19.99 | V87: =+J87 -> 124.99 | W87: =+K87 -> 17.99 | X87: =+R87/S87 -> 6.7877814 | Y87: =+S87/U87 -> 1.4002001 | Z87: =+T87/U87 -> 7.0030015 | AA87: =+V87/W87 -> 6.9477487 | AB87: =+W87/U87 -> 0.89994997 | AD87: =+R87/F87-1 -> 0 | AE87: =+S87/G87-1 -> 0 | AF87: =+T87/H87-1 -> 0 | AG87: =+U87/I87-1 -> 0 | AH87: =+V87/J87-1 -> 0 | AI87: =+W87/K87-1 -> 0 | AK87: 1.14175 | AL87: =+R87*$AK87 -> 216.92108 | AM87: =+S87*$AK87 -> 31.957583 | AN87: =+T87*$AK87 -> 159.83358 | AO87: =+U87*$AK87 -> 22.823583 | AP87: =+V87*$AK87 -> 142.70733 | AQ87: =+W87*$AK87 -> 20.540083 | AS87: =+VLOOKUP(B87,'Country & Code Abbreviation'!$B$3:$C$245,2,FALSE) -> DE
B88: Ghana | C88: Africa | E88: =+VLOOKUP($B88,'[3]INT Web'!$B$5:$W$247,'[3]INT Web'!Q$1,FALSE) -> GHS | F88: =+VLOOKUP($B88,'[3]INT Web'!$B$5:$W$247,'[3]INT Web'!R$1,FALSE) -> 679 | G88: =+VLOOKUP($B88,'[3]INT Web'!$B$5:$W$247,'[3]INT Web'!S$1,FALSE) -> 114 | H88: =+VLOOKUP($B88,'[3]INT Web'!$B$5:$W$247,'[3]INT Web'!T$1,FALSE) -> 479 | I88: =+VLOOKUP($B88,'[3]INT Web'!$B$5:$W$247,'[3]INT Web'!U$1,FALSE) -> 79 | J88: =+VLOOKUP($B88,'[3]INT Web'!$B$5:$W$247,'[3]INT Web'!V$1,FALSE) -> 419 | K88: =+VLOOKUP($B88,'[3]INT Web'!$B$5:$W$247,'[3]INT Web'!W$1,FALSE) -> 69 | L88: =+F88/G88 -> 5.9561404 | M88: =+G88/I88 -> 1.443038 | N88: =+H88/I88 -> 6.0632911 | O88: =+J88/K88 -> 6.0724638 | P88: =+K88/I88 -> 0.87341772 | Q88: =+E88 -> GHS | R88: =+VLOOKUP($B88,'Country-Level Tactics'!$B$5:$AL$248,'Country-Level Tactics'!AH$1,FALSE) -> 679 | S88: =+VLOOKUP($B88,'Country-Level Tactics'!$B$5:$AL$248,'Country-Level Tactics'!X$1,FALSE) -> 114 | T88: =+VLOOKUP($B88,'Country-Level Tactics'!$B$5:$AL$248,'Country-Level Tactics'!AC$1,FALSE) -> 479 | U88: =+VLOOKUP($B88,'Country-Level Tactics'!$B$5:$AL$248,'Country-Level Tactics'!T$1,FALSE) -> 79 | V88: =+J88 -> 419 | W88: =+K88 -> 69 | X88: =+R88/S88 -> 5.9561404 | Y88: =+S88/U88 -> 1.443038 | Z88: =+T88/U88 -> 6.0632911 | AA88: =+V88/W88 -> 6.0724638 | AB88: =+W88/U88 -> 0.87341772 | AD88: =+R88/F88-1 -> 0 | AE88: =+S88/G88-1 -> 0 | AF88: =+T88/H88-1 -> 0 | AG88: =+U88/I88-1 -> 0 | AH88: =+V88/J88-1 -> 0 | AI88: =+W88/K88-1 -> 0 | AK88: 0.0877193 | AL88: =+R88*$AK88 -> 59.561405 | AM88: =+S88*$AK88 -> 10 | AN88: =+T88*$AK88 -> 42.017545 | AO88: =+U88*$AK88 -> 6.9298247 | AP88: =+V88*$AK88 -> 36.754387 | AQ88: =+W88*$AK88 -> 6.0526317 | AS88: =+VLOOKUP(B88,'Country & Code Abbreviation'!$B$3:$C$245,2,FALSE) -> GH
B89: Gibraltar | C89: Europe | E89: =+VLOOKUP($B89,'[3]INT Web'!$B$5:$W$247,'[3]INT Web'!Q$1,FALSE) -> GIP | F89: =+VLOOKUP($B89,'[3]INT Web'!$B$5:$W$247,'[3]INT Web'!R$1,FALSE) -> 124.99 | G89: =+VLOOKUP($B89,'[3]INT Web'!$B$5:$W$247,'[3]INT Web'!S$1,FALSE) -> 17.99 | H89: =+VLOOKUP($B89,'[3]INT Web'!$B$5:$W$247,'[3]INT Web'!T$1,FALSE) -> 79.99 | I89: =+VLOOKUP($B89,'[3]INT Web'!$B$5:$W$247,'[3]INT Web'!U$1,FALSE) -> 12.99 | J89: =+VLOOKUP($B89,'[3]INT Web'!$B$5:$W$247,'[3]INT Web'!V$1,FALSE) -> 69.99 | K89: =+VLOOKUP($B89,'[3]INT Web'!$B$5:$W$247,'[3]INT Web'!W$1,FALSE) -> 11.99 | L89: =+F89/G89 -> 6.9477487 | M89: =+G89/I89 -> 1.3849115 | N89: =+H89/I89 -> 6.1578137 | O89: =+J89/K89 -> 5.8373645 | P89: =+K89/I89 -> 0.92301771 | Q89: =+E89 -> GIP | R89: =+VLOOKUP($B89,'Country-Level Tactics'!$B$5:$AL$248,'Country-Level Tactics'!AH$1,FALSE) -> 124.99 | S89: =+VLOOKUP($B89,'Country-Level Tactics'!$B$5:$AL$248,'Country-Level Tactics'!X$1,FALSE) -> 17.99 | T89: =+VLOOKUP($B89,'Country-Level Tactics'!$B$5:$AL$248,'Country-Level Tactics'!AC$1,FALSE) -> 79.99 | U89: =+VLOOKUP($B89,'Country-Level Tactics'!$B$5:$AL$248,'Country-Level Tactics'!T$1,FALSE) -> 12.99 | V89: =+J89 -> 69.99 | W89: =+K89 -> 11.99 | X89: =+R89/S89 -> 6.9477487 | Y89: =+S89/U89 -> 1.3849115 | Z89: =+T89/U89 -> 6.1578137 | AA89: =+V89/W89 -> 5.8373645 | AB89: =+W89/U89 -> 0.92301771 | AD89: =+R89/F89-1 -> 0 | AE89: =+S89/G89-1 -> 0 | AF89: =+T89/H89-1 -> 0 | AG89: =+U89/I89-1 -> 0 | AH89: =+V89/J89-1 -> 0 | AI89: =+W89/K89-1 -> 0 | AK89: 1.3335 | AL89: =+R89*$AK89 -> 166.67416 | AM89: =+S89*$AK89 -> 23.989665 | AN89: =+T89*$AK89 -> 106.66666 | AO89: =+U89*$AK89 -> 17.322165 | AP89: =+V89*$AK89 -> 93.331665 | AQ89: =+W89*$AK89 -> 15.988665 | AS89: =+VLOOKUP(B89,'Country & Code Abbreviation'!$B$3:$C$245,2,FALSE) -> GI
B90: Greece | C90: Europe | D90: E~ | E90: =+VLOOKUP($B90,'[3]INT Web'!$B$5:$W$247,'[3]INT Web'!Q$1,FALSE) -> EUR | F90: =+VLOOKUP($B90,'[3]INT Web'!$B$5:$W$247,'[3]INT Web'!R$1,FALSE) -> 117.99 | G90: =+VLOOKUP($B90,'[3]INT Web'!$B$5:$W$247,'[3]INT Web'!S$1,FALSE) -> 16.99 | H90: =+VLOOKUP($B90,'[3]INT Web'!$B$5:$W$247,'[3]INT Web'!T$1,FALSE) -> 89.99 | I90: =+VLOOKUP($B90,'[3]INT Web'!$B$5:$W$247,'[3]INT Web'!U$1,FALSE) -> 12.99 | J90: =+VLOOKUP($B90,'[3]INT Web'!$B$5:$W$247,'[3]INT Web'!V$1,FALSE) -> 79.99 | K90: =+VLOOKUP($B90,'[3]INT Web'!$B$5:$W$247,'[3]INT Web'!W$1,FALSE) -> 11.99 | L90: =+F90/G90 -> 6.9446733 | M90: =+G90/I90 -> 1.3079292 | N90: =+H90/I90 -> 6.9276366 | O90: =+J90/K90 -> 6.6713928 | P90: =+K90/I90 -> 0.92301771 | Q90: =+E90 -> EUR | R90: =+VLOOKUP($B90,'Country-Level Tactics'!$B$5:$AL$248,'Country-Level Tactics'!AH$1,FALSE) -> 117.99 | S90: =+VLOOKUP($B90,'Country-Level Tactics'!$B$5:$AL$248,'Country-Level Tactics'!X$1,FALSE) -> 16.99 | T90: =+VLOOKUP($B90,'Country-Level Tactics'!$B$5:$AL$248,'Country-Level Tactics'!AC$1,FALSE) -> 89.99 | U90: =+VLOOKUP($B90,'Country-Level Tactics'!$B$5:$AL$248,'Country-Level Tactics'!T$1,FALSE) -> 12.99 | V90: =+J90 -> 79.99 | W90: =+K90 -> 11.99 | X90: =+R90/S90 -> 6.9446733 | Y90: =+S90/U90 -> 1.3079292 | Z90: =+T90/U90 -> 6.9276366 | AA90: =+V90/W90 -> 6.6713928 | AB90: =+W90/U90 -> 0.92301771 | AD90: =+R90/F90-1 -> 0 | AE90: =+S90/G90-1 -> 0 | AF90: =+T90/H90-1 -> 0 | AG90: =+U90/I90-1 -> 0 | AH90: =+V90/J90-1 -> 0 | AI90: =+W90/K90-1 -> 0 | AK90: 1.14175 | AL90: =+R90*$AK90 -> 134.71508 | AM90: =+S90*$AK90 -> 19.398332 | AN90: =+T90*$AK90 -> 102.74608 | AO90: =+U90*$AK90 -> 14.831333 | AP90: =+V90*$AK90 -> 91.328582 | AQ90: =+W90*$AK90 -> 13.689583 | AS90: =+VLOOKUP(B90,'Country & Code Abbreviation'!$B$3:$C$245,2,FALSE) -> GR
B91: Greenland | C91: Europe | E91: =+VLOOKUP($B91,'[3]INT Web'!$B$5:$W$247,'[3]INT Web'!Q$1,FALSE) -> DKK | F91: =+VLOOKUP($B91,'[3]INT Web'!$B$5:$W$247,'[3]INT Web'!R$1,FALSE) -> 1079.99 | G91: =+VLOOKUP($B91,'[3]INT Web'!$B$5:$W$247,'[3]INT Web'!S$1,FALSE) -> 179.99 | H91: =+VLOOKUP($B91,'[3]INT Web'!$B$5:$W$247,'[3]INT Web'!T$1,FALSE) -> 829.99 | I91: =+VLOOKUP($B91,'[3]INT Web'!$B$5:$W$247,'[3]INT Web'!U$1,FALSE) -> 139.99 | J91: =+VLOOKUP($B91,'[3]INT Web'!$B$5:$W$247,'[3]INT Web'!V$1,FALSE) -> 779.99 | K91: =+VLOOKUP($B91,'[3]INT Web'!$B$5:$W$247,'[3]INT Web'!W$1,FALSE) -> 129.99 | L91: =+F91/G91 -> 6.0002778 | M91: =+G91/I91 -> 1.2857347 | N91: =+H91/I91 -> 5.9289235 | O91: =+J91/K91 -> 6.0003846 | P91: =+K91/I91 -> 0.92856633 | Q91: =+E91 -> DKK | R91: =+VLOOKUP($B91,'Country-Level Tactics'!$B$5:$AL$248,'Country-Level Tactics'!AH$1,FALSE) -> 1079.99 | S91: =+VLOOKUP($B91,'Country-Level Tactics'!$B$5:$AL$248,'Country-Level Tactics'!X$1,FALSE) -> 179.99 | T91: =+VLOOKUP($B91,'Country-Level Tactics'!$B$5:$AL$248,'Country-Level Tactics'!AC$1,FALSE) -> 829.99 | U91: =+VLOOKUP($B91,'Country-Level Tactics'!$B$5:$AL$248,'Country-Level Tactics'!T$1,FALSE) -> 139.99 | V91: =+J91 -> 779.99 | W91: =+K91 -> 129.99 | X91: =+R91/S91 -> 6.0002778 | Y91: =+S91/U91 -> 1.2857347 | Z91: =+T91/U91 -> 5.9289235 | AA91: =+V91/W91 -> 6.0003846 | AB91: =+W91/U91 -> 0.92856633 | AD91: =+R91/F91-1 -> 0 | AE91: =+S91/G91-1 -> 0 | AF91: =+T91/H91-1 -> 0 | AG91: =+U91/I91-1 -> 0 | AH91: =+V91/J91-1 -> 0 | AI91: =+W91/K91-1 -> 0 | AK91: 0.15274872 | AL91: =+R91*$AK91 -> 164.96709 | AM91: =+S91*$AK91 -> 27.493242 | AN91: =+T91*$AK91 -> 126.77991 | AO91: =+U91*$AK91 -> 21.383293 | AP91: =+V91*$AK91 -> 119.14247 | AQ91: =+W91*$AK91 -> 19.855806 | AS91: =+VLOOKUP(B91,'Country & Code Abbreviation'!$B$3:$C$245,2,FALSE) -> GL
